Workbook

Sheet README
A1: OAL Demo Data - Sample Datasets for Power BI
A2: All names and figures are fictional sample data for demos. Amounts are in NGN. Period: Jan 2025 to Oct 2026.
A4: Sheets and the dashboard each one feeds
A5: Sheet | B5: Rows | C5: Feeds dashboard | D5: What it holds
A6: Customers | B6: =COUNTA(Customers!A2:A16) -> 15 | C6: Sales / CRM / Finance | D6: Client list with segment, state, account manager, payment terms
A7: Vendors | B7: =COUNTA(Vendors!A2:A8) -> 7 | C7: Inventory | D7: Suppliers, origin and lead time
A8: Items | B8: =COUNTA(Items!A2:A24) -> 23 | C8: Sales / Inventory | D8: Services and stock items with cost, price, service line, reorder level
A9: Sales | B9: =COUNTA(Sales!A2:A759) -> 758 | C9: Sales | D9: Order lines: revenue, cost, discount, gross profit
A10: Quotes | B10: =COUNTA(Quotes!A2:A361) -> 360 | C10: Customer and Pipeline (CRM) | D10: Quotes by stage, value, probability, weighted value, loss reason
A11: Stages | B11: =COUNTA(Stages!A2:A6) -> 5 | C11: Customer and Pipeline (CRM) | D11: Win probability per pipeline stage
A12: Jobs | B12: =COUNTA(Jobs!A2:A120) -> 119 | C12: Production Tracker | D12: Workshop jobs: status, due vs completion, hours, delivery status
A13: Inventory | B13: =COUNTA(Inventory!A2:A309) -> 308 | C13: Inventory | D13: Monthly stock movement and stock value per stock item
A14: Invoices | B14: =COUNTA(Invoices!A2:A371) -> 370 | C14: Finance | D14: Invoices with due date, payments, balance, ageing bucket
A15: Expenses | B15: =COUNTA(Expenses!A2:A155) -> 154 | C15: Finance | D15: Monthly operating expenses by category and cost centre
A17: Relationships to create in Power BI (many-to-one, single direction)
A18: Sales[CustomerID] -> Customers[CustomerID]
A19: Sales[ItemID] -> Items[ItemID]
A20: Quotes[CustomerID] -> Customers[CustomerID]
A21: Quotes[Stage] -> Stages[Stage]
A22: Jobs[CustomerID] -> Customers[CustomerID]
A23: Jobs[QuoteID] -> Quotes[QuoteID]
A24: Inventory[ItemID] -> Items[ItemID]
A25: Items[VendorID] -> Vendors[VendorID]
A26: Invoices[CustomerID] -> Customers[CustomerID]
A27: Invoices[OrderNo] -> Sales[OrderNo] (optional; OrderNo repeats in Sales, so leave out or use a bridge)
A29: Date table
... A33: Navy header = typed data. Purple header = calculated column (formula). The as-of date on the Settings sheet drives overdue, late and ageing logic.

Sheet Settings
A1: Setting | B1: Value
A2: As-of date (today for status calculations) | B2: 46320
A3: Currency | B3: NGN
A4: Change the as-of date to re-age invoices, jobs and quotes.

Sheet Customers
A1: CustomerID | B1: Customer Name | C1: Segment | D1: State | E1: Account Manager | F1: Payment Terms (Days) | G1: Customer Since
A2: C001 | B2: Delta Crude Services Ltd | C2: Oil & Gas Operator | D2: Delta | E2: Chidi Okafor | F2: 30 | G2: 2019
A3: C002 | B3: Niger Basin Petroleum | C3: Oil & Gas Operator | D3: Rivers | E3: Amaka Eze | F3: 45 | G3: 2018
A4: C003 | B4: Atlantic Offshore Marine | C4: Offshore Services | D4: Lagos | E4: Tunde Bakare | F4: 45 | G4: 2020
A5: C004 | B5: Eko Gas Processing Ltd | C5: Gas Processing | D5: Lagos | E5: Ngozi Udoh | F5: 30 | G5: 2021
A6: C005 | B6: Bonny Terminal Logistics | C6: Midstream | D6: Rivers | E6: Chidi Okafor | F6: 60 | G6: 2019
A7: C006 | B7: Calabar Energy Partners | C7: Oil & Gas Operator | D7: Akwa Ibom | E7: Amaka Eze | F7: 45 | G7: 2022
A8: C007 | B8: Warri Drilling Solutions | C8: Drilling Contractor | D8: Delta | E8: Tunde Bakare | F8: 30 | G8: 2020
A9: C008 | B9: Sapele Pipeline Works | C9: EPC Contractor | D9: Delta | E9: Ngozi Udoh | F9: 60 | G9: 2021
A10: C009 | B10: Harbour Point Engineering | C10: EPC Contractor | D10: Rivers | E10: Chidi Okafor | F10: 45 | G10: 2022
A11: C010 | B11: Okoro & Sons Oilfield Supplies | C11: Trading / Distributor | D11: Rivers | E11: Amaka Eze | F11: 30 | G11: 2023
A12: C011 | B12: Bayelsa Marginal Fields Ltd | C12: Oil & Gas Operator | D12: Bayelsa | E12: Tunde Bakare | F12: 60 | G12: 2023
A13: C012 | B13: Ibom Refining Co | C13: Refinery | D13: Akwa Ibom | E13: Ngozi Udoh | F13: 45 | G13: 2022
... A16: C015 | B16: Apex Wellhead Services | C16: Wellhead Services | D16: Rivers | E16: Tunde Bakare | F16: 30 | G16: 2024

Sheet Vendors
A1: VendorID | B1: Vendor Name | C1: Origin | D1: Lead Time (Days)
A2: V001 | B2: Hi Kalibre (Principal) | C2: Imported | D2: 45
A3: V002 | B3: Lagos Steel & Alloys | C3: Local | D3: 10
A4: V003 | B4: Apapa Industrial Supplies | C4: Local | D4: 7
A5: V004 | B5: Gulf Valve & Fittings | C5: Local | D5: 14
A6: V005 | B6: Weldtech Consumables | C6: Local | D6: 10
A7: V006 | B7: SafeSense Detection Systems | C7: Imported | D7: 60
A8: V007 | B8: Port Harcourt Bearings & Seals | C8: Local | D8: 10

Sheet Items
A1: ItemID | B1: Description | C1: Service Line | D1: Item Type | E1: Brand | F1: UOM | G1: Unit Cost | H1: Unit Price | I1: Reorder Level | J1: VendorID | K1: Margin %
A2: I101 | B2: Hi Kalibre Gate Valve 4" | C2: Spares & Procurement | D2: Stock | E2: Hi Kalibre | F2: Each | G2: 420000 | H2: 560000 | I2: 8 | J2: V001 | K2: =(H2-G2)/H2 -> 0.25
A3: I102 | B3: Hi Kalibre Ball Valve 2" | C3: Spares & Procurement | D3: Stock | E3: Hi Kalibre | F3: Each | G3: 180000 | H3: 250000 | I3: 15 | J3: V001 | K3: =(H3-G3)/H3 -> 0.28
A4: I103 | B4: Hi Kalibre Check Valve 6" | C4: Spares & Procurement | D4: Stock | E4: Hi Kalibre | F4: Each | G4: 610000 | H4: 820000 | I4: 6 | J4: V001 | K4: =(H4-G4)/H4 -> 0.25609756
A5: I104 | B5: Pressure Gauge 0-600 psi | C5: Spares & Procurement | D5: Stock | E5: Generic | F5: Each | G5: 45000 | H5: 68000 | I5: 25 | J5: V004 | K5: =(H5-G5)/H5 -> 0.33823529
A6: I105 | B6: Pipe Flange 6" 150# | C6: Spares & Procurement | D6: Stock | E6: Generic | F6: Each | G6: 95000 | H6: 135000 | I6: 30 | J6: V002 | K6: =(H6-G6)/H6 -> 0.2962963
A7: I106 | B7: Steel Pipe 6" Sch40 (6m) | C7: Spares & Procurement | D7: Stock | E7: Generic | F7: Length | G7: 380000 | H7: 480000 | I7: 20 | J7: V002 | K7: =(H7-G7)/H7 -> 0.20833333
A8: I107 | B8: Stud Bolt Set M20 | C8: Spares & Procurement | D8: Stock | E8: Generic | F8: Set | G8: 28000 | H8: 42000 | I8: 50 | J8: V003 | K8: =(H8-G8)/H8 -> 0.33333333
A9: I108 | B9: Gasket Kit (Spiral Wound) | C9: Spares & Procurement | D9: Stock | E9: Generic | F9: Kit | G9: 35000 | H9: 55000 | I9: 40 | J9: V003 | K9: =(H9-G9)/H9 -> 0.36363636
A10: I109 | B10: Hydraulic Hose Assembly | C10: Spares & Procurement | D10: Stock | E10: Generic | F10: Each | G10: 85000 | H10: 125000 | I10: 20 | J10: V003 | K10: =(H10-G10)/H10 -> 0.32
A11: I110 | B11: Heavy Duty Bearing Set | C11: Spares & Procurement | D11: Stock | E11: Generic | F11: Set | G11: 120000 | H11: 175000 | I11: 15 | J11: V007 | K11: =(H11-G11)/H11 -> 0.31428571
A12: I111 | B12: Welding Electrodes Box (E7018) | C12: Spares & Procurement | D12: Stock | E12: Generic | F12: Box | G12: 22000 | H12: 32000 | I12: 60 | J12: V005 | K12: =(H12-G12)/H12 -> 0.3125
A13: I112 | B13: Carbide Cutting Inserts Box | C13: Spares & Procurement | D13: Stock | E13: Generic | F13: Box | G13: 65000 | H13: 95000 | I13: 25 | J13: V005 | K13: =(H13-G13)/H13 -> 0.31578947
... A15: I114 | B15: Flame Detector UV/IR | C15: Fire & Gas | D15: Stock | E15: Generic | F15: Each | G15: 1100000 | H15: 1450000 | I15: 4 | J15: V006 | K15: =(H15-G15)/H15 -> 0.24137931
A16: I201 | B16: CNC Machining (per hour) | C16: Machining | D16: Service | E16: OAL Service | F16: Hour | G16: 28000 | H16: 45000 | K16: =(H16-G16)/H16 -> 0.37777778
A17: I202 | B17: Precision Turning Job | C17: Machining | D17: Service | E17: OAL Service | F17: Each | G17: 150000 | H17: 240000 | K17: =(H17-G17)/H17 -> 0.375
A18: I203 | B18: Pipe Thread Repair (per joint) | C18: Pipe Thread Repair | D18: Service | E18: OAL Service | F18: Joint | G18: 55000 | H18: 85000 | K18: =(H18-G18)/H18 -> 0.35294118
A19: I204 | B19: Tubing Thread Re-cut (per joint) | C19: Pipe Thread Repair | D19: Service | E19: OAL Service | F19: Joint | G19: 38000 | H19: 62000 | K19: =(H19-G19)/H19 -> 0.38709677
A20: I205 | B20: Fabrication - Skid Frame | C20: Fabrication | D20: Service | E20: OAL Service | F20: Each | G20: 2200000 | H20: 3500000 | K20: =(H20-G20)/H20 -> 0.37142857
A21: I206 | B21: Fabrication - Pressure Vessel | C21: Fabrication | D21: Service | E21: OAL Service | F21: Each | G21: 7800000 | H21: 12000000 | K21: =(H21-G21)/H21 -> 0.35
A22: I207 | B22: Pigging Service (per run) | C22: Pigging | D22: Service | E22: OAL Service | F22: Run | G22: 1700000 | H22: 2800000 | K22: =(H22-G22)/H22 -> 0.39285714
A23: I208 | B23: Epoxy Coating (per m2) | C23: Coating | D23: Service | E23: OAL Service | F23: m2 | G23: 11000 | H23: 18000 | K23: =(H23-G23)/H23 -> 0.38888889
A24: I209 | B24: Fire & Gas Detector Installation | C24: Fire & Gas | D24: Service | E24: OAL Service | F24: Each | G24: 400000 | H24: 650000 | K24: =(H24-G24)/H24 -> 0.38461538

Sheet Sales
A1: LineID | B1: OrderNo | C1: Order Date | D1: CustomerID | E1: Salesperson | F1: ItemID | G1: Service Line | H1: Quantity | I1: Unit Price | J1: Unit Cost | K1: Discount % | L1: Revenue | M1: Cost | N1: Gross Profit
A2: L00001 | B2: SO-2025-0001 | C2: 45662 | D2: C003 | E2: Tunde Bakare | F2: I205 | G2: =VLOOKUP(F2,Items!$A$2:$C$24,3,FALSE()) -> Fabrication | H2: 3 | I2: 3574300 | J2: 2209600 | K2: 0.02 | L2: =H2*I2*(1-K2) -> 10508442 | M2: =H2*J2 -> 6628800 | N2: =L2-M2 -> 3879642
A3: L00002 | B3: SO-2025-0001 | C3: 45662 | D3: C003 | E3: Tunde Bakare | F3: I104 | G3: =VLOOKUP(F3,Items!$A$2:$C$24,3,FALSE()) -> Spares & Procurement | H3: 17 | I3: 70800 | J3: 45700 | K3: 0 | L3: =H3*I3*(1-K3) -> 1203600 | M3: =H3*J3 -> 776900 | N3: =L3-M3 -> 426700
A4: L00003 | B4: SO-2025-0001 | C4: 45662 | D4: C003 | E4: Tunde Bakare | F4: I201 | G4: =VLOOKUP(F4,Items!$A$2:$C$24,3,FALSE()) -> Machining | H4: 282 | I4: 46900 | J4: 29100 | K4: 0 | L4: =H4*I4*(1-K4) -> 13225800 | M4: =H4*J4 -> 8206200 | N4: =L4-M4 -> 5019600
A5: L00004 | B5: SO-2025-0001 | C5: 45662 | D5: C003 | E5: Tunde Bakare | F5: I206 | G5: =VLOOKUP(F5,Items!$A$2:$C$24,3,FALSE()) -> Fabrication | H5: 2 | I5: 11740900 | J5: 8089500 | K5: 0 | L5: =H5*I5*(1-K5) -> 23481800 | M5: =H5*J5 -> 16179000 | N5: =L5-M5 -> 7302800
A6: L00005 | B6: SO-2025-0002 | C6: 45664 | D6: C002 | E6: Amaka Eze | F6: I101 | G6: =VLOOKUP(F6,Items!$A$2:$C$24,3,FALSE()) -> Spares & Procurement | H6: 2 | I6: 592800 | J6: 427000 | K6: 0.02 | L6: =H6*I6*(1-K6) -> 1161888 | M6: =H6*J6 -> 854000 | N6: =L6-M6 -> 307888
A7: L00006 | B7: SO-2025-0002 | C7: 45664 | D7: C002 | E7: Amaka Eze | F7: I201 | G7: =VLOOKUP(F7,Items!$A$2:$C$24,3,FALSE()) -> Machining | H7: 236 | I7: 45700 | J7: 27800 | K7: 0 | L7: =H7*I7*(1-K7) -> 10785200 | M7: =H7*J7 -> 6560800 | N7: =L7-M7 -> 4224400
A8: L00007 | B8: SO-2025-0002 | C8: 45664 | D8: C002 | E8: Amaka Eze | F8: I102 | G8: =VLOOKUP(F8,Items!$A$2:$C$24,3,FALSE()) -> Spares & Procurement | H8: 8 | I8: 247400 | J8: 185100 | K8: 0 | L8: =H8*I8*(1-K8) -> 1979200 | M8: =H8*J8 -> 1480800 | N8: =L8-M8 -> 498400
A9: L00008 | B9: SO-2025-0003 | C9: 45667 | D9: C004 | E9: Ngozi Udoh | F9: I113 | G9: =VLOOKUP(F9,Items!$A$2:$C$24,3,FALSE()) -> Fire & Gas | H9: 8 | I9: 707000 | J9: 524100 | K9: 0 | L9: =H9*I9*(1-K9) -> 5656000 | M9: =H9*J9 -> 4192800 | N9: =L9-M9 -> 1463200
A10: L00009 | B10: SO-2025-0003 | C10: 45667 | D10: C004 | E10: Ngozi Udoh | F10: I206 | G10: =VLOOKUP(F10,Items!$A$2:$C$24,3,FALSE()) -> Fabrication | H10: 2 | I10: 12301700 | J10: 7980600 | K10: 0 | L10: =H10*I10*(1-K10) -> 24603400 | M10: =H10*J10 -> 15961200 | N10: =L10-M10 -> 8642200
A11: L00010 | B11: SO-2025-0004 | C11: 45667 | D11: C009 | E11: Chidi Okafor | F11: I207 | G11: =VLOOKUP(F11,Items!$A$2:$C$24,3,FALSE()) -> Pigging | H11: 2 | I11: 2781300 | J11: 1691200 | K11: 0 | L11: =H11*I11*(1-K11) -> 5562600 | M11: =H11*J11 -> 3382400 | N11: =L11-M11 -> 2180200
A12: L00011 | B12: SO-2025-0004 | C12: 45667 | D12: C009 | E12: Chidi Okafor | F12: I204 | G12: =VLOOKUP(F12,Items!$A$2:$C$24,3,FALSE()) -> Pipe Thread Repair | H12: 180 | I12: 61500 | J12: 38200 | K12: 0 | L12: =H12*I12*(1-K12) -> 11070000 | M12: =H12*J12 -> 6876000 | N12: =L12-M12 -> 4194000
A13: L00012 | B13: SO-2025-0005 | C13: 45667 | D13: C002 | E13: Amaka Eze | F13: I207 | G13: =VLOOKUP(F13,Items!$A$2:$C$24,3,FALSE()) -> Pigging | H13: 1 | I13: 2754000 | J13: 1705100 | K13: 0 | L13: =H13*I13*(1-K13) -> 2754000 | M13: =H13*J13 -> 1705100 | N13: =L13-M13 -> 1048900
... A759: L00758 | B759: SO-2026-0380 | C759: 46319 | D759: C006 | E759: Amaka Eze | F759: I103 | G759: =VLOOKUP(F759,Items!$A$2:$C$24,3,FALSE()) -> Spares & Procurement | H759: 4 | I759: 832100 | J759: 603600 | K759: 0.05 | L759: =H759*I759*(1-K759) -> 3161980 | M759: =H759*J759 -> 2414400 | N759: =L759-M759 -> 747580

Sheet Quotes
A1: QuoteID | B1: Quote Date | C1: CustomerID | D1: Salesperson | E1: Service Line | F1: Description | G1: Stage | H1: Quote Value | I1: Probability | J1: Weighted Value | K1: Close Date (Actual or Expected) | L1: Loss Reason | M1: Age (Days)
A2: Q0001 | B2: 45660 | C2: C001 | D2: Chidi Okafor | E2: Fabrication | F2: Wellhead skid fabrication | G2: Won | H2: 1516000 | I2: =VLOOKUP(G2,Stages!$A$2:$B$6,2,FALSE()) -> 1 | J2: =H2*I2 -> 1516000 | K2: 45693 | M2: =IF(OR(G2="Won",G2="Lost"),K2-B2,Settings!$B$2-B2) -> 33
A3: Q0002 | B3: 45661 | C3: C004 | D3: Ngozi Udoh | E3: Fabrication | F3: Manifold fabrication | G3: Won | H3: 2235000 | I3: =VLOOKUP(G3,Stages!$A$2:$B$6,2,FALSE()) -> 1 | J3: =H3*I3 -> 2235000 | K3: 45720 | M3: =IF(OR(G3="Won",G3="Lost"),K3-B3,Settings!$B$2-B3) -> 59
A4: Q0003 | B4: 45663 | C4: C003 | D4: Tunde Bakare | E4: Spares & Procurement | F4: Spares package - rotating equipment | G4: Won | H4: 2029000 | I4: =VLOOKUP(G4,Stages!$A$2:$B$6,2,FALSE()) -> 1 | J4: =H4*I4 -> 2029000 | K4: 45726 | M4: =IF(OR(G4="Won",G4="Lost"),K4-B4,Settings!$B$2-B4) -> 63
A5: Q0004 | B5: 45664 | C5: C008 | D5: Ngozi Udoh | E5: Pigging | F5: Pipeline pigging run | G5: Lost | H5: 14683000 | I5: =VLOOKUP(G5,Stages!$A$2:$B$6,2,FALSE()) -> 0 | J5: =H5*I5 -> 0 | K5: 45725 | L5: Lead time too long | M5: =IF(OR(G5="Won",G5="Lost"),K5-B5,Settings!$B$2-B5) -> 61
A6: Q0005 | B6: 45667 | C6: C004 | D6: Ngozi Udoh | E6: Machining | F6: Custom flange machining | G6: Quoted | H6: 17124000 | I6: =VLOOKUP(G6,Stages!$A$2:$B$6,2,FALSE()) -> 0.3 | J6: =H6*I6 -> 5137200 | K6: 45716 | M6: =IF(OR(G6="Won",G6="Lost"),K6-B6,Settings!$B$2-B6) -> 653
A7: Q0006 | B7: 45674 | C7: C001 | D7: Chidi Okafor | E7: Pipe Thread Repair | F7: Casing thread inspection and repair | G7: Negotiation | H7: 16101000 | I7: =VLOOKUP(G7,Stages!$A$2:$B$6,2,FALSE()) -> 0.6 | J7: =H7*I7 -> 9660600 | K7: 45715 | M7: =IF(OR(G7="Won",G7="Lost"),K7-B7,Settings!$B$2-B7) -> 646
A8: Q0007 | B8: 45674 | C8: C001 | D8: Chidi Okafor | E8: Spares & Procurement | F8: Consumables supply | G8: Won | H8: 9271000 | I8: =VLOOKUP(G8,Stages!$A$2:$B$6,2,FALSE()) -> 1 | J8: =H8*I8 -> 9271000 | K8: 45698 | M8: =IF(OR(G8="Won",G8="Lost"),K8-B8,Settings!$B$2-B8) -> 24
A9: Q0008 | B9: 45677 | C9: C001 | D9: Chidi Okafor | E9: Machining | F9: Pump shaft re-machining | G9: Won | H9: 19080000 | I9: =VLOOKUP(G9,Stages!$A$2:$B$6,2,FALSE()) -> 1 | J9: =H9*I9 -> 19080000 | K9: 45691 | M9: =IF(OR(G9="Won",G9="Lost"),K9-B9,Settings!$B$2-B9) -> 14
A10: Q0009 | B10: 45678 | C10: C008 | D10: Ngozi Udoh | E10: Spares & Procurement | F10: Consumables supply | G10: Won | H10: 4986000 | I10: =VLOOKUP(G10,Stages!$A$2:$B$6,2,FALSE()) -> 1 | J10: =H10*I10 -> 4986000 | K10: 45695 | M10: =IF(OR(G10="Won",G10="Lost"),K10-B10,Settings!$B$2-B10) -> 17
A11: Q0010 | B11: 45678 | C11: C001 | D11: Chidi Okafor | E11: Fabrication | F11: Pressure vessel fabrication | G11: Won | H11: 7139000 | I11: =VLOOKUP(G11,Stages!$A$2:$B$6,2,FALSE()) -> 1 | J11: =H11*I11 -> 7139000 | K11: 45700 | M11: =IF(OR(G11="Won",G11="Lost"),K11-B11,Settings!$B$2-B11) -> 22
A12: Q0011 | B12: 45682 | C12: C006 | D12: Amaka Eze | E12: Machining | F12: Custom flange machining | G12: Won | H12: 8253000 | I12: =VLOOKUP(G12,Stages!$A$2:$B$6,2,FALSE()) -> 1 | J12: =H12*I12 -> 8253000 | K12: 45729 | M12: =IF(OR(G12="Won",G12="Lost"),K12-B12,Settings!$B$2-B12) -> 47
A13: Q0012 | B13: 45682 | C13: C003 | D13: Tunde Bakare | E13: Spares & Procurement | F13: Valve and fittings supply | G13: Quoted | H13: 6936000 | I13: =VLOOKUP(G13,Stages!$A$2:$B$6,2,FALSE()) -> 0.3 | J13: =H13*I13 -> 2080800 | K13: 45716 | M13: =IF(OR(G13="Won",G13="Lost"),K13-B13,Settings!$B$2-B13) -> 638
A14: Q0013 | B14: 45682 | C14: C009 | D14: Chidi Okafor | E14: Spares & Procurement | F14: Valve and fittings supply | G14: Lost | H14: 621000 | I14: =VLOOKUP(G14,Stages!$A$2:$B$6,2,FALSE()) -> 0 | J14: =H14*I14 -> 0 | K14: 45692 | L14: Lost to competitor | M14: =IF(OR(G14="Won",G14="Lost"),K14-B14,Settings!$B$2-B14) -> 10
A15: Q0014 | B15: 45687 | C15: C012 | D15: Ngozi Udoh | E15: Spares & Procurement | F15: Valve and fittings supply | G15: Lost | H15: 7099000 | I15: =VLOOKUP(G15,Stages!$A$2:$B$6,2,FALSE()) -> 0 | J15: =H15*I15 -> 0 | K15: 45740 | L15: Lost to competitor | M15: =IF(OR(G15="Won",G15="Lost"),K15-B15,Settings!$B$2-B15) -> 53
A16: Q0015 | B16: 45692 | C16: C001 | D16: Chidi Okafor | E16: Machining | F16: Pump shaft re-machining | G16: Won | H16: 19220000 | I16: =VLOOKUP(G16,Stages!$A$2:$B$6,2,FALSE()) -> 1 | J16: =H16*I16 -> 19220000 | K16: 45737 | M16: =IF(OR(G16="Won",G16="Lost"),K16-B16,Settings!$B$2-B16) -> 45
A17: Q0016 | B17: 45695 | C17: C001 | D17: Chidi Okafor | E17: Pipe Thread Repair | F17: Premium connection repair | G17: Won | H17: 3791000 | I17: =VLOOKUP(G17,Stages!$A$2:$B$6,2,FALSE()) -> 1 | J17: =H17*I17 -> 3791000 | K17: 45748 | M17: =IF(OR(G17="Won",G17="Lost"),K17-B17,Settings!$B$2-B17) -> 53
A18: Q0017 | B18: 45696 | C18: C002 | D18: Amaka Eze | E18: Pipe Thread Repair | F18: Premium connection repair | G18: Negotiation | H18: 2243000 | I18: =VLOOKUP(G18,Stages!$A$2:$B$6,2,FALSE()) -> 0.6 | J18: =H18*I18 -> 1345800 | K18: 45783 | M18: =IF(OR(G18="Won",G18="Lost"),K18-B18,Settings!$B$2-B18) -> 624
A19: Q0018 | B19: 45699 | C19: C012 | D19: Ngozi Udoh | E19: Fabrication | F19: Manifold fabrication | G19: Won | H19: 11073000 | I19: =VLOOKUP(G19,Stages!$A$2:$B$6,2,FALSE()) -> 1 | J19: =H19*I19 -> 11073000 | K19: 45734 | M19: =IF(OR(G19="Won",G19="Lost"),K19-B19,Settings!$B$2-B19) -> 35
A20: Q0019 | B20: 45700 | C20: C004 | D20: Ngozi Udoh | E20: Fire & Gas | F20: Flame detector replacement | G20: Won | H20: 2863000 | I20: =VLOOKUP(G20,Stages!$A$2:$B$6,2,FALSE()) -> 1 | J20: =H20*I20 -> 2863000 | K20: 45716 | M20: =IF(OR(G20="Won",G20="Lost"),K20-B20,Settings!$B$2-B20) -> 16
A21: Q0020 | B21: 45701 | C21: C012 | D21: Ngozi Udoh | E21: Spares & Procurement | F21: Flanges and pipe supply | G21: Won | H21: 14789000 | I21: =VLOOKUP(G21,Stages!$A$2:$B$6,2,FALSE()) -> 1 | J21: =H21*I21 -> 14789000 | K21: 45749 | M21: =IF(OR(G21="Won",G21="Lost"),K21-B21,Settings!$B$2-B21) -> 48
A22: Q0021 | B22: 45702 | C22: C001 | D22: Chidi Okafor | E22: Spares & Procurement | F22: Consumables supply | G22: Lost | H22: 1478000 | I22: =VLOOKUP(G22,Stages!$A$2:$B$6,2,FALSE()) -> 0 | J22: =H22*I22 -> 0 | K22: 45749 | L22: Lead time too long | M22: =IF(OR(G22="Won",G22="Lost"),K22-B22,Settings!$B$2-B22) -> 47
A23: Q0022 | B23: 45702 | C23: C003 | D23: Tunde Bakare | E23: Fire & Gas | F23: Fire and gas panel commissioning | G23: Negotiation | H23: 1797000 | I23: =VLOOKUP(G23,Stages!$A$2:$B$6,2,FALSE()) -> 0.6 | J23: =H23*I23 -> 1078200 | K23: 45739 | M23: =IF(OR(G23="Won",G23="Lost"),K23-B23,Settings!$B$2-B23) -> 618
A24: Q0023 | B24: 45705 | C24: C004 | D24: Ngozi Udoh | E24: Fabrication | F24: Pressure vessel fabrication | G24: Negotiation | H24: 13473000 | I24: =VLOOKUP(G24,Stages!$A$2:$B$6,2,FALSE()) -> 0.6 | J24: =H24*I24 -> 8083800 | K24: 45736 | M24: =IF(OR(G24="Won",G24="Lost"),K24-B24,Settings!$B$2-B24) -> 615
A25: Q0024 | B25: 45713 | C25: C003 | D25: Tunde Bakare | E25: Fire & Gas | F25: Flame detector replacement | G25: Won | H25: 6007000 | I25: =VLOOKUP(G25,Stages!$A$2:$B$6,2,FALSE()) -> 1 | J25: =H25*I25 -> 6007000 | K25: 45727 | M25: =IF(OR(G25="Won",G25="Lost"),K25-B25,Settings!$B$2-B25) -> 14
A26: Q0025 | B26: 45715 | C26: C008 | D26: Ngozi Udoh | E26: Spares & Procurement | F26: Consumables supply | G26: Quoted | H26: 1249000 | I26: =VLOOKUP(G26,Stages!$A$2:$B$6,2,FALSE()) -> 0.3 | J26: =H26*I26 -> 374700 | K26: 45776 | M26: =IF(OR(G26="Won",G26="Lost"),K26-B26,Settings!$B$2-B26) -> 605
A27: Q0026 | B27: 45717 | C27: C008 | D27: Ngozi Udoh | E27: Spares & Procurement | F27: Flanges and pipe supply | G27: Quoted | H27: 1674000 | I27: =VLOOKUP(G27,Stages!$A$2:$B$6,2,FALSE()) -> 0.3 | J27: =H27*I27 -> 502200 | K27: 45801 | M27: =IF(OR(G27="Won",G27="Lost"),K27-B27,Settings!$B$2-B27) -> 603
A28: Q0027 | B28: 45727 | C28: C003 | D28: Tunde Bakare | E28: Machining | F28: Valve body CNC machining | G28: Won | H28: 14881000 | I28: =VLOOKUP(G28,Stages!$A$2:$B$6,2,FALSE()) -> 1 | J28: =H28*I28 -> 14881000 | K28: 45793 | M28: =IF(OR(G28="Won",G28="Lost"),K28-B28,Settings!$B$2-B28) -> 66
A29: Q0028 | B29: 45734 | C29: C004 | D29: Ngozi Udoh | E29: Machining | F29: Wellhead component turning | G29: Lost | H29: 4772000 | I29: =VLOOKUP(G29,Stages!$A$2:$B$6,2,FALSE()) -> 0 | J29: =H29*I29 -> 0 | K29: 45787 | L29: No response from client | M29: =IF(OR(G29="Won",G29="Lost"),K29-B29,Settings!$B$2-B29) -> 53
A30: Q0029 | B30: 45734 | C30: C006 | D30: Amaka Eze | E30: Coating | F30: Pipe external coating | G30: Lost | H30: 14784000 | I30: =VLOOKUP(G30,Stages!$A$2:$B$6,2,FALSE()) -> 0 | J30: =H30*I30 -> 0 | K30: 45769 | L30: Lead time too long | M30: =IF(OR(G30="Won",G30="Lost"),K30-B30,Settings!$B$2-B30) -> 35
A31: Q0030 | B31: 45734 | C31: C005 | D31: Chidi Okafor | E31: Fabrication | F31: Wellhead skid fabrication | G31: Lost | H31: 8666000 | I31: =VLOOKUP(G31,Stages!$A$2:$B$6,2,FALSE()) -> 0 | J31: =H31*I31 -> 0 | K31: 45747 | L31: No response from client | M31: =IF(OR(G31="Won",G31="Lost"),K31-B31,Settings!$B$2-B31) -> 13
A32: Q0031 | B32: 45742 | C32: C001 | D32: Chidi Okafor | E32: Spares & Procurement | F32: Flanges and pipe supply | G32: Won | H32: 12204000 | I32: =VLOOKUP(G32,Stages!$A$2:$B$6,2,FALSE()) -> 1 | J32: =H32*I32 -> 12204000 | K32: 45758 | M32: =IF(OR(G32="Won",G32="Lost"),K32-B32,Settings!$B$2-B32) -> 16
A33: Q0032 | B33: 45744 | C33: C002 | D33: Amaka Eze | E33: Fabrication | F33: Pipe rack structure | G33: Won | H33: 6789000 | I33: =VLOOKUP(G33,Stages!$A$2:$B$6,2,FALSE()) -> 1 | J33: =H33*I33 -> 6789000 | K33: 45795 | M33: =IF(OR(G33="Won",G33="Lost"),K33-B33,Settings!$B$2-B33) -> 51
A34: Q0033 | B34: 45747 | C34: C005 | D34: Chidi Okafor | E34: Spares & Procurement | F34: Consumables supply | G34: Won | H34: 3095000 | I34: =VLOOKUP(G34,Stages!$A$2:$B$6,2,FALSE()) -> 1 | J34: =H34*I34 -> 3095000 | K34: 45758 | M34: =IF(OR(G34="Won",G34="Lost"),K34-B34,Settings!$B$2-B34) -> 11
A35: Q0034 | B35: 45748 | C35: C004 | D35: Ngozi Udoh | E35: Machining | F35: Wellhead component turning | G35: Won | H35: 5725000 | I35: =VLOOKUP(G35,Stages!$A$2:$B$6,2,FALSE()) -> 1 | J35: =H35*I35 -> 5725000 | K35: 45764 | M35: =IF(OR(G35="Won",G35="Lost"),K35-B35,Settings!$B$2-B35) -> 16
A36: Q0035 | B36: 45749 | C36: C001 | D36: Chidi Okafor | E36: Fire & Gas | F36: Gas detector installation | G36: Won | H36: 4966000 | I36: =VLOOKUP(G36,Stages!$A$2:$B$6,2,FALSE()) -> 1 | J36: =H36*I36 -> 4966000 | K36: 45780 | M36: =IF(OR(G36="Won",G36="Lost"),K36-B36,Settings!$B$2-B36) -> 31
A37: Q0036 | B37: 45756 | C37: C005 | D37: Chidi Okafor | E37: Fabrication | F37: Wellhead skid fabrication | G37: Lost | H37: 4729000 | I37: =VLOOKUP(G37,Stages!$A$2:$B$6,2,FALSE()) -> 0 | J37: =H37*I37 -> 0 | K37: 45816 | L37: No response from client | M37: =IF(OR(G37="Won",G37="Lost"),K37-B37,Settings!$B$2-B37) -> 60
A38: Q0037 | B38: 45761 | C38: C002 | D38: Amaka Eze | E38: Fabrication | F38: Wellhead skid fabrication | G38: Won | H38: 8718000 | I38: =VLOOKUP(G38,Stages!$A$2:$B$6,2,FALSE()) -> 1 | J38: =H38*I38 -> 8718000 | K38: 45810 | M38: =IF(OR(G38="Won",G38="Lost"),K38-B38,Settings!$B$2-B38) -> 49
A39: Q0038 | B39: 45761 | C39: C007 | D39: Tunde Bakare | E39: Coating | F39: Pipe external coating | G39: Lost | H39: 2176000 | I39: =VLOOKUP(G39,Stages!$A$2:$B$6,2,FALSE()) -> 0 | J39: =H39*I39 -> 0 | K39: 45804 | L39: Lead time too long | M39: =IF(OR(G39="Won",G39="Lost"),K39-B39,Settings!$B$2-B39) -> 43
A40: Q0039 | B40: 45762 | C40: C002 | D40: Amaka Eze | E40: Spares & Procurement | F40: Consumables supply | G40: Lost | H40: 1023000 | I40: =VLOOKUP(G40,Stages!$A$2:$B$6,2,FALSE()) -> 0 | J40: =H40*I40 -> 0 | K40: 45799 | L40: Lost to competitor | M40: =IF(OR(G40="Won",G40="Lost"),K40-B40,Settings!$B$2-B40) -> 37
A41: Q0040 | B41: 45764 | C41: C003 | D41: Tunde Bakare | E41: Fabrication | F41: Wellhead skid fabrication | G41: Lost | H41: 8758000 | I41: =VLOOKUP(G41,Stages!$A$2:$B$6,2,FALSE()) -> 0 | J41: =H41*I41 -> 0 | K41: 45830 | L41: No response from client | M41: =IF(OR(G41="Won",G41="Lost"),K41-B41,Settings!$B$2-B41) -> 66
A42: Q0041 | B42: 45766 | C42: C010 | D42: Amaka Eze | E42: Coating | F42: Structural steel coating | G42: Won | H42: 2183000 | I42: =VLOOKUP(G42,Stages!$A$2:$B$6,2,FALSE()) -> 1 | J42: =H42*I42 -> 2183000 | K42: 45810 | M42: =IF(OR(G42="Won",G42="Lost"),K42-B42,Settings!$B$2-B42) -> 44
A43: Q0042 | B43: 45769 | C43: C010 | D43: Amaka Eze | E43: Spares & Procurement | F43: Consumables supply | G43: Negotiation | H43: 7076000 | I43: =VLOOKUP(G43,Stages!$A$2:$B$6,2,FALSE()) -> 0.6 | J43: =H43*I43 -> 4245600 | K43: 45811 | M43: =IF(OR(G43="Won",G43="Lost"),K43-B43,Settings!$B$2-B43) -> 551
A44: Q0043 | B44: 45770 | C44: C004 | D44: Ngozi Udoh | E44: Fabrication | F44: Wellhead skid fabrication | G44: Lost | H44: 1810000 | I44: =VLOOKUP(G44,Stages!$A$2:$B$6,2,FALSE()) -> 0 | J44: =H44*I44 -> 0 | K44: 45838 | L44: Lost to competitor | M44: =IF(OR(G44="Won",G44="Lost"),K44-B44,Settings!$B$2-B44) -> 68
A45: Q0044 | B45: 45775 | C45: C010 | D45: Amaka Eze | E45: Fabrication | F45: Manifold fabrication | G45: Won | H45: 915000 | I45: =VLOOKUP(G45,Stages!$A$2:$B$6,2,FALSE()) -> 1 | J45: =H45*I45 -> 915000 | K45: 45800 | M45: =IF(OR(G45="Won",G45="Lost"),K45-B45,Settings!$B$2-B45) -> 25
A46: Q0045 | B46: 45776 | C46: C002 | D46: Amaka Eze | E46: Machining | F46: Gearbox housing machining | G46: Won | H46: 9485000 | I46: =VLOOKUP(G46,Stages!$A$2:$B$6,2,FALSE()) -> 1 | J46: =H46*I46 -> 9485000 | K46: 45817 | M46: =IF(OR(G46="Won",G46="Lost"),K46-B46,Settings!$B$2-B46) -> 41
A47: Q0046 | B47: 45778 | C47: C007 | D47: Tunde Bakare | E47: Spares & Procurement | F47: Valve and fittings supply | G47: Won | H47: 11903000 | I47: =VLOOKUP(G47,Stages!$A$2:$B$6,2,FALSE()) -> 1 | J47: =H47*I47 -> 11903000 | K47: 45807 | M47: =IF(OR(G47="Won",G47="Lost"),K47-B47,Settings!$B$2-B47) -> 29
A48: Q0047 | B48: 45779 | C48: C011 | D48: Tunde Bakare | E48: Pipe Thread Repair | F48: Tubing thread repair | G48: Won | H48: 6371000 | I48: =VLOOKUP(G48,Stages!$A$2:$B$6,2,FALSE()) -> 1 | J48: =H48*I48 -> 6371000 | K48: 45849 | M48: =IF(OR(G48="Won",G48="Lost"),K48-B48,Settings!$B$2-B48) -> 70
A49: Q0048 | B49: 45779 | C49: C002 | D49: Amaka Eze | E49: Coating | F49: Structural steel coating | G49: Lost | H49: 852000 | I49: =VLOOKUP(G49,Stages!$A$2:$B$6,2,FALSE()) -> 0 | J49: =H49*I49 -> 0 | K49: 45826 | L49: Project cancelled / postponed | M49: =IF(OR(G49="Won",G49="Lost"),K49-B49,Settings!$B$2-B49) -> 47
A50: Q0049 | B50: 45782 | C50: C004 | D50: Ngozi Udoh | E50: Machining | F50: Gearbox housing machining | G50: Lost | H50: 9014000 | I50: =VLOOKUP(G50,Stages!$A$2:$B$6,2,FALSE()) -> 0 | J50: =H50*I50 -> 0 | K50: 45845 | L50: Lead time too long | M50: =IF(OR(G50="Won",G50="Lost"),K50-B50,Settings!$B$2-B50) -> 63
A51: Q0050 | B51: 45783 | C51: C009 | D51: Chidi Okafor | E51: Spares & Procurement | F51: Consumables supply | G51: Negotiation | H51: 2995000 | I51: =VLOOKUP(G51,Stages!$A$2:$B$6,2,FALSE()) -> 0.6 | J51: =H51*I51 -> 1797000 | K51: 45826 | M51: =IF(OR(G51="Won",G51="Lost"),K51-B51,Settings!$B$2-B51) -> 537
A52: Q0051 | B52: 45783 | C52: C003 | D52: Tunde Bakare | E52: Fabrication | F52: Wellhead skid fabrication | G52: Lost | H52: 4762000 | I52: =VLOOKUP(G52,Stages!$A$2:$B$6,2,FALSE()) -> 0 | J52: =H52*I52 -> 0 | K52: 45853 | L52: Project cancelled / postponed | M52: =IF(OR(G52="Won",G52="Lost"),K52-B52,Settings!$B$2-B52) -> 70
A53: Q0052 | B53: 45784 | C53: C005 | D53: Chidi Okafor | E53: Pipe Thread Repair | F53: Casing thread inspection and repair | G53: Won | H53: 994000 | I53: =VLOOKUP(G53,Stages!$A$2:$B$6,2,FALSE()) -> 1 | J53: =H53*I53 -> 994000 | K53: 45803 | M53: =IF(OR(G53="Won",G53="Lost"),K53-B53,Settings!$B$2-B53) -> 19
A54: Q0053 | B54: 45786 | C54: C004 | D54: Ngozi Udoh | E54: Fabrication | F54: Wellhead skid fabrication | G54: Won | H54: 52105000 | I54: =VLOOKUP(G54,Stages!$A$2:$B$6,2,FALSE()) -> 1 | J54: =H54*I54 -> 52105000 | K54: 45798 | M54: =IF(OR(G54="Won",G54="Lost"),K54-B54,Settings!$B$2-B54) -> 12
A55: Q0054 | B55: 45786 | C55: C007 | D55: Tunde Bakare | E55: Spares & Procurement | F55: Consumables supply | G55: Won | H55: 5487000 | I55: =VLOOKUP(G55,Stages!$A$2:$B$6,2,FALSE()) -> 1 | J55: =H55*I55 -> 5487000 | K55: 45840 | M55: =IF(OR(G55="Won",G55="Lost"),K55-B55,Settings!$B$2-B55) -> 54
A56: Q0055 | B56: 45786 | C56: C011 | D56: Tunde Bakare | E56: Fire & Gas | F56: Fire and gas panel commissioning | G56: Lost | H56: 2350000 | I56: =VLOOKUP(G56,Stages!$A$2:$B$6,2,FALSE()) -> 0 | J56: =H56*I56 -> 0 | K56: 45796 | L56: Project cancelled / postponed | M56: =IF(OR(G56="Won",G56="Lost"),K56-B56,Settings!$B$2-B56) -> 10
A57: Q0056 | B57: 45791 | C57: C002 | D57: Amaka Eze | E57: Spares & Procurement | F57: Flanges and pipe supply | G57: Lost | H57: 527000 | I57: =VLOOKUP(G57,Stages!$A$2:$B$6,2,FALSE()) -> 0 | J57: =H57*I57 -> 0 | K57: 45811 | L57: Project cancelled / postponed | M57: =IF(OR(G57="Won",G57="Lost"),K57-B57,Settings!$B$2-B57) -> 20
A58: Q0057 | B58: 45791 | C58: C010 | D58: Amaka Eze | E58: Spares & Procurement | F58: Consumables supply | G58: Lost | H58: 4520000 | I58: =VLOOKUP(G58,Stages!$A$2:$B$6,2,FALSE()) -> 0 | J58: =H58*I58 -> 0 | K58: 45854 | L58: Lead time too long | M58: =IF(OR(G58="Won",G58="Lost"),K58-B58,Settings!$B$2-B58) -> 63
A59: Q0058 | B59: 45795 | C59: C010 | D59: Amaka Eze | E59: Spares & Procurement | F59: Flanges and pipe supply | G59: Quoted | H59: 9073000 | I59: =VLOOKUP(G59,Stages!$A$2:$B$6,2,FALSE()) -> 0.3 | J59: =H59*I59 -> 2721900 | K59: 45847 | M59: =IF(OR(G59="Won",G59="Lost"),K59-B59,Settings!$B$2-B59) -> 525
A60: Q0059 | B60: 45798 | C60: C005 | D60: Chidi Okafor | E60: Spares & Procurement | F60: Spares package - rotating equipment | G60: Lost | H60: 4528000 | I60: =VLOOKUP(G60,Stages!$A$2:$B$6,2,FALSE()) -> 0 | J60: =H60*I60 -> 0 | K60: 45811 | L60: Lead time too long | M60: =IF(OR(G60="Won",G60="Lost"),K60-B60,Settings!$B$2-B60) -> 13
A61: Q0060 | B61: 45798 | C61: C008 | D61: Ngozi Udoh | E61: Machining | F61: Pump shaft re-machining | G61: Lost | H61: 6509000 | I61: =VLOOKUP(G61,Stages!$A$2:$B$6,2,FALSE()) -> 0 | J61: =H61*I61 -> 0 | K61: 45813 | L61: Lost to competitor | M61: =IF(OR(G61="Won",G61="Lost"),K61-B61,Settings!$B$2-B61) -> 15
A62: Q0061 | B62: 45799 | C62: C002 | D62: Amaka Eze | E62: Fire & Gas | F62: Flame detector replacement | G62: Lost | H62: 6355000 | I62: =VLOOKUP(G62,Stages!$A$2:$B$6,2,FALSE()) -> 0 | J62: =H62*I62 -> 0 | K62: 45847 | L62: Lead time too long | M62: =IF(OR(G62="Won",G62="Lost"),K62-B62,Settings!$B$2-B62) -> 48
A63: Q0062 | B63: 45803 | C63: C008 | D63: Ngozi Udoh | E63: Fabrication | F63: Chemical injection skid | G63: Lost | H63: 7969000 | I63: =VLOOKUP(G63,Stages!$A$2:$B$6,2,FALSE()) -> 0 | J63: =H63*I63 -> 0 | K63: 45856 | L63: Project cancelled / postponed | M63: =IF(OR(G63="Won",G63="Lost"),K63-B63,Settings!$B$2-B63) -> 53
A64: Q0063 | B64: 45803 | C64: C008 | D64: Ngozi Udoh | E64: Machining | F64: Valve body CNC machining | G64: Lost | H64: 39775000 | I64: =VLOOKUP(G64,Stages!$A$2:$B$6,2,FALSE()) -> 0 | J64: =H64*I64 -> 0 | K64: 45842 | L64: Project cancelled / postponed | M64: =IF(OR(G64="Won",G64="Lost"),K64-B64,Settings!$B$2-B64) -> 39
A65: Q0064 | B65: 45805 | C65: C007 | D65: Tunde Bakare | E65: Machining | F65: Custom flange machining | G65: Lost | H65: 4204000 | I65: =VLOOKUP(G65,Stages!$A$2:$B$6,2,FALSE()) -> 0 | J65: =H65*I65 -> 0 | K65: 45820 | L65: Lost to competitor | M65: =IF(OR(G65="Won",G65="Lost"),K65-B65,Settings!$B$2-B65) -> 15
A66: Q0065 | B66: 45806 | C66: C013 | D66: Chidi Okafor | E66: Machining | F66: Wellhead component turning | G66: Lost | H66: 1395000 | I66: =VLOOKUP(G66,Stages!$A$2:$B$6,2,FALSE()) -> 0 | J66: =H66*I66 -> 0 | K66: 45845 | L66: Price too high | M66: =IF(OR(G66="Won",G66="Lost"),K66-B66,Settings!$B$2-B66) -> 39
A67: Q0066 | B67: 45808 | C67: C002 | D67: Amaka Eze | E67: Fabrication | F67: Manifold fabrication | G67: Negotiation | H67: 9430000 | I67: =VLOOKUP(G67,Stages!$A$2:$B$6,2,FALSE()) -> 0.6 | J67: =H67*I67 -> 5658000 | K67: 45885 | M67: =IF(OR(G67="Won",G67="Lost"),K67-B67,Settings!$B$2-B67) -> 512
A68: Q0067 | B68: 45809 | C68: C005 | D68: Chidi Okafor | E68: Spares & Procurement | F68: Flanges and pipe supply | G68: Won | H68: 8245000 | I68: =VLOOKUP(G68,Stages!$A$2:$B$6,2,FALSE()) -> 1 | J68: =H68*I68 -> 8245000 | K68: 45819 | M68: =IF(OR(G68="Won",G68="Lost"),K68-B68,Settings!$B$2-B68) -> 10
A69: Q0068 | B69: 45813 | C69: C001 | D69: Chidi Okafor | E69: Fabrication | F69: Manifold fabrication | G69: Lost | H69: 13341000 | I69: =VLOOKUP(G69,Stages!$A$2:$B$6,2,FALSE()) -> 0 | J69: =H69*I69 -> 0 | K69: 45868 | L69: No response from client | M69: =IF(OR(G69="Won",G69="Lost"),K69-B69,Settings!$B$2-B69) -> 55
A70: Q0069 | B70: 45813 | C70: C002 | D70: Amaka Eze | E70: Machining | F70: Custom flange machining | G70: Won | H70: 3481000 | I70: =VLOOKUP(G70,Stages!$A$2:$B$6,2,FALSE()) -> 1 | J70: =H70*I70 -> 3481000 | K70: 45881 | M70: =IF(OR(G70="Won",G70="Lost"),K70-B70,Settings!$B$2-B70) -> 68
A71: Q0070 | B71: 45814 | C71: C015 | D71: Tunde Bakare | E71: Spares & Procurement | F71: Valve and fittings supply | G71: Negotiation | H71: 8908000 | I71: =VLOOKUP(G71,Stages!$A$2:$B$6,2,FALSE()) -> 0.6 | J71: =H71*I71 -> 5344800 | K71: 45846 | M71: =IF(OR(G71="Won",G71="Lost"),K71-B71,Settings!$B$2-B71) -> 506
A72: Q0071 | B72: 45815 | C72: C002 | D72: Amaka Eze | E72: Coating | F72: Structural steel coating | G72: Won | H72: 3766000 | I72: =VLOOKUP(G72,Stages!$A$2:$B$6,2,FALSE()) -> 1 | J72: =H72*I72 -> 3766000 | K72: 45882 | M72: =IF(OR(G72="Won",G72="Lost"),K72-B72,Settings!$B$2-B72) -> 67
A73: Q0072 | B73: 45815 | C73: C001 | D73: Chidi Okafor | E73: Machining | F73: Valve body CNC machining | G73: Won | H73: 4796000 | I73: =VLOOKUP(G73,Stages!$A$2:$B$6,2,FALSE()) -> 1 | J73: =H73*I73 -> 4796000 | K73: 45854 | M73: =IF(OR(G73="Won",G73="Lost"),K73-B73,Settings!$B$2-B73) -> 39
A74: Q0073 | B74: 45815 | C74: C001 | D74: Chidi Okafor | E74: Fire & Gas | F74: Fire and gas panel commissioning | G74: Lost | H74: 2846000 | I74: =VLOOKUP(G74,Stages!$A$2:$B$6,2,FALSE()) -> 0 | J74: =H74*I74 -> 0 | K74: 45833 | L74: Project cancelled / postponed | M74: =IF(OR(G74="Won",G74="Lost"),K74-B74,Settings!$B$2-B74) -> 18
A75: Q0074 | B75: 45816 | C75: C007 | D75: Tunde Bakare | E75: Spares & Procurement | F75: Consumables supply | G75: Won | H75: 21934000 | I75: =VLOOKUP(G75,Stages!$A$2:$B$6,2,FALSE()) -> 1 | J75: =H75*I75 -> 21934000 | K75: 45874 | M75: =IF(OR(G75="Won",G75="Lost"),K75-B75,Settings!$B$2-B75) -> 58
A76: Q0075 | B76: 45817 | C76: C004 | D76: Ngozi Udoh | E76: Pipe Thread Repair | F76: Tubing thread repair | G76: Won | H76: 10008000 | I76: =VLOOKUP(G76,Stages!$A$2:$B$6,2,FALSE()) -> 1 | J76: =H76*I76 -> 10008000 | K76: 45887 | M76: =IF(OR(G76="Won",G76="Lost"),K76-B76,Settings!$B$2-B76) -> 70
A77: Q0076 | B77: 45818 | C77: C005 | D77: Chidi Okafor | E77: Spares & Procurement | F77: Spares package - rotating equipment | G77: Lost | H77: 4350000 | I77: =VLOOKUP(G77,Stages!$A$2:$B$6,2,FALSE()) -> 0 | J77: =H77*I77 -> 0 | K77: 45831 | L77: Lost to competitor | M77: =IF(OR(G77="Won",G77="Lost"),K77-B77,Settings!$B$2-B77) -> 13
A78: Q0077 | B78: 45818 | C78: C001 | D78: Chidi Okafor | E78: Fabrication | F78: Manifold fabrication | G78: Lost | H78: 2278000 | I78: =VLOOKUP(G78,Stages!$A$2:$B$6,2,FALSE()) -> 0 | J78: =H78*I78 -> 0 | K78: 45859 | L78: Lead time too long | M78: =IF(OR(G78="Won",G78="Lost"),K78-B78,Settings!$B$2-B78) -> 41
A79: Q0078 | B79: 45821 | C79: C001 | D79: Chidi Okafor | E79: Fire & Gas | F79: Gas detector installation | G79: Won | H79: 3643000 | I79: =VLOOKUP(G79,Stages!$A$2:$B$6,2,FALSE()) -> 1 | J79: =H79*I79 -> 3643000 | K79: 45849 | M79: =IF(OR(G79="Won",G79="Lost"),K79-B79,Settings!$B$2-B79) -> 28
A80: Q0079 | B80: 45822 | C80: C009 | D80: Chidi Okafor | E80: Spares & Procurement | F80: Valve and fittings supply | G80: Quoted | H80: 6517000 | I80: =VLOOKUP(G80,Stages!$A$2:$B$6,2,FALSE()) -> 0.3 | J80: =H80*I80 -> 1955100 | K80: 45865 | M80: =IF(OR(G80="Won",G80="Lost"),K80-B80,Settings!$B$2-B80) -> 498
A81: Q0080 | B81: 45822 | C81: C004 | D81: Ngozi Udoh | E81: Coating | F81: Pipe external coating | G81: Lost | H81: 55123000 | I81: =VLOOKUP(G81,Stages!$A$2:$B$6,2,FALSE()) -> 0 | J81: =H81*I81 -> 0 | K81: 45833 | L81: Price too high | M81: =IF(OR(G81="Won",G81="Lost"),K81-B81,Settings!$B$2-B81) -> 11
A82: Q0081 | B82: 45822 | C82: C003 | D82: Tunde Bakare | E82: Coating | F82: Pipe external coating | G82: Negotiation | H82: 9019000 | I82: =VLOOKUP(G82,Stages!$A$2:$B$6,2,FALSE()) -> 0.6 | J82: =H82*I82 -> 5411400 | K82: 45857 | M82: =IF(OR(G82="Won",G82="Lost"),K82-B82,Settings!$B$2-B82) -> 498
A83: Q0082 | B83: 45828 | C83: C009 | D83: Chidi Okafor | E83: Fire & Gas | F83: Flame detector replacement | G83: Lost | H83: 1782000 | I83: =VLOOKUP(G83,Stages!$A$2:$B$6,2,FALSE()) -> 0 | J83: =H83*I83 -> 0 | K83: 45884 | L83: Lost to competitor | M83: =IF(OR(G83="Won",G83="Lost"),K83-B83,Settings!$B$2-B83) -> 56
A84: Q0083 | B84: 45830 | C84: C002 | D84: Amaka Eze | E84: Machining | F84: Gearbox housing machining | G84: Lost | H84: 3653000 | I84: =VLOOKUP(G84,Stages!$A$2:$B$6,2,FALSE()) -> 0 | J84: =H84*I84 -> 0 | K84: 45844 | L84: No response from client | M84: =IF(OR(G84="Won",G84="Lost"),K84-B84,Settings!$B$2-B84) -> 14
A85: Q0084 | B85: 45832 | C85: C003 | D85: Tunde Bakare | E85: Fabrication | F85: Pressure vessel fabrication | G85: Won | H85: 1274000 | I85: =VLOOKUP(G85,Stages!$A$2:$B$6,2,FALSE()) -> 1 | J85: =H85*I85 -> 1274000 | K85: 45883 | M85: =IF(OR(G85="Won",G85="Lost"),K85-B85,Settings!$B$2-B85) -> 51
A86: Q0085 | B86: 45834 | C86: C001 | D86: Chidi Okafor | E86: Pipe Thread Repair | F86: Tubing thread repair | G86: Lost | H86: 9680000 | I86: =VLOOKUP(G86,Stages!$A$2:$B$6,2,FALSE()) -> 0 | J86: =H86*I86 -> 0 | K86: 45887 | L86: Project cancelled / postponed | M86: =IF(OR(G86="Won",G86="Lost"),K86-B86,Settings!$B$2-B86) -> 53
A87: Q0086 | B87: 45835 | C87: C006 | D87: Amaka Eze | E87: Spares & Procurement | F87: Consumables supply | G87: Lost | H87: 4240000 | I87: =VLOOKUP(G87,Stages!$A$2:$B$6,2,FALSE()) -> 0 | J87: =H87*I87 -> 0 | K87: 45875 | L87: No response from client | M87: =IF(OR(G87="Won",G87="Lost"),K87-B87,Settings!$B$2-B87) -> 40
A88: Q0087 | B88: 45836 | C88: C005 | D88: Chidi Okafor | E88: Machining | F88: Wellhead component turning | G88: Lost | H88: 3798000 | I88: =VLOOKUP(G88,Stages!$A$2:$B$6,2,FALSE()) -> 0 | J88: =H88*I88 -> 0 | K88: 45886 | L88: Price too high | M88: =IF(OR(G88="Won",G88="Lost"),K88-B88,Settings!$B$2-B88) -> 50
A89: Q0088 | B89: 45840 | C89: C001 | D89: Chidi Okafor | E89: Pipe Thread Repair | F89: Drill pipe thread re-cutting | G89: Lost | H89: 5146000 | I89: =VLOOKUP(G89,Stages!$A$2:$B$6,2,FALSE()) -> 0 | J89: =H89*I89 -> 0 | K89: 45877 | L89: Lead time too long | M89: =IF(OR(G89="Won",G89="Lost"),K89-B89,Settings!$B$2-B89) -> 37
A90: Q0089 | B90: 45846 | C90: C002 | D90: Amaka Eze | E90: Spares & Procurement | F90: Consumables supply | G90: Lost | H90: 3236000 | I90: =VLOOKUP(G90,Stages!$A$2:$B$6,2,FALSE()) -> 0 | J90: =H90*I90 -> 0 | K90: 45883 | L90: No response from client | M90: =IF(OR(G90="Won",G90="Lost"),K90-B90,Settings!$B$2-B90) -> 37
A91: Q0090 | B91: 45849 | C91: C001 | D91: Chidi Okafor | E91: Machining | F91: Wellhead component turning | G91: Won | H91: 1701000 | I91: =VLOOKUP(G91,Stages!$A$2:$B$6,2,FALSE()) -> 1 | J91: =H91*I91 -> 1701000 | K91: 45865 | M91: =IF(OR(G91="Won",G91="Lost"),K91-B91,Settings!$B$2-B91) -> 16
A92: Q0091 | B92: 45853 | C92: C006 | D92: Amaka Eze | E92: Pigging | F92: Pipeline pigging run | G92: Won | H92: 3229000 | I92: =VLOOKUP(G92,Stages!$A$2:$B$6,2,FALSE()) -> 1 | J92: =H92*I92 -> 3229000 | K92: 45895 | M92: =IF(OR(G92="Won",G92="Lost"),K92-B92,Settings!$B$2-B92) -> 42
A93: Q0092 | B93: 45855 | C93: C001 | D93: Chidi Okafor | E93: Fire & Gas | F93: Fire and gas panel commissioning | G93: Won | H93: 2173000 | I93: =VLOOKUP(G93,Stages!$A$2:$B$6,2,FALSE()) -> 1 | J93: =H93*I93 -> 2173000 | K93: 45870 | M93: =IF(OR(G93="Won",G93="Lost"),K93-B93,Settings!$B$2-B93) -> 15
A94: Q0093 | B94: 45859 | C94: C010 | D94: Amaka Eze | E94: Fabrication | F94: Pipe rack structure | G94: Lost | H94: 3950000 | I94: =VLOOKUP(G94,Stages!$A$2:$B$6,2,FALSE()) -> 0 | J94: =H94*I94 -> 0 | K94: 45908 | L94: Project cancelled / postponed | M94: =IF(OR(G94="Won",G94="Lost"),K94-B94,Settings!$B$2-B94) -> 49
A95: Q0094 | B95: 45860 | C95: C014 | D95: Amaka Eze | E95: Spares & Procurement | F95: Consumables supply | G95: Won | H95: 714000 | I95: =VLOOKUP(G95,Stages!$A$2:$B$6,2,FALSE()) -> 1 | J95: =H95*I95 -> 714000 | K95: 45908 | M95: =IF(OR(G95="Won",G95="Lost"),K95-B95,Settings!$B$2-B95) -> 48
A96: Q0095 | B96: 45860 | C96: C010 | D96: Amaka Eze | E96: Machining | F96: Wellhead component turning | G96: Lost | H96: 1850000 | I96: =VLOOKUP(G96,Stages!$A$2:$B$6,2,FALSE()) -> 0 | J96: =H96*I96 -> 0 | K96: 45914 | L96: No response from client | M96: =IF(OR(G96="Won",G96="Lost"),K96-B96,Settings!$B$2-B96) -> 54
A97: Q0096 | B97: 45861 | C97: C007 | D97: Tunde Bakare | E97: Fabrication | F97: Manifold fabrication | G97: Quoted | H97: 8734000 | I97: =VLOOKUP(G97,Stages!$A$2:$B$6,2,FALSE()) -> 0.3 | J97: =H97*I97 -> 2620200 | K97: 45935 | M97: =IF(OR(G97="Won",G97="Lost"),K97-B97,Settings!$B$2-B97) -> 459
A98: Q0097 | B98: 45870 | C98: C002 | D98: Amaka Eze | E98: Fire & Gas | F98: Flame detector replacement | G98: Lost | H98: 3741000 | I98: =VLOOKUP(G98,Stages!$A$2:$B$6,2,FALSE()) -> 0 | J98: =H98*I98 -> 0 | K98: 45930 | L98: Lost to competitor | M98: =IF(OR(G98="Won",G98="Lost"),K98-B98,Settings!$B$2-B98) -> 60
A99: Q0098 | B99: 45870 | C99: C001 | D99: Chidi Okafor | E99: Spares & Procurement | F99: Spares package - rotating equipment | G99: Won | H99: 4254000 | I99: =VLOOKUP(G99,Stages!$A$2:$B$6,2,FALSE()) -> 1 | J99: =H99*I99 -> 4254000 | K99: 45937 | M99: =IF(OR(G99="Won",G99="Lost"),K99-B99,Settings!$B$2-B99) -> 67
A100: Q0099 | B100: 45870 | C100: C007 | D100: Tunde Bakare | E100: Pipe Thread Repair | F100: Tubing thread repair | G100: Lost | H100: 1268000 | I100: =VLOOKUP(G100,Stages!$A$2:$B$6,2,FALSE()) -> 0 | J100: =H100*I100 -> 0 | K100: 45895 | L100: Project cancelled / postponed | M100: =IF(OR(G100="Won",G100="Lost"),K100-B100,Settings!$B$2-B100) -> 25
...

Sheet Stages
A1: Stage | B1: Probability
A2: Lead | B2: 0.1
A3: Quoted | B3: 0.3
A4: Negotiation | B4: 0.6
A5: Won | B5: 1
A6: Lost | B6: 0

Sheet Jobs
A1: JobID | B1: QuoteID | C1: CustomerID | D1: Service Line | E1: Description | F1: Supervisor | G1: Start Date | H1: Due Date | I1: Completion Date | J1: Status | K1: Workshop Stage | L1: Job Value | M1: Budgeted Hours | N1: Actual Hours | O1: Hours Variance | P1: Days Late | Q1: Delivery Status
A2: J0001 | B2: Q0001 | C2: C001 | D2: Fabrication | E2: Wellhead skid fabrication | F2: Bala Garba | G2: 45700 | H2: 45803 | I2: 45807 | J2: Completed | K2: Dispatched | L2: 1516000 | M2: 27 | N2: 34 | O2: =N2-M2 -> 7 | P2: =IF(I2<>"",MAX(0,I2-H2),MAX(0,Settings!$B$2-H2)) -> 4 | Q2: =IF(J2="Completed",IF(I2<=H2,"On Time","Late Delivery"),IF(Settings!$B$2>H2,"Overdue","On Track")) -> Late Delivery
A3: J0002 | B3: Q0002 | C3: C004 | D3: Fabrication | E3: Manifold fabrication | F3: Bala Garba | G3: 45726 | H3: 45799 | I3: 45788 | J3: Completed | K3: Dispatched | L3: 2235000 | M3: 40 | N3: 36 | O3: =N3-M3 -> -4 | P3: =IF(I3<>"",MAX(0,I3-H3),MAX(0,Settings!$B$2-H3)) -> 0 | Q3: =IF(J3="Completed",IF(I3<=H3,"On Time","Late Delivery"),IF(Settings!$B$2>H3,"Overdue","On Track")) -> On Time
A4: J0003 | B4: Q0008 | C4: C001 | D4: Machining | E4: Pump shaft re-machining | F4: Emeka Obi | G4: 45700 | H4: 45716 | I4: 45713 | J4: Completed | K4: Dispatched | L4: 19080000 | M4: 346 | N4: 311 | O4: =N4-M4 -> -35 | P4: =IF(I4<>"",MAX(0,I4-H4),MAX(0,Settings!$B$2-H4)) -> 0 | Q4: =IF(J4="Completed",IF(I4<=H4,"On Time","Late Delivery"),IF(Settings!$B$2>H4,"Overdue","On Track")) -> On Time
A5: J0004 | B5: Q0010 | C5: C001 | D5: Fabrication | E5: Pressure vessel fabrication | F5: Femi Adeyemi | G5: 45710 | H5: 45831 | I5: 45830 | J5: Completed | K5: Dispatched | L5: 7139000 | M5: 129 | N5: 111 | O5: =N5-M5 -> -18 | P5: =IF(I5<>"",MAX(0,I5-H5),MAX(0,Settings!$B$2-H5)) -> 0 | Q5: =IF(J5="Completed",IF(I5<=H5,"On Time","Late Delivery"),IF(Settings!$B$2>H5,"Overdue","On Track")) -> On Time
A6: J0005 | B6: Q0011 | C6: C006 | D6: Machining | E6: Custom flange machining | F6: Bala Garba | G6: 45734 | H6: 45754 | I6: 45760 | J6: Completed | K6: Dispatched | L6: 8253000 | M6: 150 | N6: 156 | O6: =N6-M6 -> 6 | P6: =IF(I6<>"",MAX(0,I6-H6),MAX(0,Settings!$B$2-H6)) -> 6 | Q6: =IF(J6="Completed",IF(I6<=H6,"On Time","Late Delivery"),IF(Settings!$B$2>H6,"Overdue","On Track")) -> Late Delivery
A7: J0006 | B7: Q0015 | C7: C001 | D7: Machining | E7: Pump shaft re-machining | F7: Femi Adeyemi | G7: 45747 | H7: 45770 | I7: 45769 | J7: Completed | K7: Dispatched | L7: 19220000 | M7: 349 | N7: 406 | O7: =N7-M7 -> 57 | P7: =IF(I7<>"",MAX(0,I7-H7),MAX(0,Settings!$B$2-H7)) -> 0 | Q7: =IF(J7="Completed",IF(I7<=H7,"On Time","Late Delivery"),IF(Settings!$B$2>H7,"Overdue","On Track")) -> On Time
A8: J0007 | B8: Q0016 | C8: C001 | D8: Pipe Thread Repair | E8: Premium connection repair | F8: Emeka Obi | G8: 45758 | H8: 45781 | I8: 45774 | J8: Completed | K8: Dispatched | L8: 3791000 | M8: 68 | N8: 58 | O8: =N8-M8 -> -10 | P8: =IF(I8<>"",MAX(0,I8-H8),MAX(0,Settings!$B$2-H8)) -> 0 | Q8: =IF(J8="Completed",IF(I8<=H8,"On Time","Late Delivery"),IF(Settings!$B$2>H8,"Overdue","On Track")) -> On Time
A9: J0008 | B9: Q0018 | C9: C012 | D9: Fabrication | E9: Manifold fabrication | F9: Bala Garba | G9: 45739 | H9: 45791 | I9: 45791 | J9: Completed | K9: Dispatched | L9: 11073000 | M9: 201 | N9: 174 | O9: =N9-M9 -> -27 | P9: =IF(I9<>"",MAX(0,I9-H9),MAX(0,Settings!$B$2-H9)) -> 0 | Q9: =IF(J9="Completed",IF(I9<=H9,"On Time","Late Delivery"),IF(Settings!$B$2>H9,"Overdue","On Track")) -> On Time
A10: J0009 | B10: Q0019 | C10: C004 | D10: Fire & Gas | E10: Flame detector replacement | F10: Femi Adeyemi | G10: 45727 | H10: 45751 | I10: 45752 | J10: Completed | K10: Dispatched | L10: 2863000 | M10: 52 | N10: 65 | O10: =N10-M10 -> 13 | P10: =IF(I10<>"",MAX(0,I10-H10),MAX(0,Settings!$B$2-H10)) -> 1 | Q10: =IF(J10="Completed",IF(I10<=H10,"On Time","Late Delivery"),IF(Settings!$B$2>H10,"Overdue","On Track")) -> Late Delivery
A11: J0010 | B11: Q0024 | C11: C003 | D11: Fire & Gas | E11: Flame detector replacement | F11: Bala Garba | G11: 45739 | H11: 45772 | I11: 45765 | J11: Completed | K11: Dispatched | L11: 6007000 | M11: 109 | N11: 113 | O11: =N11-M11 -> 4 | P11: =IF(I11<>"",MAX(0,I11-H11),MAX(0,Settings!$B$2-H11)) -> 0 | Q11: =IF(J11="Completed",IF(I11<=H11,"On Time","Late Delivery"),IF(Settings!$B$2>H11,"Overdue","On Track")) -> On Time
A12: J0011 | B12: Q0027 | C12: C003 | D12: Machining | E12: Valve body CNC machining | F12: Emeka Obi | G12: 45800 | H12: 45820 | I12: 45820 | J12: Completed | K12: Dispatched | L12: 14881000 | M12: 270 | N12: 255 | O12: =N12-M12 -> -15 | P12: =IF(I12<>"",MAX(0,I12-H12),MAX(0,Settings!$B$2-H12)) -> 0 | Q12: =IF(J12="Completed",IF(I12<=H12,"On Time","Late Delivery"),IF(Settings!$B$2>H12,"Overdue","On Track")) -> On Time
A13: J0012 | B13: Q0032 | C13: C002 | D13: Fabrication | E13: Pipe rack structure | F13: Emeka Obi | G13: 45801 | H13: 45896 | I13: 45894 | J13: Completed | K13: Dispatched | L13: 6789000 | M13: 123 | N13: 146 | O13: =N13-M13 -> 23 | P13: =IF(I13<>"",MAX(0,I13-H13),MAX(0,Settings!$B$2-H13)) -> 0 | Q13: =IF(J13="Completed",IF(I13<=H13,"On Time","Late Delivery"),IF(Settings!$B$2>H13,"Overdue","On Track")) -> On Time
... A20: J0019 | B20: Q0047 | C20: C011 | D20: Pipe Thread Repair | E20: Tubing thread repair | F20: Segun Alabi | G20: 45852 | H20: 45873 | I20: 45876 | J20: Completed | K20: Dispatched | L20: 6371000 | M20: 115 | N20: 114 | O20: =N20-M20 -> -1 | P20: =IF(I20<>"",MAX(0,I20-H20),MAX(0,Settings!$B$2-H20)) -> 3 | Q20: =IF(J20="Completed",IF(I20<=H20,"On Time","Late Delivery"),IF(Settings!$B$2>H20,"Overdue","On Track")) -> Late Delivery
A21: J0020 | B21: Q0052 | C21: C005 | D21: Pipe Thread Repair | E21: Casing thread inspection and repair | F21: Emeka Obi | G21: 45817 | H21: 45838 | J21: On Hold | K21: - | L21: 994000 | M21: 20 | N21: 22 | O21: =N21-M21 -> 2 | P21: =IF(I21<>"",MAX(0,I21-H21),MAX(0,Settings!$B$2-H21)) -> 482 | Q21: =IF(J21="Completed",IF(I21<=H21,"On Time","Late Delivery"),IF(Settings!$B$2>H21,"Overdue","On Track")) -> Overdue
A22: J0021 | B22: Q0053 | C22: C004 | D22: Fabrication | E22: Wellhead skid fabrication | F22: Bala Garba | G22: 45806 | H22: 45903 | I22: 45900 | J22: Completed | K22: Dispatched | L22: 52105000 | M22: 947 | N22: 1020 | O22: =N22-M22 -> 73 | P22: =IF(I22<>"",MAX(0,I22-H22),MAX(0,Settings!$B$2-H22)) -> 0 | Q22: =IF(J22="Completed",IF(I22<=H22,"On Time","Late Delivery"),IF(Settings!$B$2>H22,"Overdue","On Track")) -> On Time
A23: J0022 | B23: Q0069 | C23: C002 | D23: Machining | E23: Custom flange machining | F23: Segun Alabi | G23: 45884 | H23: 45923 | I23: 45922 | J23: Completed | K23: Dispatched | L23: 3481000 | M23: 63 | N23: 58 | O23: =N23-M23 -> -5 | P23: =IF(I23<>"",MAX(0,I23-H23),MAX(0,Settings!$B$2-H23)) -> 0 | Q23: =IF(J23="Completed",IF(I23<=H23,"On Time","Late Delivery"),IF(Settings!$B$2>H23,"Overdue","On Track")) -> On Time
A24: J0023 | B24: Q0071 | C24: C002 | D24: Coating | E24: Structural steel coating | F24: Bala Garba | G24: 45886 | H24: 45946 | I24: 45943 | J24: Completed | K24: Dispatched | L24: 3766000 | M24: 68 | N24: 80 | O24: =N24-M24 -> 12 | P24: =IF(I24<>"",MAX(0,I24-H24),MAX(0,Settings!$B$2-H24)) -> 0 | Q24: =IF(J24="Completed",IF(I24<=H24,"On Time","Late Delivery"),IF(Settings!$B$2>H24,"Overdue","On Track")) -> On Time
A25: J0024 | B25: Q0072 | C25: C001 | D25: Machining | E25: Valve body CNC machining | F25: Femi Adeyemi | G25: 45867 | H25: 45891 | I25: 45894 | J25: Completed | K25: Dispatched | L25: 4796000 | M25: 87 | N25: 94 | O25: =N25-M25 -> 7 | P25: =IF(I25<>"",MAX(0,I25-H25),MAX(0,Settings!$B$2-H25)) -> 3 | Q25: =IF(J25="Completed",IF(I25<=H25,"On Time","Late Delivery"),IF(Settings!$B$2>H25,"Overdue","On Track")) -> Late Delivery
A26: J0025 | B26: Q0075 | C26: C004 | D26: Pipe Thread Repair | E26: Tubing thread repair | F26: Segun Alabi | G26: 45897 | H26: 45911 | I26: 45918 | J26: Completed | K26: Dispatched | L26: 10008000 | M26: 181 | N26: 183 | O26: =N26-M26 -> 2 | P26: =IF(I26<>"",MAX(0,I26-H26),MAX(0,Settings!$B$2-H26)) -> 7 | Q26: =IF(J26="Completed",IF(I26<=H26,"On Time","Late Delivery"),IF(Settings!$B$2>H26,"Overdue","On Track")) -> Late Delivery
A27: J0026 | B27: Q0078 | C27: C001 | D27: Fire & Gas | E27: Gas detector installation | F27: Segun Alabi | G27: 45852 | H27: 45890 | I27: 45893 | J27: Completed | K27: Dispatched | L27: 3643000 | M27: 66 | N27: 85 | O27: =N27-M27 -> 19 | P27: =IF(I27<>"",MAX(0,I27-H27),MAX(0,Settings!$B$2-H27)) -> 3 | Q27: =IF(J27="Completed",IF(I27<=H27,"On Time","Late Delivery"),IF(Settings!$B$2>H27,"Overdue","On Track")) -> Late Delivery
A28: J0027 | B28: Q0084 | C28: C003 | D28: Fabrication | E28: Pressure vessel fabrication | F28: Emeka Obi | G28: 45887 | H28: 45933 | I28: 45931 | J28: Completed | K28: Dispatched | L28: 1274000 | M28: 23 | N28: 29 | O28: =N28-M28 -> 6 | P28: =IF(I28<>"",MAX(0,I28-H28),MAX(0,Settings!$B$2-H28)) -> 0 | Q28: =IF(J28="Completed",IF(I28<=H28,"On Time","Late Delivery"),IF(Settings!$B$2>H28,"Overdue","On Track")) -> On Time
A29: J0028 | B29: Q0090 | C29: C001 | D29: Machining | E29: Wellhead component turning | F29: Femi Adeyemi | G29: 45875 | H29: 45896 | I29: 45896 | J29: Completed | K29: Dispatched | L29: 1701000 | M29: 30 | N29: 26 | O29: =N29-M29 -> -4 | P29: =IF(I29<>"",MAX(0,I29-H29),MAX(0,Settings!$B$2-H29)) -> 0 | Q29: =IF(J29="Completed",IF(I29<=H29,"On Time","Late Delivery"),IF(Settings!$B$2>H29,"Overdue","On Track")) -> On Time
A30: J0029 | B30: Q0091 | C30: C006 | D30: Pigging | E30: Pipeline pigging run | F30: Segun Alabi | G30: 45903 | H30: 45910 | I30: 45911 | J30: Completed | K30: Dispatched | L30: 3229000 | M30: 58 | N30: 68 | O30: =N30-M30 -> 10 | P30: =IF(I30<>"",MAX(0,I30-H30),MAX(0,Settings!$B$2-H30)) -> 1 | Q30: =IF(J30="Completed",IF(I30<=H30,"On Time","Late Delivery"),IF(Settings!$B$2>H30,"Overdue","On Track")) -> Late Delivery
A31: J0030 | B31: Q0092 | C31: C001 | D31: Fire & Gas | E31: Fire and gas panel commissioning | F31: Segun Alabi | G31: 45877 | H31: 45921 | J31: On Hold | K31: - | L31: 2173000 | M31: 39 | N31: 44 | O31: =N31-M31 -> 5 | P31: =IF(I31<>"",MAX(0,I31-H31),MAX(0,Settings!$B$2-H31)) -> 399 | Q31: =IF(J31="Completed",IF(I31<=H31,"On Time","Late Delivery"),IF(Settings!$B$2>H31,"Overdue","On Track")) -> Overdue
A32: J0031 | B32: Q0106 | C32: C002 | D32: Fire & Gas | E32: Flame detector replacement | F32: Segun Alabi | G32: 45912 | H32: 45934 | J32: On Hold | K32: - | L32: 4723000 | M32: 85 | N32: 101 | O32: =N32-M32 -> 16 | P32: =IF(I32<>"",MAX(0,I32-H32),MAX(0,Settings!$B$2-H32)) -> 386 | Q32: =IF(J32="Completed",IF(I32<=H32,"On Time","Late Delivery"),IF(Settings!$B$2>H32,"Overdue","On Track")) -> Overdue
A33: J0032 | B33: Q0108 | C33: C015 | D33: Fabrication | E33: Chemical injection skid | F33: Bala Garba | G33: 45963 | H33: 46054 | I33: 46046 | J33: Completed | K33: Dispatched | L33: 6790000 | M33: 123 | N33: 155 | O33: =N33-M33 -> 32 | P33: =IF(I33<>"",MAX(0,I33-H33),MAX(0,Settings!$B$2-H33)) -> 0 | Q33: =IF(J33="Completed",IF(I33<=H33,"On Time","Late Delivery"),IF(Settings!$B$2>H33,"Overdue","On Track")) -> On Time
A34: J0033 | B34: Q0112 | C34: C001 | D34: Machining | E34: Wellhead component turning | F34: Femi Adeyemi | G34: 45969 | H34: 46007 | I34: 46010 | J34: Completed | K34: Dispatched | L34: 2221000 | M34: 40 | N34: 45 | O34: =N34-M34 -> 5 | P34: =IF(I34<>"",MAX(0,I34-H34),MAX(0,Settings!$B$2-H34)) -> 3 | Q34: =IF(J34="Completed",IF(I34<=H34,"On Time","Late Delivery"),IF(Settings!$B$2>H34,"Overdue","On Track")) -> Late Delivery
A35: J0034 | B35: Q0117 | C35: C008 | D35: Fabrication | E35: Pressure vessel fabrication | F35: Emeka Obi | G35: 45987 | H35: 46042 | I35: 46037 | J35: Completed | K35: Dispatched | L35: 1913000 | M35: 34 | N35: 42 | O35: =N35-M35 -> 8 | P35: =IF(I35<>"",MAX(0,I35-H35),MAX(0,Settings!$B$2-H35)) -> 0 | Q35: =IF(J35="Completed",IF(I35<=H35,"On Time","Late Delivery"),IF(Settings!$B$2>H35,"Overdue","On Track")) -> On Time
A36: J0035 | B36: Q0118 | C36: C003 | D36: Fabrication | E36: Chemical injection skid | F36: Emeka Obi | G36: 45988 | H36: 46115 | I36: 46113 | J36: Completed | K36: Dispatched | L36: 1638000 | M36: 29 | N36: 35 | O36: =N36-M36 -> 6 | P36: =IF(I36<>"",MAX(0,I36-H36),MAX(0,Settings!$B$2-H36)) -> 0 | Q36: =IF(J36="Completed",IF(I36<=H36,"On Time","Late Delivery"),IF(Settings!$B$2>H36,"Overdue","On Track")) -> On Time
A37: J0036 | B37: Q0119 | C37: C010 | D37: Fire & Gas | E37: Flame detector replacement | F37: Segun Alabi | G37: 45995 | H37: 46015 | I37: 46015 | J37: Completed | K37: Dispatched | L37: 1214000 | M37: 22 | N37: 19 | O37: =N37-M37 -> -3 | P37: =IF(I37<>"",MAX(0,I37-H37),MAX(0,Settings!$B$2-H37)) -> 0 | Q37: =IF(J37="Completed",IF(I37<=H37,"On Time","Late Delivery"),IF(Settings!$B$2>H37,"Overdue","On Track")) -> On Time
A38: J0037 | B38: Q0124 | C38: C006 | D38: Machining | E38: Gearbox housing machining | F38: Segun Alabi | G38: 45967 | H38: 45987 | I38: 45988 | J38: Completed | K38: Dispatched | L38: 9518000 | M38: 173 | N38: 184 | O38: =N38-M38 -> 11 | P38: =IF(I38<>"",MAX(0,I38-H38),MAX(0,Settings!$B$2-H38)) -> 1 | Q38: =IF(J38="Completed",IF(I38<=H38,"On Time","Late Delivery"),IF(Settings!$B$2>H38,"Overdue","On Track")) -> Late Delivery
A39: J0038 | B39: Q0128 | C39: C009 | D39: Machining | E39: Pump shaft re-machining | F39: Segun Alabi | G39: 45980 | H39: 46000 | I39: 46006 | J39: Completed | K39: Dispatched | L39: 15330000 | M39: 278 | N39: 286 | O39: =N39-M39 -> 8 | P39: =IF(I39<>"",MAX(0,I39-H39),MAX(0,Settings!$B$2-H39)) -> 6 | Q39: =IF(J39="Completed",IF(I39<=H39,"On Time","Late Delivery"),IF(Settings!$B$2>H39,"Overdue","On Track")) -> Late Delivery
A40: J0039 | B40: Q0133 | C40: C001 | D40: Machining | E40: Gearbox housing machining | F40: Segun Alabi | G40: 45967 | H40: 46007 | I40: 46011 | J40: Completed | K40: Dispatched | L40: 4395000 | M40: 79 | N40: 78 | O40: =N40-M40 -> -1 | P40: =IF(I40<>"",MAX(0,I40-H40),MAX(0,Settings!$B$2-H40)) -> 4 | Q40: =IF(J40="Completed",IF(I40<=H40,"On Time","Late Delivery"),IF(Settings!$B$2>H40,"Overdue","On Track")) -> Late Delivery
A41: J0040 | B41: Q0135 | C41: C001 | D41: Pigging | E41: Intelligent pigging support | F41: Segun Alabi | G41: 45982 | H41: 45999 | I41: 46000 | J41: Completed | K41: Dispatched | L41: 1258000 | M41: 22 | N41: 24 | O41: =N41-M41 -> 2 | P41: =IF(I41<>"",MAX(0,I41-H41),MAX(0,Settings!$B$2-H41)) -> 1 | Q41: =IF(J41="Completed",IF(I41<=H41,"On Time","Late Delivery"),IF(Settings!$B$2>H41,"Overdue","On Track")) -> Late Delivery
A42: J0041 | B42: Q0136 | C42: C004 | D42: Fabrication | E42: Manifold fabrication | F42: Segun Alabi | G42: 46002 | H42: 46128 | I42: 46129 | J42: Completed | K42: Dispatched | L42: 2525000 | M42: 45 | N42: 50 | O42: =N42-M42 -> 5 | P42: =IF(I42<>"",MAX(0,I42-H42),MAX(0,Settings!$B$2-H42)) -> 1 | Q42: =IF(J42="Completed",IF(I42<=H42,"On Time","Late Delivery"),IF(Settings!$B$2>H42,"Overdue","On Track")) -> Late Delivery
A43: J0042 | B43: Q0137 | C43: C008 | D43: Fire & Gas | E43: Flame detector replacement | F43: Emeka Obi | G43: 46003 | H43: 46040 | I43: 46041 | J43: Completed | K43: Dispatched | L43: 7176000 | M43: 130 | N43: 123 | O43: =N43-M43 -> -7 | P43: =IF(I43<>"",MAX(0,I43-H43),MAX(0,Settings!$B$2-H43)) -> 1 | Q43: =IF(J43="Completed",IF(I43<=H43,"On Time","Late Delivery"),IF(Settings!$B$2>H43,"Overdue","On Track")) -> Late Delivery
A44: J0043 | B44: Q0141 | C44: C008 | D44: Pigging | E44: Pig launcher/receiver servicing | F44: Emeka Obi | G44: 45979 | H44: 45991 | I44: 45989 | J44: Completed | K44: Dispatched | L44: 8219000 | M44: 149 | N44: 169 | O44: =N44-M44 -> 20 | P44: =IF(I44<>"",MAX(0,I44-H44),MAX(0,Settings!$B$2-H44)) -> 0 | Q44: =IF(J44="Completed",IF(I44<=H44,"On Time","Late Delivery"),IF(Settings!$B$2>H44,"Overdue","On Track")) -> On Time
... A51: J0050 | B51: Q0160 | C51: C005 | D51: Machining | E51: Valve body CNC machining | F51: Segun Alabi | G51: 46023 | H51: 46047 | I51: 46049 | J51: Completed | K51: Dispatched | L51: 1969000 | M51: 35 | N51: 35 | O51: =N51-M51 -> 0 | P51: =IF(I51<>"",MAX(0,I51-H51),MAX(0,Settings!$B$2-H51)) -> 2 | Q51: =IF(J51="Completed",IF(I51<=H51,"On Time","Late Delivery"),IF(Settings!$B$2>H51,"Overdue","On Track")) -> Late Delivery
A52: J0051 | B52: Q0161 | C52: C011 | D52: Fire & Gas | E52: Fire and gas panel commissioning | F52: Bala Garba | G52: 46048 | H52: 46062 | J52: On Hold | K52: - | L52: 8482000 | M52: 154 | N52: 182 | O52: =N52-M52 -> 28 | P52: =IF(I52<>"",MAX(0,I52-H52),MAX(0,Settings!$B$2-H52)) -> 258 | Q52: =IF(J52="Completed",IF(I52<=H52,"On Time","Late Delivery"),IF(Settings!$B$2>H52,"Overdue","On Track")) -> Overdue
A53: J0052 | B53: Q0166 | C53: C001 | D53: Coating | E53: Structural steel coating | F53: Emeka Obi | G53: 46060 | H53: 46108 | I53: 46104 | J53: Completed | K53: Dispatched | L53: 4379000 | M53: 79 | N53: 88 | O53: =N53-M53 -> 9 | P53: =IF(I53<>"",MAX(0,I53-H53),MAX(0,Settings!$B$2-H53)) -> 0 | Q53: =IF(J53="Completed",IF(I53<=H53,"On Time","Late Delivery"),IF(Settings!$B$2>H53,"Overdue","On Track")) -> On Time
A54: J0053 | B54: Q0172 | C54: C004 | D54: Coating | E54: Structural steel coating | F54: Femi Adeyemi | G54: 46068 | H54: 46100 | I54: 46096 | J54: Completed | K54: Dispatched | L54: 12004000 | M54: 218 | N54: 222 | O54: =N54-M54 -> 4 | P54: =IF(I54<>"",MAX(0,I54-H54),MAX(0,Settings!$B$2-H54)) -> 0 | Q54: =IF(J54="Completed",IF(I54<=H54,"On Time","Late Delivery"),IF(Settings!$B$2>H54,"Overdue","On Track")) -> On Time
A55: J0054 | B55: Q0173 | C55: C001 | D55: Pigging | E55: Pipeline pigging run | F55: Emeka Obi | G55: 46026 | H55: 46035 | J55: On Hold | K55: - | L55: 4521000 | M55: 82 | N55: 88 | O55: =N55-M55 -> 6 | P55: =IF(I55<>"",MAX(0,I55-H55),MAX(0,Settings!$B$2-H55)) -> 285 | Q55: =IF(J55="Completed",IF(I55<=H55,"On Time","Late Delivery"),IF(Settings!$B$2>H55,"Overdue","On Track")) -> Overdue
A56: J0055 | B56: Q0174 | C56: C001 | D56: Machining | E56: Custom flange machining | F56: Emeka Obi | G56: 46061 | H56: 46099 | I56: 46096 | J56: Completed | K56: Dispatched | L56: 6376000 | M56: 115 | N56: 144 | O56: =N56-M56 -> 29 | P56: =IF(I56<>"",MAX(0,I56-H56),MAX(0,Settings!$B$2-H56)) -> 0 | Q56: =IF(J56="Completed",IF(I56<=H56,"On Time","Late Delivery"),IF(Settings!$B$2>H56,"Overdue","On Track")) -> On Time
A57: J0056 | B57: Q0177 | C57: C003 | D57: Machining | E57: Wellhead component turning | F57: Segun Alabi | G57: 46076 | H57: 46122 | I57: 46116 | J57: Completed | K57: Dispatched | L57: 2335000 | M57: 42 | N57: 42 | O57: =N57-M57 -> 0 | P57: =IF(I57<>"",MAX(0,I57-H57),MAX(0,Settings!$B$2-H57)) -> 0 | Q57: =IF(J57="Completed",IF(I57<=H57,"On Time","Late Delivery"),IF(Settings!$B$2>H57,"Overdue","On Track")) -> On Time
A58: J0057 | B58: Q0179 | C58: C002 | D58: Machining | E58: Wellhead component turning | F58: Segun Alabi | G58: 46047 | H58: 46083 | I58: 46082 | J58: Completed | K58: Dispatched | L58: 1611000 | M58: 29 | N58: 27 | O58: =N58-M58 -> -2 | P58: =IF(I58<>"",MAX(0,I58-H58),MAX(0,Settings!$B$2-H58)) -> 0 | Q58: =IF(J58="Completed",IF(I58<=H58,"On Time","Late Delivery"),IF(Settings!$B$2>H58,"Overdue","On Track")) -> On Time
A59: J0058 | B59: Q0181 | C59: C003 | D59: Machining | E59: Gearbox housing machining | F59: Segun Alabi | G59: 46042 | H59: 46068 | I59: 46068 | J59: Completed | K59: Dispatched | L59: 2111000 | M59: 38 | N59: 37 | O59: =N59-M59 -> -1 | P59: =IF(I59<>"",MAX(0,I59-H59),MAX(0,Settings!$B$2-H59)) -> 0 | Q59: =IF(J59="Completed",IF(I59<=H59,"On Time","Late Delivery"),IF(Settings!$B$2>H59,"Overdue","On Track")) -> On Time
A60: J0059 | B60: Q0188 | C60: C005 | D60: Machining | E60: Wellhead component turning | F60: Emeka Obi | G60: 46107 | H60: 46140 | I60: 46142 | J60: Completed | K60: Dispatched | L60: 3869000 | M60: 70 | N60: 89 | O60: =N60-M60 -> 19 | P60: =IF(I60<>"",MAX(0,I60-H60),MAX(0,Settings!$B$2-H60)) -> 2 | Q60: =IF(J60="Completed",IF(I60<=H60,"On Time","Late Delivery"),IF(Settings!$B$2>H60,"Overdue","On Track")) -> Late Delivery
A61: J0060 | B61: Q0193 | C61: C001 | D61: Machining | E61: Custom flange machining | F61: Emeka Obi | G61: 46071 | H61: 46092 | I61: 46099 | J61: Completed | K61: Dispatched | L61: 2426000 | M61: 44 | N61: 39 | O61: =N61-M61 -> -5 | P61: =IF(I61<>"",MAX(0,I61-H61),MAX(0,Settings!$B$2-H61)) -> 7 | Q61: =IF(J61="Completed",IF(I61<=H61,"On Time","Late Delivery"),IF(Settings!$B$2>H61,"Overdue","On Track")) -> Late Delivery
A62: J0061 | B62: Q0194 | C62: C001 | D62: Coating | E62: Pipe external coating | F62: Femi Adeyemi | G62: 46095 | H62: 46143 | I62: 46142 | J62: Completed | K62: Dispatched | L62: 33640000 | M62: 611 | N62: 741 | O62: =N62-M62 -> 130 | P62: =IF(I62<>"",MAX(0,I62-H62),MAX(0,Settings!$B$2-H62)) -> 0 | Q62: =IF(J62="Completed",IF(I62<=H62,"On Time","Late Delivery"),IF(Settings!$B$2>H62,"Overdue","On Track")) -> On Time
A63: J0062 | B63: Q0199 | C63: C003 | D63: Coating | E63: Pipe external coating | F63: Segun Alabi | G63: 46107 | H63: 46140 | I63: 46134 | J63: Completed | K63: Dispatched | L63: 3186000 | M63: 57 | N63: 53 | O63: =N63-M63 -> -4 | P63: =IF(I63<>"",MAX(0,I63-H63),MAX(0,Settings!$B$2-H63)) -> 0 | Q63: =IF(J63="Completed",IF(I63<=H63,"On Time","Late Delivery"),IF(Settings!$B$2>H63,"Overdue","On Track")) -> On Time
A64: J0063 | B64: Q0200 | C64: C008 | D64: Fire & Gas | E64: Gas detector installation | F64: Segun Alabi | G64: 46061 | H64: 46097 | J64: On Hold | K64: - | L64: 6652000 | M64: 120 | N64: 141 | O64: =N64-M64 -> 21 | P64: =IF(I64<>"",MAX(0,I64-H64),MAX(0,Settings!$B$2-H64)) -> 223 | Q64: =IF(J64="Completed",IF(I64<=H64,"On Time","Late Delivery"),IF(Settings!$B$2>H64,"Overdue","On Track")) -> Overdue
A65: J0064 | B65: Q0202 | C65: C015 | D65: Fabrication | E65: Pipe rack structure | F65: Bala Garba | G65: 46077 | H65: 46172 | I65: 46171 | J65: Completed | K65: Dispatched | L65: 5207000 | M65: 94 | N65: 96 | O65: =N65-M65 -> 2 | P65: =IF(I65<>"",MAX(0,I65-H65),MAX(0,Settings!$B$2-H65)) -> 0 | Q65: =IF(J65="Completed",IF(I65<=H65,"On Time","Late Delivery"),IF(Settings!$B$2>H65,"Overdue","On Track")) -> On Time
A66: J0065 | B66: Q0206 | C66: C001 | D66: Coating | E66: Pipe external coating | F66: Segun Alabi | G66: 46105 | H66: 46143 | I66: 46139 | J66: Completed | K66: Dispatched | L66: 966000 | M66: 20 | N66: 25 | O66: =N66-M66 -> 5 | P66: =IF(I66<>"",MAX(0,I66-H66),MAX(0,Settings!$B$2-H66)) -> 0 | Q66: =IF(J66="Completed",IF(I66<=H66,"On Time","Late Delivery"),IF(Settings!$B$2>H66,"Overdue","On Track")) -> On Time
A67: J0066 | B67: Q0209 | C67: C007 | D67: Fire & Gas | E67: Fire and gas panel commissioning | F67: Emeka Obi | G67: 46092 | H67: 46121 | I67: 46116 | J67: Completed | K67: Dispatched | L67: 12218000 | M67: 222 | N67: 280 | O67: =N67-M67 -> 58 | P67: =IF(I67<>"",MAX(0,I67-H67),MAX(0,Settings!$B$2-H67)) -> 0 | Q67: =IF(J67="Completed",IF(I67<=H67,"On Time","Late Delivery"),IF(Settings!$B$2>H67,"Overdue","On Track")) -> On Time
A68: J0067 | B68: Q0216 | C68: C001 | D68: Pigging | E68: Intelligent pigging support | F68: Femi Adeyemi | G68: 46114 | H68: 46120 | I68: 46116 | J68: Completed | K68: Dispatched | L68: 2035000 | M68: 37 | N68: 45 | O68: =N68-M68 -> 8 | P68: =IF(I68<>"",MAX(0,I68-H68),MAX(0,Settings!$B$2-H68)) -> 0 | Q68: =IF(J68="Completed",IF(I68<=H68,"On Time","Late Delivery"),IF(Settings!$B$2>H68,"Overdue","On Track")) -> On Time
A69: J0068 | B69: Q0220 | C69: C011 | D69: Machining | E69: Valve body CNC machining | F69: Bala Garba | G69: 46093 | H69: 46118 | J69: On Hold | K69: - | L69: 22893000 | M69: 416 | N69: 498 | O69: =N69-M69 -> 82 | P69: =IF(I69<>"",MAX(0,I69-H69),MAX(0,Settings!$B$2-H69)) -> 202 | Q69: =IF(J69="Completed",IF(I69<=H69,"On Time","Late Delivery"),IF(Settings!$B$2>H69,"Overdue","On Track")) -> Overdue
A70: J0069 | B70: Q0222 | C70: C001 | D70: Fabrication | E70: Wellhead skid fabrication | F70: Emeka Obi | G70: 46126 | H70: 46221 | I70: 46224 | J70: Completed | K70: Dispatched | L70: 2099000 | M70: 38 | N70: 43 | O70: =N70-M70 -> 5 | P70: =IF(I70<>"",MAX(0,I70-H70),MAX(0,Settings!$B$2-H70)) -> 3 | Q70: =IF(J70="Completed",IF(I70<=H70,"On Time","Late Delivery"),IF(Settings!$B$2>H70,"Overdue","On Track")) -> Late Delivery
A71: J0070 | B71: Q0223 | C71: C003 | D71: Pipe Thread Repair | E71: Drill pipe thread re-cutting | F71: Femi Adeyemi | G71: 46133 | H71: 46156 | I71: 46147 | J71: Completed | K71: Dispatched | L71: 19574000 | M71: 355 | N71: 330 | O71: =N71-M71 -> -25 | P71: =IF(I71<>"",MAX(0,I71-H71),MAX(0,Settings!$B$2-H71)) -> 0 | Q71: =IF(J71="Completed",IF(I71<=H71,"On Time","Late Delivery"),IF(Settings!$B$2>H71,"Overdue","On Track")) -> On Time
A72: J0071 | B72: Q0224 | C72: C001 | D72: Fabrication | E72: Chemical injection skid | F72: Bala Garba | G72: 46168 | H72: 46233 | I72: 46223 | J72: Completed | K72: Dispatched | L72: 1296000 | M72: 23 | N72: 21 | O72: =N72-M72 -> -2 | P72: =IF(I72<>"",MAX(0,I72-H72),MAX(0,Settings!$B$2-H72)) -> 0 | Q72: =IF(J72="Completed",IF(I72<=H72,"On Time","Late Delivery"),IF(Settings!$B$2>H72,"Overdue","On Track")) -> On Time
A73: J0072 | B73: Q0227 | C73: C004 | D73: Fire & Gas | E73: Gas detector installation | F73: Femi Adeyemi | G73: 46142 | H73: 46163 | I73: 46163 | J73: Completed | K73: Dispatched | L73: 2280000 | M73: 41 | N73: 46 | O73: =N73-M73 -> 5 | P73: =IF(I73<>"",MAX(0,I73-H73),MAX(0,Settings!$B$2-H73)) -> 0 | Q73: =IF(J73="Completed",IF(I73<=H73,"On Time","Late Delivery"),IF(Settings!$B$2>H73,"Overdue","On Track")) -> On Time
A74: J0073 | B74: Q0228 | C74: C005 | D74: Machining | E74: Pump shaft re-machining | F74: Emeka Obi | G74: 46129 | H74: 46154 | J74: On Hold | K74: - | L74: 3368000 | M74: 61 | N74: 59 | O74: =N74-M74 -> -2 | P74: =IF(I74<>"",MAX(0,I74-H74),MAX(0,Settings!$B$2-H74)) -> 166 | Q74: =IF(J74="Completed",IF(I74<=H74,"On Time","Late Delivery"),IF(Settings!$B$2>H74,"Overdue","On Track")) -> Overdue
A75: J0074 | B75: Q0232 | C75: C005 | D75: Fabrication | E75: Manifold fabrication | F75: Bala Garba | G75: 46169 | H75: 46269 | I75: 46259 | J75: Completed | K75: Dispatched | L75: 4459000 | M75: 81 | N75: 97 | O75: =N75-M75 -> 16 | P75: =IF(I75<>"",MAX(0,I75-H75),MAX(0,Settings!$B$2-H75)) -> 0 | Q75: =IF(J75="Completed",IF(I75<=H75,"On Time","Late Delivery"),IF(Settings!$B$2>H75,"Overdue","On Track")) -> On Time
A76: J0075 | B76: Q0237 | C76: C012 | D76: Coating | E76: Pipe external coating | F76: Bala Garba | G76: 46155 | H76: 46214 | I76: 46213 | J76: Completed | K76: Dispatched | L76: 7812000 | M76: 142 | N76: 145 | O76: =N76-M76 -> 3 | P76: =IF(I76<>"",MAX(0,I76-H76),MAX(0,Settings!$B$2-H76)) -> 0 | Q76: =IF(J76="Completed",IF(I76<=H76,"On Time","Late Delivery"),IF(Settings!$B$2>H76,"Overdue","On Track")) -> On Time
A77: J0076 | B77: Q0239 | C77: C010 | D77: Fire & Gas | E77: Flame detector replacement | F77: Bala Garba | G77: 46162 | H77: 46198 | I77: 46195 | J77: Completed | K77: Dispatched | L77: 3789000 | M77: 68 | N77: 78 | O77: =N77-M77 -> 10 | P77: =IF(I77<>"",MAX(0,I77-H77),MAX(0,Settings!$B$2-H77)) -> 0 | Q77: =IF(J77="Completed",IF(I77<=H77,"On Time","Late Delivery"),IF(Settings!$B$2>H77,"Overdue","On Track")) -> On Time
A78: J0077 | B78: Q0246 | C78: C009 | D78: Fabrication | E78: Wellhead skid fabrication | F78: Femi Adeyemi | G78: 46172 | H78: 46241 | I78: 46239 | J78: Completed | K78: Dispatched | L78: 3755000 | M78: 68 | N78: 82 | O78: =N78-M78 -> 14 | P78: =IF(I78<>"",MAX(0,I78-H78),MAX(0,Settings!$B$2-H78)) -> 0 | Q78: =IF(J78="Completed",IF(I78<=H78,"On Time","Late Delivery"),IF(Settings!$B$2>H78,"Overdue","On Track")) -> On Time
A79: J0078 | B79: Q0250 | C79: C005 | D79: Fabrication | E79: Pipe rack structure | F79: Emeka Obi | G79: 46172 | H79: 46223 | I79: 46228 | J79: Completed | K79: Dispatched | L79: 36841000 | M79: 669 | N79: 850 | O79: =N79-M79 -> 181 | P79: =IF(I79<>"",MAX(0,I79-H79),MAX(0,Settings!$B$2-H79)) -> 5 | Q79: =IF(J79="Completed",IF(I79<=H79,"On Time","Late Delivery"),IF(Settings!$B$2>H79,"Overdue","On Track")) -> Late Delivery
A80: J0079 | B80: Q0255 | C80: C006 | D80: Fabrication | E80: Wellhead skid fabrication | F80: Bala Garba | G80: 46171 | H80: 46290 | I80: 46295 | J80: Completed | K80: Dispatched | L80: 3499000 | M80: 63 | N80: 57 | O80: =N80-M80 -> -6 | P80: =IF(I80<>"",MAX(0,I80-H80),MAX(0,Settings!$B$2-H80)) -> 5 | Q80: =IF(J80="Completed",IF(I80<=H80,"On Time","Late Delivery"),IF(Settings!$B$2>H80,"Overdue","On Track")) -> Late Delivery
A81: J0080 | B81: Q0258 | C81: C003 | D81: Coating | E81: Pipe external coating | F81: Segun Alabi | G81: 46223 | H81: 46259 | I81: 46263 | J81: Completed | K81: Dispatched | L81: 961000 | M81: 20 | N81: 18 | O81: =N81-M81 -> -2 | P81: =IF(I81<>"",MAX(0,I81-H81),MAX(0,Settings!$B$2-H81)) -> 4 | Q81: =IF(J81="Completed",IF(I81<=H81,"On Time","Late Delivery"),IF(Settings!$B$2>H81,"Overdue","On Track")) -> Late Delivery
A82: J0081 | B82: Q0261 | C82: C001 | D82: Pipe Thread Repair | E82: Tubing thread repair | F82: Emeka Obi | G82: 46185 | H82: 46201 | I82: 46198 | J82: Completed | K82: Dispatched | L82: 6789000 | M82: 123 | N82: 109 | O82: =N82-M82 -> -14 | P82: =IF(I82<>"",MAX(0,I82-H82),MAX(0,Settings!$B$2-H82)) -> 0 | Q82: =IF(J82="Completed",IF(I82<=H82,"On Time","Late Delivery"),IF(Settings!$B$2>H82,"Overdue","On Track")) -> On Time
A83: J0082 | B83: Q0262 | C83: C008 | D83: Fire & Gas | E83: Fire and gas panel commissioning | F83: Segun Alabi | G83: 46181 | H83: 46221 | I83: 46219 | J83: Completed | K83: Dispatched | L83: 3424000 | M83: 62 | N83: 61 | O83: =N83-M83 -> -1 | P83: =IF(I83<>"",MAX(0,I83-H83),MAX(0,Settings!$B$2-H83)) -> 0 | Q83: =IF(J83="Completed",IF(I83<=H83,"On Time","Late Delivery"),IF(Settings!$B$2>H83,"Overdue","On Track")) -> On Time
A84: J0083 | B84: Q0267 | C84: C002 | D84: Machining | E84: Pump shaft re-machining | F84: Emeka Obi | G84: 46240 | H84: 46266 | I84: 46269 | J84: Completed | K84: Dispatched | L84: 5811000 | M84: 105 | N84: 119 | O84: =N84-M84 -> 14 | P84: =IF(I84<>"",MAX(0,I84-H84),MAX(0,Settings!$B$2-H84)) -> 3 | Q84: =IF(J84="Completed",IF(I84<=H84,"On Time","Late Delivery"),IF(Settings!$B$2>H84,"Overdue","On Track")) -> Late Delivery
A85: J0084 | B85: Q0268 | C85: C005 | D85: Machining | E85: Pump shaft re-machining | F85: Emeka Obi | G85: 46198 | H85: 46234 | J85: On Hold | K85: - | L85: 2414000 | M85: 43 | N85: 45 | O85: =N85-M85 -> 2 | P85: =IF(I85<>"",MAX(0,I85-H85),MAX(0,Settings!$B$2-H85)) -> 86 | Q85: =IF(J85="Completed",IF(I85<=H85,"On Time","Late Delivery"),IF(Settings!$B$2>H85,"Overdue","On Track")) -> Overdue
A86: J0085 | B86: Q0269 | C86: C005 | D86: Machining | E86: Valve body CNC machining | F86: Bala Garba | G86: 46232 | H86: 46280 | I86: 46275 | J86: Completed | K86: Dispatched | L86: 2914000 | M86: 52 | N86: 66 | O86: =N86-M86 -> 14 | P86: =IF(I86<>"",MAX(0,I86-H86),MAX(0,Settings!$B$2-H86)) -> 0 | Q86: =IF(J86="Completed",IF(I86<=H86,"On Time","Late Delivery"),IF(Settings!$B$2>H86,"Overdue","On Track")) -> On Time
A87: J0086 | B87: Q0270 | C87: C004 | D87: Coating | E87: Pipe external coating | F87: Femi Adeyemi | G87: 46218 | H87: 46239 | I87: 46230 | J87: Completed | K87: Dispatched | L87: 3436000 | M87: 62 | N87: 59 | O87: =N87-M87 -> -3 | P87: =IF(I87<>"",MAX(0,I87-H87),MAX(0,Settings!$B$2-H87)) -> 0 | Q87: =IF(J87="Completed",IF(I87<=H87,"On Time","Late Delivery"),IF(Settings!$B$2>H87,"Overdue","On Track")) -> On Time
A88: J0087 | B88: Q0274 | C88: C004 | D88: Fire & Gas | E88: Flame detector replacement | F88: Emeka Obi | G88: 46236 | H88: 46263 | I88: 46260 | J88: Completed | K88: Dispatched | L88: 14857000 | M88: 270 | N88: 246 | O88: =N88-M88 -> -24 | P88: =IF(I88<>"",MAX(0,I88-H88),MAX(0,Settings!$B$2-H88)) -> 0 | Q88: =IF(J88="Completed",IF(I88<=H88,"On Time","Late Delivery"),IF(Settings!$B$2>H88,"Overdue","On Track")) -> On Time
A89: J0088 | B89: Q0276 | C89: C010 | D89: Fire & Gas | E89: Fire and gas panel commissioning | F89: Femi Adeyemi | G89: 46226 | H89: 46248 | I89: 46236 | J89: Completed | K89: Dispatched | L89: 3657000 | M89: 66 | N89: 66 | O89: =N89-M89 -> 0 | P89: =IF(I89<>"",MAX(0,I89-H89),MAX(0,Settings!$B$2-H89)) -> 0 | Q89: =IF(J89="Completed",IF(I89<=H89,"On Time","Late Delivery"),IF(Settings!$B$2>H89,"Overdue","On Track")) -> On Time
A90: J0089 | B90: Q0278 | C90: C001 | D90: Fire & Gas | E90: Gas detector installation | F90: Bala Garba | G90: 46242 | H90: 46287 | I90: 46286 | J90: Completed | K90: Dispatched | L90: 2418000 | M90: 43 | N90: 55 | O90: =N90-M90 -> 12 | P90: =IF(I90<>"",MAX(0,I90-H90),MAX(0,Settings!$B$2-H90)) -> 0 | Q90: =IF(J90="Completed",IF(I90<=H90,"On Time","Late Delivery"),IF(Settings!$B$2>H90,"Overdue","On Track")) -> On Time
A91: J0090 | B91: Q0281 | C91: C002 | D91: Machining | E91: Wellhead component turning | F91: Emeka Obi | G91: 46207 | H91: 46233 | I91: 46235 | J91: Completed | K91: Dispatched | L91: 2294000 | M91: 41 | N91: 53 | O91: =N91-M91 -> 12 | P91: =IF(I91<>"",MAX(0,I91-H91),MAX(0,Settings!$B$2-H91)) -> 2 | Q91: =IF(J91="Completed",IF(I91<=H91,"On Time","Late Delivery"),IF(Settings!$B$2>H91,"Overdue","On Track")) -> Late Delivery
A92: J0091 | B92: Q0283 | C92: C006 | D92: Pipe Thread Repair | E92: Drill pipe thread re-cutting | F92: Segun Alabi | G92: 46220 | H92: 46248 | I92: 46241 | J92: Completed | K92: Dispatched | L92: 52988000 | M92: 963 | N92: 1163 | O92: =N92-M92 -> 200 | P92: =IF(I92<>"",MAX(0,I92-H92),MAX(0,Settings!$B$2-H92)) -> 0 | Q92: =IF(J92="Completed",IF(I92<=H92,"On Time","Late Delivery"),IF(Settings!$B$2>H92,"Overdue","On Track")) -> On Time
A93: J0092 | B93: Q0288 | C93: C001 | D93: Coating | E93: Epoxy coating - tank | F93: Segun Alabi | G93: 46222 | H93: 46270 | I93: 46268 | J93: Completed | K93: Dispatched | L93: 7449000 | M93: 135 | N93: 153 | O93: =N93-M93 -> 18 | P93: =IF(I93<>"",MAX(0,I93-H93),MAX(0,Settings!$B$2-H93)) -> 0 | Q93: =IF(J93="Completed",IF(I93<=H93,"On Time","Late Delivery"),IF(Settings!$B$2>H93,"Overdue","On Track")) -> On Time
A94: J0093 | B94: Q0289 | C94: C001 | D94: Fabrication | E94: Wellhead skid fabrication | F94: Emeka Obi | G94: 46219 | H94: 46289 | I94: 46280 | J94: Completed | K94: Dispatched | L94: 9338000 | M94: 169 | N94: 172 | O94: =N94-M94 -> 3 | P94: =IF(I94<>"",MAX(0,I94-H94),MAX(0,Settings!$B$2-H94)) -> 0 | Q94: =IF(J94="Completed",IF(I94<=H94,"On Time","Late Delivery"),IF(Settings!$B$2>H94,"Overdue","On Track")) -> On Time
A95: J0094 | B95: Q0290 | C95: C014 | D95: Pigging | E95: Intelligent pigging support | F95: Femi Adeyemi | G95: 46279 | H95: 46287 | I95: 46288 | J95: Completed | K95: Dispatched | L95: 5492000 | M95: 99 | N95: 102 | O95: =N95-M95 -> 3 | P95: =IF(I95<>"",MAX(0,I95-H95),MAX(0,Settings!$B$2-H95)) -> 1 | Q95: =IF(J95="Completed",IF(I95<=H95,"On Time","Late Delivery"),IF(Settings!$B$2>H95,"Overdue","On Track")) -> Late Delivery
A96: J0095 | B96: Q0293 | C96: C004 | D96: Fabrication | E96: Pressure vessel fabrication | F96: Segun Alabi | G96: 46232 | H96: 46280 | I96: 46277 | J96: Completed | K96: Dispatched | L96: 9315000 | M96: 169 | N96: 205 | O96: =N96-M96 -> 36 | P96: =IF(I96<>"",MAX(0,I96-H96),MAX(0,Settings!$B$2-H96)) -> 0 | Q96: =IF(J96="Completed",IF(I96<=H96,"On Time","Late Delivery"),IF(Settings!$B$2>H96,"Overdue","On Track")) -> On Time
A97: J0096 | B97: Q0298 | C97: C001 | D97: Pigging | E97: Pig launcher/receiver servicing | F97: Femi Adeyemi | G97: 46248 | H97: 46259 | I97: 46258 | J97: Completed | K97: Dispatched | L97: 6849000 | M97: 124 | N97: 113 | O97: =N97-M97 -> -11 | P97: =IF(I97<>"",MAX(0,I97-H97),MAX(0,Settings!$B$2-H97)) -> 0 | Q97: =IF(J97="Completed",IF(I97<=H97,"On Time","Late Delivery"),IF(Settings!$B$2>H97,"Overdue","On Track")) -> On Time
... A99: J0098 | B99: Q0303 | C99: C003 | D99: Fire & Gas | E99: Fire and gas panel commissioning | F99: Femi Adeyemi | G99: 46275 | H99: 46318 | I99: 46315 | J99: Completed | K99: Dispatched | L99: 7472000 | M99: 135 | N99: 119 | O99: =N99-M99 -> -16 | P99: =IF(I99<>"",MAX(0,I99-H99),MAX(0,Settings!$B$2-H99)) -> 0 | Q99: =IF(J99="Completed",IF(I99<=H99,"On Time","Late Delivery"),IF(Settings!$B$2>H99,"Overdue","On Track")) -> On Time
A100: J0099 | B100: Q0306 | C100: C003 | D100: Fabrication | E100: Wellhead skid fabrication | F100: Femi Adeyemi | G100: 46304 | H100: 46376 | J100: In Progress | K100: Cutting & Machining | L100: 5751000 | M100: 104 | N100: 22 | O100: =N100-M100 -> -82 | P100: =IF(I100<>"",MAX(0,I100-H100),MAX(0,Settings!$B$2-H100)) -> 0 | Q100: =IF(J100="Completed",IF(I100<=H100,"On Time","Late Delivery"),IF(Settings!$B$2>H100,"Overdue","On Track")) -> On Track
A101: J0100 | B101: Q0314 | C101: C001 | D101: Fabrication | E101: Manifold fabrication | F101: Emeka Obi | G101: 46286 | H101: 46408 | J101: In Progress | K101: Cutting & Machining | L101: 4187000 | M101: 76 | N101: 24 | O101: =N101-M101 -> -52 | P101: =IF(I101<>"",MAX(0,I101-H101),MAX(0,Settings!$B$2-H101)) -> 0 | Q101: =IF(J101="Completed",IF(I101<=H101,"On Time","Late Delivery"),IF(Settings!$B$2>H101,"Overdue","On Track")) -> On Track
A102: J0101 | B102: Q0315 | C102: C001 | D102: Pigging | E102: Pipeline pigging run | F102: Femi Adeyemi | G102: 46294 | H102: 46314 | J102: In Progress | K102: Coating & Finishing | L102: 998000 | M102: 20 | N102: 21 | O102: =N102-M102 -> 1 | P102: =IF(I102<>"",MAX(0,I102-H102),MAX(0,Settings!$B$2-H102)) -> 6 | Q102: =IF(J102="Completed",IF(I102<=H102,"On Time","Late Delivery"),IF(Settings!$B$2>H102,"Overdue","On Track")) -> Overdue
A103: J0102 | B103: Q0320 | C103: C003 | D103: Coating | E103: Pipe external coating | F103: Emeka Obi | G103: 46291 | H103: 46323 | J103: On Hold | K103: - | L103: 4673000 | M103: 84 | N103: 80 | O103: =N103-M103 -> -4 | P103: =IF(I103<>"",MAX(0,I103-H103),MAX(0,Settings!$B$2-H103)) -> 0 | Q103: =IF(J103="Completed",IF(I103<=H103,"On Time","Late Delivery"),IF(Settings!$B$2>H103,"Overdue","On Track")) -> On Track
A104: J0103 | B104: Q0321 | C104: C002 | D104: Machining | E104: Custom flange machining | F104: Femi Adeyemi | G104: 46303 | H104: 46344 | J104: In Progress | K104: Cutting & Machining | L104: 929000 | M104: 20 | N104: 9 | O104: =N104-M104 -> -11 | P104: =IF(I104<>"",MAX(0,I104-H104),MAX(0,Settings!$B$2-H104)) -> 0 | Q104: =IF(J104="Completed",IF(I104<=H104,"On Time","Late Delivery"),IF(Settings!$B$2>H104,"Overdue","On Track")) -> On Track
A105: J0104 | B105: Q0322 | C105: C015 | D105: Fabrication | E105: Wellhead skid fabrication | F105: Emeka Obi | G105: 46309 | H105: 46403 | J105: In Progress | K105: Planning & Material | L105: 998000 | M105: 20 | N105: 2 | O105: =N105-M105 -> -18 | P105: =IF(I105<>"",MAX(0,I105-H105),MAX(0,Settings!$B$2-H105)) -> 0 | Q105: =IF(J105="Completed",IF(I105<=H105,"On Time","Late Delivery"),IF(Settings!$B$2>H105,"Overdue","On Track")) -> On Track
A106: J0105 | B106: Q0323 | C106: C007 | D106: Pigging | E106: Pig launcher/receiver servicing | F106: Segun Alabi | G106: 46305 | H106: 46323 | J106: In Progress | K106: Coating & Finishing | L106: 6385000 | M106: 116 | N106: 116 | O106: =N106-M106 -> 0 | P106: =IF(I106<>"",MAX(0,I106-H106),MAX(0,Settings!$B$2-H106)) -> 0 | Q106: =IF(J106="Completed",IF(I106<=H106,"On Time","Late Delivery"),IF(Settings!$B$2>H106,"Overdue","On Track")) -> On Track
A107: J0106 | B107: Q0327 | C107: C011 | D107: Machining | E107: Pump shaft re-machining | F107: Emeka Obi | G107: 46317 | H107: 46340 | J107: In Progress | K107: Planning & Material | L107: 14471000 | M107: 263 | N107: 35 | O107: =N107-M107 -> -228 | P107: =IF(I107<>"",MAX(0,I107-H107),MAX(0,Settings!$B$2-H107)) -> 0 | Q107: =IF(J107="Completed",IF(I107<=H107,"On Time","Late Delivery"),IF(Settings!$B$2>H107,"Overdue","On Track")) -> On Track
A108: J0107 | B108: Q0328 | C108: C001 | D108: Machining | E108: Custom flange machining | F108: Segun Alabi | G108: 46310 | H108: 46326 | J108: In Progress | K108: Welding & Assembly | L108: 11248000 | M108: 204 | N108: 118 | O108: =N108-M108 -> -86 | P108: =IF(I108<>"",MAX(0,I108-H108),MAX(0,Settings!$B$2-H108)) -> 0 | Q108: =IF(J108="Completed",IF(I108<=H108,"On Time","Late Delivery"),IF(Settings!$B$2>H108,"Overdue","On Track")) -> On Track
A109: J0108 | B109: Q0329 | C109: C007 | D109: Coating | E109: Pipe external coating | F109: Segun Alabi | G109: 46310 | H109: 46349 | J109: In Progress | K109: Cutting & Machining | L109: 2791000 | M109: 50 | N109: 14 | O109: =N109-M109 -> -36 | P109: =IF(I109<>"",MAX(0,I109-H109),MAX(0,Settings!$B$2-H109)) -> 0 | Q109: =IF(J109="Completed",IF(I109<=H109,"On Time","Late Delivery"),IF(Settings!$B$2>H109,"Overdue","On Track")) -> On Track
A110: J0109 | B110: Q0331 | C110: C001 | D110: Pipe Thread Repair | E110: Tubing thread repair | F110: Femi Adeyemi | G110: 46324 | H110: 46351 | J110: Not Started | K110: - | L110: 2722000 | M110: 49 | N110: 0 | O110: =N110-M110 -> -49 | P110: =IF(I110<>"",MAX(0,I110-H110),MAX(0,Settings!$B$2-H110)) -> 0 | Q110: =IF(J110="Completed",IF(I110<=H110,"On Time","Late Delivery"),IF(Settings!$B$2>H110,"Overdue","On Track")) -> On Track
A111: J0110 | B111: Q0332 | C111: C004 | D111: Machining | E111: Gearbox housing machining | F111: Segun Alabi | G111: 46330 | H111: 46348 | J111: Not Started | K111: - | L111: 3148000 | M111: 57 | N111: 0 | O111: =N111-M111 -> -57 | P111: =IF(I111<>"",MAX(0,I111-H111),MAX(0,Settings!$B$2-H111)) -> 0 | Q111: =IF(J111="Completed",IF(I111<=H111,"On Time","Late Delivery"),IF(Settings!$B$2>H111,"Overdue","On Track")) -> On Track
... A120: J0119 | B120: Q0353 | C120: C003 | D120: Fabrication | E120: Wellhead skid fabrication | F120: Femi Adeyemi | G120: 46327 | H120: 46381 | J120: Not Started | K120: - | L120: 12104000 | M120: 220 | N120: 0 | O120: =N120-M120 -> -220 | P120: =IF(I120<>"",MAX(0,I120-H120),MAX(0,Settings!$B$2-H120)) -> 0 | Q120: =IF(J120="Completed",IF(I120<=H120,"On Time","Late Delivery"),IF(Settings!$B$2>H120,"Overdue","On Track")) -> On Track

Sheet Inventory
A1: Month | B1: ItemID | C1: Opening Qty | D1: Inbound Qty | E1: Outbound Qty | F1: Closing Qty | G1: Unit Cost | H1: Stock Value | I1: Below Reorder Level?
A2: 45658 | B2: I101 | C2: 16 | D2: 0 | E2: 2 | F2: =C2+D2-E2 -> 14 | G2: 420000 | H2: =F2*G2 -> 5880000 | I2: =IF(F2<VLOOKUP(B2,Items!$A$2:$I$24,9,FALSE()),"Yes","No") -> No
A3: 45689 | B3: I101 | C3: 14 | D3: 0 | E3: 0 | F3: =C3+D3-E3 -> 14 | G3: 420000 | H3: =F3*G3 -> 5880000 | I3: =IF(F3<VLOOKUP(B3,Items!$A$2:$I$24,9,FALSE()),"Yes","No") -> No
A4: 45717 | B4: I101 | C4: 14 | D4: 0 | E4: 0 | F4: =C4+D4-E4 -> 14 | G4: 420000 | H4: =F4*G4 -> 5880000 | I4: =IF(F4<VLOOKUP(B4,Items!$A$2:$I$24,9,FALSE()),"Yes","No") -> No
A5: 45748 | B5: I101 | C5: 14 | D5: 0 | E5: 0 | F5: =C5+D5-E5 -> 14 | G5: 420000 | H5: =F5*G5 -> 5880000 | I5: =IF(F5<VLOOKUP(B5,Items!$A$2:$I$24,9,FALSE()),"Yes","No") -> No
A6: 45778 | B6: I101 | C6: 14 | D6: 0 | E6: 4 | F6: =C6+D6-E6 -> 10 | G6: 420000 | H6: =F6*G6 -> 4200000 | I6: =IF(F6<VLOOKUP(B6,Items!$A$2:$I$24,9,FALSE()),"Yes","No") -> No
A7: 45809 | B7: I101 | C7: 10 | D7: 0 | E7: 3 | F7: =C7+D7-E7 -> 7 | G7: 420000 | H7: =F7*G7 -> 2940000 | I7: =IF(F7<VLOOKUP(B7,Items!$A$2:$I$24,9,FALSE()),"Yes","No") -> Yes
A8: 45839 | B8: I101 | C8: 7 | D8: 0 | E8: 2 | F8: =C8+D8-E8 -> 5 | G8: 420000 | H8: =F8*G8 -> 2100000 | I8: =IF(F8<VLOOKUP(B8,Items!$A$2:$I$24,9,FALSE()),"Yes","No") -> Yes
A9: 45870 | B9: I101 | C9: 5 | D9: 21 | E9: 2 | F9: =C9+D9-E9 -> 24 | G9: 420000 | H9: =F9*G9 -> 10080000 | I9: =IF(F9<VLOOKUP(B9,Items!$A$2:$I$24,9,FALSE()),"Yes","No") -> No
A10: 45901 | B10: I101 | C10: 24 | D10: 0 | E10: 0 | F10: =C10+D10-E10 -> 24 | G10: 420000 | H10: =F10*G10 -> 10080000 | I10: =IF(F10<VLOOKUP(B10,Items!$A$2:$I$24,9,FALSE()),"Yes","No") -> No
A11: 45931 | B11: I101 | C11: 24 | D11: 0 | E11: 0 | F11: =C11+D11-E11 -> 24 | G11: 420000 | H11: =F11*G11 -> 10080000 | I11: =IF(F11<VLOOKUP(B11,Items!$A$2:$I$24,9,FALSE()),"Yes","No") -> No
A12: 45962 | B12: I101 | C12: 24 | D12: 0 | E12: 5 | F12: =C12+D12-E12 -> 19 | G12: 420000 | H12: =F12*G12 -> 7980000 | I12: =IF(F12<VLOOKUP(B12,Items!$A$2:$I$24,9,FALSE()),"Yes","No") -> No
A13: 45992 | B13: I101 | C13: 19 | D13: 8 | E13: 0 | F13: =C13+D13-E13 -> 27 | G13: 420000 | H13: =F13*G13 -> 11340000 | I13: =IF(F13<VLOOKUP(B13,Items!$A$2:$I$24,9,FALSE()),"Yes","No") -> No
... A309: 46296 | B309: I114 | C309: 10 | D309: 10 | E309: 8 | F309: =C309+D309-E309 -> 12 | G309: 1100000 | H309: =F309*G309 -> 13200000 | I309: =IF(F309<VLOOKUP(B309,Items!$A$2:$I$24,9,FALSE()),"Yes","No") -> No

Sheet Invoices
A1: InvoiceID | B1: OrderNo | C1: Invoice Date | D1: CustomerID | E1: Invoice Amount | F1: Payment Terms (Days) | G1: Due Date | H1: Payment Date | I1: Amount Paid | J1: Balance | K1: Status | L1: Days Overdue | M1: Ageing Bucket
A2: INV-00001 | B2: SO-2025-0001 | C2: 45675 | D2: C003 | E2: =SUMIFS(Sales!$L$2:$L$759,Sales!$B$2:$B$759,B2) -> 48419642 | F2: 45 | G2: =C2+F2 -> 45720 | H2: 45745 | I2: 48419642 | J2: =ROUND(E2-I2,0) -> 0 | K2: =IF(J2<=0,"Paid",IF(G2<Settings!$B$2,"Overdue","Open")) -> Paid | L2: =IF(J2>0,MAX(0,Settings!$B$2-G2),0) -> 0 | M2: =IF(J2<=0,"Paid",IF(L2=0,"Current",IF(L2<=30,"1-30",IF(L2<=60,"31-60",IF(L2<=90,"61-90","90+"))))) -> Paid
A3: INV-00002 | B3: SO-2025-0002 | C3: 45668 | D3: C002 | E3: =SUMIFS(Sales!$L$2:$L$759,Sales!$B$2:$B$759,B3) -> 13926288 | F3: 45 | G3: =C3+F3 -> 45713 | H3: 45732 | I3: 13926288 | J3: =ROUND(E3-I3,0) -> 0 | K3: =IF(J3<=0,"Paid",IF(G3<Settings!$B$2,"Overdue","Open")) -> Paid | L3: =IF(J3>0,MAX(0,Settings!$B$2-G3),0) -> 0 | M3: =IF(J3<=0,"Paid",IF(L3=0,"Current",IF(L3<=30,"1-30",IF(L3<=60,"31-60",IF(L3<=90,"61-90","90+"))))) -> Paid
A4: INV-00003 | B4: SO-2025-0003 | C4: 45672 | D4: C004 | E4: =SUMIFS(Sales!$L$2:$L$759,Sales!$B$2:$B$759,B4) -> 30259400 | F4: 30 | G4: =C4+F4 -> 45702 | H4: 45726 | I4: 30259400 | J4: =ROUND(E4-I4,0) -> 0 | K4: =IF(J4<=0,"Paid",IF(G4<Settings!$B$2,"Overdue","Open")) -> Paid | L4: =IF(J4>0,MAX(0,Settings!$B$2-G4),0) -> 0 | M4: =IF(J4<=0,"Paid",IF(L4=0,"Current",IF(L4<=30,"1-30",IF(L4<=60,"31-60",IF(L4<=90,"61-90","90+"))))) -> Paid
A5: INV-00004 | B5: SO-2025-0004 | C5: 45679 | D5: C009 | E5: =SUMIFS(Sales!$L$2:$L$759,Sales!$B$2:$B$759,B5) -> 16632600 | F5: 45 | G5: =C5+F5 -> 45724 | H5: 45754 | I5: 16632600 | J5: =ROUND(E5-I5,0) -> 0 | K5: =IF(J5<=0,"Paid",IF(G5<Settings!$B$2,"Overdue","Open")) -> Paid | L5: =IF(J5>0,MAX(0,Settings!$B$2-G5),0) -> 0 | M5: =IF(J5<=0,"Paid",IF(L5=0,"Current",IF(L5<=30,"1-30",IF(L5<=60,"31-60",IF(L5<=90,"61-90","90+"))))) -> Paid
A6: INV-00005 | B6: SO-2025-0005 | C6: 45676 | D6: C002 | E6: =SUMIFS(Sales!$L$2:$L$759,Sales!$B$2:$B$759,B6) -> 2754000 | F6: 45 | G6: =C6+F6 -> 45721 | H6: 45685 | I6: 2754000 | J6: =ROUND(E6-I6,0) -> 0 | K6: =IF(J6<=0,"Paid",IF(G6<Settings!$B$2,"Overdue","Open")) -> Paid | L6: =IF(J6>0,MAX(0,Settings!$B$2-G6),0) -> 0 | M6: =IF(J6<=0,"Paid",IF(L6=0,"Current",IF(L6<=30,"1-30",IF(L6<=60,"31-60",IF(L6<=90,"61-90","90+"))))) -> Paid
A7: INV-00006 | B7: SO-2025-0006 | C7: 45682 | D7: C002 | E7: =SUMIFS(Sales!$L$2:$L$759,Sales!$B$2:$B$759,B7) -> 16087600 | F7: 45 | G7: =C7+F7 -> 45727 | H7: 45725 | I7: 16087600 | J7: =ROUND(E7-I7,0) -> 0 | K7: =IF(J7<=0,"Paid",IF(G7<Settings!$B$2,"Overdue","Open")) -> Paid | L7: =IF(J7>0,MAX(0,Settings!$B$2-G7),0) -> 0 | M7: =IF(J7<=0,"Paid",IF(L7=0,"Current",IF(L7<=30,"1-30",IF(L7<=60,"31-60",IF(L7<=90,"61-90","90+"))))) -> Paid
A8: INV-00007 | B8: SO-2025-0007 | C8: 45675 | D8: C008 | E8: =SUMIFS(Sales!$L$2:$L$759,Sales!$B$2:$B$759,B8) -> 9421700 | F8: 60 | G8: =C8+F8 -> 45735 | H8: 45750 | I8: 9421700 | J8: =ROUND(E8-I8,0) -> 0 | K8: =IF(J8<=0,"Paid",IF(G8<Settings!$B$2,"Overdue","Open")) -> Paid | L8: =IF(J8>0,MAX(0,Settings!$B$2-G8),0) -> 0 | M8: =IF(J8<=0,"Paid",IF(L8=0,"Current",IF(L8<=30,"1-30",IF(L8<=60,"31-60",IF(L8<=90,"61-90","90+"))))) -> Paid
A9: INV-00008 | B9: SO-2025-0008 | C9: 45687 | D9: C001 | E9: =SUMIFS(Sales!$L$2:$L$759,Sales!$B$2:$B$759,B9) -> 3728100 | F9: 30 | G9: =C9+F9 -> 45717 | H9: 45736 | I9: 3728100 | J9: =ROUND(E9-I9,0) -> 0 | K9: =IF(J9<=0,"Paid",IF(G9<Settings!$B$2,"Overdue","Open")) -> Paid | L9: =IF(J9>0,MAX(0,Settings!$B$2-G9),0) -> 0 | M9: =IF(J9<=0,"Paid",IF(L9=0,"Current",IF(L9<=30,"1-30",IF(L9<=60,"31-60",IF(L9<=90,"61-90","90+"))))) -> Paid
A10: INV-00009 | B10: SO-2025-0009 | C10: 45686 | D10: C001 | E10: =SUMIFS(Sales!$L$2:$L$759,Sales!$B$2:$B$759,B10) -> 30514600 | F10: 30 | G10: =C10+F10 -> 45716 | H10: 45717 | I10: 30514600 | J10: =ROUND(E10-I10,0) -> 0 | K10: =IF(J10<=0,"Paid",IF(G10<Settings!$B$2,"Overdue","Open")) -> Paid | L10: =IF(J10>0,MAX(0,Settings!$B$2-G10),0) -> 0 | M10: =IF(J10<=0,"Paid",IF(L10=0,"Current",IF(L10<=30,"1-30",IF(L10<=60,"31-60",IF(L10<=90,"61-90","90+"))))) -> Paid
A11: INV-00010 | B11: SO-2025-0010 | C11: 45681 | D11: C002 | E11: =SUMIFS(Sales!$L$2:$L$759,Sales!$B$2:$B$759,B11) -> 4660600 | F11: 45 | G11: =C11+F11 -> 45726 | H11: 45738 | I11: 4660600 | J11: =ROUND(E11-I11,0) -> 0 | K11: =IF(J11<=0,"Paid",IF(G11<Settings!$B$2,"Overdue","Open")) -> Paid | L11: =IF(J11>0,MAX(0,Settings!$B$2-G11),0) -> 0 | M11: =IF(J11<=0,"Paid",IF(L11=0,"Current",IF(L11<=30,"1-30",IF(L11<=60,"31-60",IF(L11<=90,"61-90","90+"))))) -> Paid
A12: INV-00011 | B12: SO-2025-0011 | C12: 45695 | D12: C004 | E12: =SUMIFS(Sales!$L$2:$L$759,Sales!$B$2:$B$759,B12) -> 4933700 | F12: 30 | G12: =C12+F12 -> 45725 | H12: 45741 | I12: 4933700 | J12: =ROUND(E12-I12,0) -> 0 | K12: =IF(J12<=0,"Paid",IF(G12<Settings!$B$2,"Overdue","Open")) -> Paid | L12: =IF(J12>0,MAX(0,Settings!$B$2-G12),0) -> 0 | M12: =IF(J12<=0,"Paid",IF(L12=0,"Current",IF(L12<=30,"1-30",IF(L12<=60,"31-60",IF(L12<=90,"61-90","90+"))))) -> Paid
A13: INV-00012 | B13: SO-2025-0012 | C13: 45687 | D13: C014 | E13: =SUMIFS(Sales!$L$2:$L$759,Sales!$B$2:$B$759,B13) -> 38292800 | F13: 45 | G13: =C13+F13 -> 45732 | H13: 45746 | I13: 38292800 | J13: =ROUND(E13-I13,0) -> 0 | K13: =IF(J13<=0,"Paid",IF(G13<Settings!$B$2,"Overdue","Open")) -> Paid | L13: =IF(J13>0,MAX(0,Settings!$B$2-G13),0) -> 0 | M13: =IF(J13<=0,"Paid",IF(L13=0,"Current",IF(L13<=30,"1-30",IF(L13<=60,"31-60",IF(L13<=90,"61-90","90+"))))) -> Paid
A14: INV-00013 | B14: SO-2025-0013 | C14: 45683 | D14: C010 | E14: =SUMIFS(Sales!$L$2:$L$759,Sales!$B$2:$B$759,B14) -> 7230292 | F14: 30 | G14: =C14+F14 -> 45713 | H14: 45746 | I14: 7230292 | J14: =ROUND(E14-I14,0) -> 0 | K14: =IF(J14<=0,"Paid",IF(G14<Settings!$B$2,"Overdue","Open")) -> Paid | L14: =IF(J14>0,MAX(0,Settings!$B$2-G14),0) -> 0 | M14: =IF(J14<=0,"Paid",IF(L14=0,"Current",IF(L14<=30,"1-30",IF(L14<=60,"31-60",IF(L14<=90,"61-90","90+"))))) -> Paid
A15: INV-00014 | B15: SO-2025-0014 | C15: 45694 | D15: C007 | E15: =SUMIFS(Sales!$L$2:$L$759,Sales!$B$2:$B$759,B15) -> 18151800 | F15: 30 | G15: =C15+F15 -> 45724 | I15: 0 | J15: =ROUND(E15-I15,0) -> 18151800 | K15: =IF(J15<=0,"Paid",IF(G15<Settings!$B$2,"Overdue","Open")) -> Overdue | L15: =IF(J15>0,MAX(0,Settings!$B$2-G15),0) -> 596 | M15: =IF(J15<=0,"Paid",IF(L15=0,"Current",IF(L15<=30,"1-30",IF(L15<=60,"31-60",IF(L15<=90,"61-90","90+"))))) -> 90+
A16: INV-00015 | B16: SO-2025-0015 | C16: 45714 | D16: C004 | E16: =SUMIFS(Sales!$L$2:$L$759,Sales!$B$2:$B$759,B16) -> 990660 | F16: 30 | G16: =C16+F16 -> 45744 | H16: 45763 | I16: 990660 | J16: =ROUND(E16-I16,0) -> 0 | K16: =IF(J16<=0,"Paid",IF(G16<Settings!$B$2,"Overdue","Open")) -> Paid | L16: =IF(J16>0,MAX(0,Settings!$B$2-G16),0) -> 0 | M16: =IF(J16<=0,"Paid",IF(L16=0,"Current",IF(L16<=30,"1-30",IF(L16<=60,"31-60",IF(L16<=90,"61-90","90+"))))) -> Paid
A17: INV-00016 | B17: SO-2025-0016 | C17: 45712 | D17: C007 | E17: =SUMIFS(Sales!$L$2:$L$759,Sales!$B$2:$B$759,B17) -> 11152000 | F17: 30 | G17: =C17+F17 -> 45742 | H17: 45754 | I17: 11152000 | J17: =ROUND(E17-I17,0) -> 0 | K17: =IF(J17<=0,"Paid",IF(G17<Settings!$B$2,"Overdue","Open")) -> Paid | L17: =IF(J17>0,MAX(0,Settings!$B$2-G17),0) -> 0 | M17: =IF(J17<=0,"Paid",IF(L17=0,"Current",IF(L17<=30,"1-30",IF(L17<=60,"31-60",IF(L17<=90,"61-90","90+"))))) -> Paid
A18: INV-00017 | B18: SO-2025-0017 | C18: 45717 | D18: C001 | E18: =SUMIFS(Sales!$L$2:$L$759,Sales!$B$2:$B$759,B18) -> 2389200 | F18: 30 | G18: =C18+F18 -> 45747 | H18: 45782 | I18: 2389200 | J18: =ROUND(E18-I18,0) -> 0 | K18: =IF(J18<=0,"Paid",IF(G18<Settings!$B$2,"Overdue","Open")) -> Paid | L18: =IF(J18>0,MAX(0,Settings!$B$2-G18),0) -> 0 | M18: =IF(J18<=0,"Paid",IF(L18=0,"Current",IF(L18<=30,"1-30",IF(L18<=60,"31-60",IF(L18<=90,"61-90","90+"))))) -> Paid
A19: INV-00018 | B19: SO-2025-0018 | C19: 45719 | D19: C014 | E19: =SUMIFS(Sales!$L$2:$L$759,Sales!$B$2:$B$759,B19) -> 39721435 | F19: 45 | G19: =C19+F19 -> 45764 | H19: 45780 | I19: 39721435 | J19: =ROUND(E19-I19,0) -> 0 | K19: =IF(J19<=0,"Paid",IF(G19<Settings!$B$2,"Overdue","Open")) -> Paid | L19: =IF(J19>0,MAX(0,Settings!$B$2-G19),0) -> 0 | M19: =IF(J19<=0,"Paid",IF(L19=0,"Current",IF(L19<=30,"1-30",IF(L19<=60,"31-60",IF(L19<=90,"61-90","90+"))))) -> Paid
A20: INV-00019 | B20: SO-2025-0019 | C20: 45710 | D20: C013 | E20: =SUMIFS(Sales!$L$2:$L$759,Sales!$B$2:$B$759,B20) -> 39993000 | F20: 30 | G20: =C20+F20 -> 45740 | H20: 45749 | I20: 39993000 | J20: =ROUND(E20-I20,0) -> 0 | K20: =IF(J20<=0,"Paid",IF(G20<Settings!$B$2,"Overdue","Open")) -> Paid | L20: =IF(J20>0,MAX(0,Settings!$B$2-G20),0) -> 0 | M20: =IF(J20<=0,"Paid",IF(L20=0,"Current",IF(L20<=30,"1-30",IF(L20<=60,"31-60",IF(L20<=90,"61-90","90+"))))) -> Paid
A21: INV-00020 | B21: SO-2025-0020 | C21: 45715 | D21: C003 | E21: =SUMIFS(Sales!$L$2:$L$759,Sales!$B$2:$B$759,B21) -> 29517400 | F21: 45 | G21: =C21+F21 -> 45760 | H21: 45772 | I21: 29517400 | J21: =ROUND(E21-I21,0) -> 0 | K21: =IF(J21<=0,"Paid",IF(G21<Settings!$B$2,"Overdue","Open")) -> Paid | L21: =IF(J21>0,MAX(0,Settings!$B$2-G21),0) -> 0 | M21: =IF(J21<=0,"Paid",IF(L21=0,"Current",IF(L21<=30,"1-30",IF(L21<=60,"31-60",IF(L21<=90,"61-90","90+"))))) -> Paid
A22: INV-00021 | B22: SO-2025-0021 | C22: 45729 | D22: C006 | E22: =SUMIFS(Sales!$L$2:$L$759,Sales!$B$2:$B$759,B22) -> 970400 | F22: 45 | G22: =C22+F22 -> 45774 | H22: 45799 | I22: 970400 | J22: =ROUND(E22-I22,0) -> 0 | K22: =IF(J22<=0,"Paid",IF(G22<Settings!$B$2,"Overdue","Open")) -> Paid | L22: =IF(J22>0,MAX(0,Settings!$B$2-G22),0) -> 0 | M22: =IF(J22<=0,"Paid",IF(L22=0,"Current",IF(L22<=30,"1-30",IF(L22<=60,"31-60",IF(L22<=90,"61-90","90+"))))) -> Paid
A23: INV-00022 | B23: SO-2025-0022 | C23: 45730 | D23: C009 | E23: =SUMIFS(Sales!$L$2:$L$759,Sales!$B$2:$B$759,B23) -> 1605600 | F23: 45 | G23: =C23+F23 -> 45775 | H23: 45825 | I23: 1605600 | J23: =ROUND(E23-I23,0) -> 0 | K23: =IF(J23<=0,"Paid",IF(G23<Settings!$B$2,"Overdue","Open")) -> Paid | L23: =IF(J23>0,MAX(0,Settings!$B$2-G23),0) -> 0 | M23: =IF(J23<=0,"Paid",IF(L23=0,"Current",IF(L23<=30,"1-30",IF(L23<=60,"31-60",IF(L23<=90,"61-90","90+"))))) -> Paid
A24: INV-00023 | B24: SO-2025-0023 | C24: 45733 | D24: C001 | E24: =SUMIFS(Sales!$L$2:$L$759,Sales!$B$2:$B$759,B24) -> 32476600 | F24: 30 | G24: =C24+F24 -> 45763 | H24: 45784 | I24: 27141885 | J24: =ROUND(E24-I24,0) -> 5334715 | K24: =IF(J24<=0,"Paid",IF(G24<Settings!$B$2,"Overdue","Open")) -> Overdue | L24: =IF(J24>0,MAX(0,Settings!$B$2-G24),0) -> 557 | M24: =IF(J24<=0,"Paid",IF(L24=0,"Current",IF(L24<=30,"1-30",IF(L24<=60,"31-60",IF(L24<=90,"61-90","90+"))))) -> 90+
A25: INV-00024 | B25: SO-2025-0024 | C25: 45735 | D25: C010 | E25: =SUMIFS(Sales!$L$2:$L$759,Sales!$B$2:$B$759,B25) -> 3249900 | F25: 30 | G25: =C25+F25 -> 45765 | H25: 45807 | I25: 3249900 | J25: =ROUND(E25-I25,0) -> 0 | K25: =IF(J25<=0,"Paid",IF(G25<Settings!$B$2,"Overdue","Open")) -> Paid | L25: =IF(J25>0,MAX(0,Settings!$B$2-G25),0) -> 0 | M25: =IF(J25<=0,"Paid",IF(L25=0,"Current",IF(L25<=30,"1-30",IF(L25<=60,"31-60",IF(L25<=90,"61-90","90+"))))) -> Paid
A26: INV-00025 | B26: SO-2025-0025 | C26: 45742 | D26: C004 | E26: =SUMIFS(Sales!$L$2:$L$759,Sales!$B$2:$B$759,B26) -> 2967600 | F26: 30 | G26: =C26+F26 -> 45772 | H26: 45797 | I26: 2967600 | J26: =ROUND(E26-I26,0) -> 0 | K26: =IF(J26<=0,"Paid",IF(G26<Settings!$B$2,"Overdue","Open")) -> Paid | L26: =IF(J26>0,MAX(0,Settings!$B$2-G26),0) -> 0 | M26: =IF(J26<=0,"Paid",IF(L26=0,"Current",IF(L26<=30,"1-30",IF(L26<=60,"31-60",IF(L26<=90,"61-90","90+"))))) -> Paid
A27: INV-00026 | B27: SO-2025-0026 | C27: 45744 | D27: C007 | E27: =SUMIFS(Sales!$L$2:$L$759,Sales!$B$2:$B$759,B27) -> 1314200 | F27: 30 | G27: =C27+F27 -> 45774 | H27: 45777 | I27: 1314200 | J27: =ROUND(E27-I27,0) -> 0 | K27: =IF(J27<=0,"Paid",IF(G27<Settings!$B$2,"Overdue","Open")) -> Paid | L27: =IF(J27>0,MAX(0,Settings!$B$2-G27),0) -> 0 | M27: =IF(J27<=0,"Paid",IF(L27=0,"Current",IF(L27<=30,"1-30",IF(L27<=60,"31-60",IF(L27<=90,"61-90","90+"))))) -> Paid
... A42: INV-00041 | B42: SO-2025-0041 | C42: 45755 | D42: C004 | E42: =SUMIFS(Sales!$L$2:$L$759,Sales!$B$2:$B$759,B42) -> 9068700 | F42: 30 | G42: =C42+F42 -> 45785 | H42: 45811 | I42: 9068700 | J42: =ROUND(E42-I42,0) -> 0 | K42: =IF(J42<=0,"Paid",IF(G42<Settings!$B$2,"Overdue","Open")) -> Paid | L42: =IF(J42>0,MAX(0,Settings!$B$2-G42),0) -> 0 | M42: =IF(J42<=0,"Paid",IF(L42=0,"Current",IF(L42<=30,"1-30",IF(L42<=60,"31-60",IF(L42<=90,"61-90","90+"))))) -> Paid
A43: INV-00042 | B43: SO-2025-0042 | C43: 45771 | D43: C002 | E43: =SUMIFS(Sales!$L$2:$L$759,Sales!$B$2:$B$759,B43) -> 51779116 | F43: 45 | G43: =C43+F43 -> 45816 | I43: 0 | J43: =ROUND(E43-I43,0) -> 51779116 | K43: =IF(J43<=0,"Paid",IF(G43<Settings!$B$2,"Overdue","Open")) -> Overdue | L43: =IF(J43>0,MAX(0,Settings!$B$2-G43),0) -> 504 | M43: =IF(J43<=0,"Paid",IF(L43=0,"Current",IF(L43<=30,"1-30",IF(L43<=60,"31-60",IF(L43<=90,"61-90","90+"))))) -> 90+
A44: INV-00043 | B44: SO-2025-0043 | C44: 45770 | D44: C002 | E44: =SUMIFS(Sales!$L$2:$L$759,Sales!$B$2:$B$759,B44) -> 3399700 | F44: 45 | G44: =C44+F44 -> 45815 | H44: 45797 | I44: 1575278 | J44: =ROUND(E44-I44,0) -> 1824422 | K44: =IF(J44<=0,"Paid",IF(G44<Settings!$B$2,"Overdue","Open")) -> Overdue | L44: =IF(J44>0,MAX(0,Settings!$B$2-G44),0) -> 505 | M44: =IF(J44<=0,"Paid",IF(L44=0,"Current",IF(L44<=30,"1-30",IF(L44<=60,"31-60",IF(L44<=90,"61-90","90+"))))) -> 90+
A45: INV-00044 | B45: SO-2025-0044 | C45: 45768 | D45: C002 | E45: =SUMIFS(Sales!$L$2:$L$759,Sales!$B$2:$B$759,B45) -> 1738800 | F45: 45 | G45: =C45+F45 -> 45813 | H45: 45808 | I45: 1738800 | J45: =ROUND(E45-I45,0) -> 0 | K45: =IF(J45<=0,"Paid",IF(G45<Settings!$B$2,"Overdue","Open")) -> Paid | L45: =IF(J45>0,MAX(0,Settings!$B$2-G45),0) -> 0 | M45: =IF(J45<=0,"Paid",IF(L45=0,"Current",IF(L45<=30,"1-30",IF(L45<=60,"31-60",IF(L45<=90,"61-90","90+"))))) -> Paid
A46: INV-00045 | B46: SO-2025-0045 | C46: 45776 | D46: C008 | E46: =SUMIFS(Sales!$L$2:$L$759,Sales!$B$2:$B$759,B46) -> 6473200 | F46: 60 | G46: =C46+F46 -> 45836 | H46: 45874 | I46: 6473200 | J46: =ROUND(E46-I46,0) -> 0 | K46: =IF(J46<=0,"Paid",IF(G46<Settings!$B$2,"Overdue","Open")) -> Paid | L46: =IF(J46>0,MAX(0,Settings!$B$2-G46),0) -> 0 | M46: =IF(J46<=0,"Paid",IF(L46=0,"Current",IF(L46<=30,"1-30",IF(L46<=60,"31-60",IF(L46<=90,"61-90","90+"))))) -> Paid
A47: INV-00046 | B47: SO-2025-0046 | C47: 45771 | D47: C010 | E47: =SUMIFS(Sales!$L$2:$L$759,Sales!$B$2:$B$759,B47) -> 5288800 | F47: 30 | G47: =C47+F47 -> 45801 | H47: 45826 | I47: 5288800 | J47: =ROUND(E47-I47,0) -> 0 | K47: =IF(J47<=0,"Paid",IF(G47<Settings!$B$2,"Overdue","Open")) -> Paid | L47: =IF(J47>0,MAX(0,Settings!$B$2-G47),0) -> 0 | M47: =IF(J47<=0,"Paid",IF(L47=0,"Current",IF(L47<=30,"1-30",IF(L47<=60,"31-60",IF(L47<=90,"61-90","90+"))))) -> Paid
A48: INV-00047 | B48: SO-2025-0047 | C48: 45781 | D48: C004 | E48: =SUMIFS(Sales!$L$2:$L$759,Sales!$B$2:$B$759,B48) -> 53926400 | F48: 30 | G48: =C48+F48 -> 45811 | H48: 45825 | I48: 53926400 | J48: =ROUND(E48-I48,0) -> 0 | K48: =IF(J48<=0,"Paid",IF(G48<Settings!$B$2,"Overdue","Open")) -> Paid | L48: =IF(J48>0,MAX(0,Settings!$B$2-G48),0) -> 0 | M48: =IF(J48<=0,"Paid",IF(L48=0,"Current",IF(L48<=30,"1-30",IF(L48<=60,"31-60",IF(L48<=90,"61-90","90+"))))) -> Paid
A49: INV-00048 | B49: SO-2025-0048 | C49: 45786 | D49: C002 | E49: =SUMIFS(Sales!$L$2:$L$759,Sales!$B$2:$B$759,B49) -> 5709600 | F49: 45 | G49: =C49+F49 -> 45831 | H49: 45822 | I49: 5709600 | J49: =ROUND(E49-I49,0) -> 0 | K49: =IF(J49<=0,"Paid",IF(G49<Settings!$B$2,"Overdue","Open")) -> Paid | L49: =IF(J49>0,MAX(0,Settings!$B$2-G49),0) -> 0 | M49: =IF(J49<=0,"Paid",IF(L49=0,"Current",IF(L49<=30,"1-30",IF(L49<=60,"31-60",IF(L49<=90,"61-90","90+"))))) -> Paid
A50: INV-00049 | B50: SO-2025-0049 | C50: 45780 | D50: C001 | E50: =SUMIFS(Sales!$L$2:$L$759,Sales!$B$2:$B$759,B50) -> 55271860 | F50: 30 | G50: =C50+F50 -> 45810 | H50: 45801 | I50: 55271860 | J50: =ROUND(E50-I50,0) -> 0 | K50: =IF(J50<=0,"Paid",IF(G50<Settings!$B$2,"Overdue","Open")) -> Paid | L50: =IF(J50>0,MAX(0,Settings!$B$2-G50),0) -> 0 | M50: =IF(J50<=0,"Paid",IF(L50=0,"Current",IF(L50<=30,"1-30",IF(L50<=60,"31-60",IF(L50<=90,"61-90","90+"))))) -> Paid
A51: INV-00050 | B51: SO-2025-0050 | C51: 45790 | D51: C003 | E51: =SUMIFS(Sales!$L$2:$L$759,Sales!$B$2:$B$759,B51) -> 24743650 | F51: 45 | G51: =C51+F51 -> 45835 | H51: 45849 | I51: 24743650 | J51: =ROUND(E51-I51,0) -> 0 | K51: =IF(J51<=0,"Paid",IF(G51<Settings!$B$2,"Overdue","Open")) -> Paid | L51: =IF(J51>0,MAX(0,Settings!$B$2-G51),0) -> 0 | M51: =IF(J51<=0,"Paid",IF(L51=0,"Current",IF(L51<=30,"1-30",IF(L51<=60,"31-60",IF(L51<=90,"61-90","90+"))))) -> Paid
A52: INV-00051 | B52: SO-2025-0051 | C52: 45792 | D52: C012 | E52: =SUMIFS(Sales!$L$2:$L$759,Sales!$B$2:$B$759,B52) -> 4219500 | F52: 45 | G52: =C52+F52 -> 45837 | H52: 45841 | I52: 3611995.8 | J52: =ROUND(E52-I52,0) -> 607504 | K52: =IF(J52<=0,"Paid",IF(G52<Settings!$B$2,"Overdue","Open")) -> Overdue | L52: =IF(J52>0,MAX(0,Settings!$B$2-G52),0) -> 483 | M52: =IF(J52<=0,"Paid",IF(L52=0,"Current",IF(L52<=30,"1-30",IF(L52<=60,"31-60",IF(L52<=90,"61-90","90+"))))) -> 90+
A53: INV-00052 | B53: SO-2025-0052 | C53: 45792 | D53: C014 | E53: =SUMIFS(Sales!$L$2:$L$759,Sales!$B$2:$B$759,B53) -> 3639000 | F53: 45 | G53: =C53+F53 -> 45837 | H53: 45867 | I53: 3639000 | J53: =ROUND(E53-I53,0) -> 0 | K53: =IF(J53<=0,"Paid",IF(G53<Settings!$B$2,"Overdue","Open")) -> Paid | L53: =IF(J53>0,MAX(0,Settings!$B$2-G53),0) -> 0 | M53: =IF(J53<=0,"Paid",IF(L53=0,"Current",IF(L53<=30,"1-30",IF(L53<=60,"31-60",IF(L53<=90,"61-90","90+"))))) -> Paid
A54: INV-00053 | B54: SO-2025-0053 | C54: 45782 | D54: C002 | E54: =SUMIFS(Sales!$L$2:$L$759,Sales!$B$2:$B$759,B54) -> 14611800 | F54: 45 | G54: =C54+F54 -> 45827 | H54: 45843 | I54: 14611800 | J54: =ROUND(E54-I54,0) -> 0 | K54: =IF(J54<=0,"Paid",IF(G54<Settings!$B$2,"Overdue","Open")) -> Paid | L54: =IF(J54>0,MAX(0,Settings!$B$2-G54),0) -> 0 | M54: =IF(J54<=0,"Paid",IF(L54=0,"Current",IF(L54<=30,"1-30",IF(L54<=60,"31-60",IF(L54<=90,"61-90","90+"))))) -> Paid
A55: INV-00054 | B55: SO-2025-0054 | C55: 45794 | D55: C007 | E55: =SUMIFS(Sales!$L$2:$L$759,Sales!$B$2:$B$759,B55) -> 13586400 | F55: 30 | G55: =C55+F55 -> 45824 | H55: 45822 | I55: 13586400 | J55: =ROUND(E55-I55,0) -> 0 | K55: =IF(J55<=0,"Paid",IF(G55<Settings!$B$2,"Overdue","Open")) -> Paid | L55: =IF(J55>0,MAX(0,Settings!$B$2-G55),0) -> 0 | M55: =IF(J55<=0,"Paid",IF(L55=0,"Current",IF(L55<=30,"1-30",IF(L55<=60,"31-60",IF(L55<=90,"61-90","90+"))))) -> Paid
... A57: INV-00056 | B57: SO-2025-0056 | C57: 45793 | D57: C005 | E57: =SUMIFS(Sales!$L$2:$L$759,Sales!$B$2:$B$759,B57) -> 9862400 | F57: 60 | G57: =C57+F57 -> 45853 | H57: 45873 | I57: 9862400 | J57: =ROUND(E57-I57,0) -> 0 | K57: =IF(J57<=0,"Paid",IF(G57<Settings!$B$2,"Overdue","Open")) -> Paid | L57: =IF(J57>0,MAX(0,Settings!$B$2-G57),0) -> 0 | M57: =IF(J57<=0,"Paid",IF(L57=0,"Current",IF(L57<=30,"1-30",IF(L57<=60,"31-60",IF(L57<=90,"61-90","90+"))))) -> Paid
A58: INV-00057 | B58: SO-2025-0057 | C58: 45801 | D58: C001 | E58: =SUMIFS(Sales!$L$2:$L$759,Sales!$B$2:$B$759,B58) -> 4033500 | F58: 30 | G58: =C58+F58 -> 45831 | I58: 0 | J58: =ROUND(E58-I58,0) -> 4033500 | K58: =IF(J58<=0,"Paid",IF(G58<Settings!$B$2,"Overdue","Open")) -> Overdue | L58: =IF(J58>0,MAX(0,Settings!$B$2-G58),0) -> 489 | M58: =IF(J58<=0,"Paid",IF(L58=0,"Current",IF(L58<=30,"1-30",IF(L58<=60,"31-60",IF(L58<=90,"61-90","90+"))))) -> 90+
A59: INV-00058 | B59: SO-2025-0058 | C59: 45798 | D59: C013 | E59: =SUMIFS(Sales!$L$2:$L$759,Sales!$B$2:$B$759,B59) -> 7861800 | F59: 30 | G59: =C59+F59 -> 45828 | H59: 45835 | I59: 7861800 | J59: =ROUND(E59-I59,0) -> 0 | K59: =IF(J59<=0,"Paid",IF(G59<Settings!$B$2,"Overdue","Open")) -> Paid | L59: =IF(J59>0,MAX(0,Settings!$B$2-G59),0) -> 0 | M59: =IF(J59<=0,"Paid",IF(L59=0,"Current",IF(L59<=30,"1-30",IF(L59<=60,"31-60",IF(L59<=90,"61-90","90+"))))) -> Paid
A60: INV-00059 | B60: SO-2025-0059 | C60: 45801 | D60: C008 | E60: =SUMIFS(Sales!$L$2:$L$759,Sales!$B$2:$B$759,B60) -> 9501000 | F60: 60 | G60: =C60+F60 -> 45861 | H60: 45891 | I60: 9501000 | J60: =ROUND(E60-I60,0) -> 0 | K60: =IF(J60<=0,"Paid",IF(G60<Settings!$B$2,"Overdue","Open")) -> Paid | L60: =IF(J60>0,MAX(0,Settings!$B$2-G60),0) -> 0 | M60: =IF(J60<=0,"Paid",IF(L60=0,"Current",IF(L60<=30,"1-30",IF(L60<=60,"31-60",IF(L60<=90,"61-90","90+"))))) -> Paid
A61: INV-00060 | B61: SO-2025-0060 | C61: 45790 | D61: C005 | E61: =SUMIFS(Sales!$L$2:$L$759,Sales!$B$2:$B$759,B61) -> 13363500 | F61: 60 | G61: =C61+F61 -> 45850 | H61: 45857 | I61: 13363500 | J61: =ROUND(E61-I61,0) -> 0 | K61: =IF(J61<=0,"Paid",IF(G61<Settings!$B$2,"Overdue","Open")) -> Paid | L61: =IF(J61>0,MAX(0,Settings!$B$2-G61),0) -> 0 | M61: =IF(J61<=0,"Paid",IF(L61=0,"Current",IF(L61<=30,"1-30",IF(L61<=60,"31-60",IF(L61<=90,"61-90","90+"))))) -> Paid
A62: INV-00061 | B62: SO-2025-0061 | C62: 45799 | D62: C004 | E62: =SUMIFS(Sales!$L$2:$L$759,Sales!$B$2:$B$759,B62) -> 3382400 | F62: 30 | G62: =C62+F62 -> 45829 | H62: 45844 | I62: 3382400 | J62: =ROUND(E62-I62,0) -> 0 | K62: =IF(J62<=0,"Paid",IF(G62<Settings!$B$2,"Overdue","Open")) -> Paid | L62: =IF(J62>0,MAX(0,Settings!$B$2-G62),0) -> 0 | M62: =IF(J62<=0,"Paid",IF(L62=0,"Current",IF(L62<=30,"1-30",IF(L62<=60,"31-60",IF(L62<=90,"61-90","90+"))))) -> Paid
A63: INV-00062 | B63: SO-2025-0062 | C63: 45808 | D63: C008 | E63: =SUMIFS(Sales!$L$2:$L$759,Sales!$B$2:$B$759,B63) -> 9077330 | F63: 60 | G63: =C63+F63 -> 45868 | H63: 45896 | I63: 9077330 | J63: =ROUND(E63-I63,0) -> 0 | K63: =IF(J63<=0,"Paid",IF(G63<Settings!$B$2,"Overdue","Open")) -> Paid | L63: =IF(J63>0,MAX(0,Settings!$B$2-G63),0) -> 0 | M63: =IF(J63<=0,"Paid",IF(L63=0,"Current",IF(L63<=30,"1-30",IF(L63<=60,"31-60",IF(L63<=90,"61-90","90+"))))) -> Paid
A64: INV-00063 | B64: SO-2025-0063 | C64: 45808 | D64: C002 | E64: =SUMIFS(Sales!$L$2:$L$759,Sales!$B$2:$B$759,B64) -> 23218600 | F64: 45 | G64: =C64+F64 -> 45853 | H64: 45853 | I64: 23218600 | J64: =ROUND(E64-I64,0) -> 0 | K64: =IF(J64<=0,"Paid",IF(G64<Settings!$B$2,"Overdue","Open")) -> Paid | L64: =IF(J64>0,MAX(0,Settings!$B$2-G64),0) -> 0 | M64: =IF(J64<=0,"Paid",IF(L64=0,"Current",IF(L64<=30,"1-30",IF(L64<=60,"31-60",IF(L64<=90,"61-90","90+"))))) -> Paid
A65: INV-00064 | B65: SO-2025-0064 | C65: 45805 | D65: C006 | E65: =SUMIFS(Sales!$L$2:$L$759,Sales!$B$2:$B$759,B65) -> 24055030 | F65: 45 | G65: =C65+F65 -> 45850 | H65: 45883 | I65: 24055030 | J65: =ROUND(E65-I65,0) -> 0 | K65: =IF(J65<=0,"Paid",IF(G65<Settings!$B$2,"Overdue","Open")) -> Paid | L65: =IF(J65>0,MAX(0,Settings!$B$2-G65),0) -> 0 | M65: =IF(J65<=0,"Paid",IF(L65=0,"Current",IF(L65<=30,"1-30",IF(L65<=60,"31-60",IF(L65<=90,"61-90","90+"))))) -> Paid
A66: INV-00065 | B66: SO-2025-0065 | C66: 45813 | D66: C010 | E66: =SUMIFS(Sales!$L$2:$L$759,Sales!$B$2:$B$759,B66) -> 16065000 | F66: 30 | G66: =C66+F66 -> 45843 | H66: 45856 | I66: 16065000 | J66: =ROUND(E66-I66,0) -> 0 | K66: =IF(J66<=0,"Paid",IF(G66<Settings!$B$2,"Overdue","Open")) -> Paid | L66: =IF(J66>0,MAX(0,Settings!$B$2-G66),0) -> 0 | M66: =IF(J66<=0,"Paid",IF(L66=0,"Current",IF(L66<=30,"1-30",IF(L66<=60,"31-60",IF(L66<=90,"61-90","90+"))))) -> Paid
A67: INV-00066 | B67: SO-2025-0066 | C67: 45824 | D67: C003 | E67: =SUMIFS(Sales!$L$2:$L$759,Sales!$B$2:$B$759,B67) -> 34860000 | F67: 45 | G67: =C67+F67 -> 45869 | H67: 45870 | I67: 34860000 | J67: =ROUND(E67-I67,0) -> 0 | K67: =IF(J67<=0,"Paid",IF(G67<Settings!$B$2,"Overdue","Open")) -> Paid | L67: =IF(J67>0,MAX(0,Settings!$B$2-G67),0) -> 0 | M67: =IF(J67<=0,"Paid",IF(L67=0,"Current",IF(L67<=30,"1-30",IF(L67<=60,"31-60",IF(L67<=90,"61-90","90+"))))) -> Paid
A68: INV-00067 | B68: SO-2025-0067 | C68: 45829 | D68: C003 | E68: =SUMIFS(Sales!$L$2:$L$759,Sales!$B$2:$B$759,B68) -> 6879400 | F68: 45 | G68: =C68+F68 -> 45874 | H68: 45900 | I68: 6879400 | J68: =ROUND(E68-I68,0) -> 0 | K68: =IF(J68<=0,"Paid",IF(G68<Settings!$B$2,"Overdue","Open")) -> Paid | L68: =IF(J68>0,MAX(0,Settings!$B$2-G68),0) -> 0 | M68: =IF(J68<=0,"Paid",IF(L68=0,"Current",IF(L68<=30,"1-30",IF(L68<=60,"31-60",IF(L68<=90,"61-90","90+"))))) -> Paid
A69: INV-00068 | B69: SO-2025-0068 | C69: 45825 | D69: C011 | E69: =SUMIFS(Sales!$L$2:$L$759,Sales!$B$2:$B$759,B69) -> 12744000 | F69: 60 | G69: =C69+F69 -> 45885 | H69: 45896 | I69: 12744000 | J69: =ROUND(E69-I69,0) -> 0 | K69: =IF(J69<=0,"Paid",IF(G69<Settings!$B$2,"Overdue","Open")) -> Paid | L69: =IF(J69>0,MAX(0,Settings!$B$2-G69),0) -> 0 | M69: =IF(J69<=0,"Paid",IF(L69=0,"Current",IF(L69<=30,"1-30",IF(L69<=60,"31-60",IF(L69<=90,"61-90","90+"))))) -> Paid
A70: INV-00069 | B70: SO-2025-0069 | C70: 45820 | D70: C003 | E70: =SUMIFS(Sales!$L$2:$L$759,Sales!$B$2:$B$759,B70) -> 10302600 | F70: 45 | G70: =C70+F70 -> 45865 | H70: 45884 | I70: 10302600 | J70: =ROUND(E70-I70,0) -> 0 | K70: =IF(J70<=0,"Paid",IF(G70<Settings!$B$2,"Overdue","Open")) -> Paid | L70: =IF(J70>0,MAX(0,Settings!$B$2-G70),0) -> 0 | M70: =IF(J70<=0,"Paid",IF(L70=0,"Current",IF(L70<=30,"1-30",IF(L70<=60,"31-60",IF(L70<=90,"61-90","90+"))))) -> Paid
... A244: INV-00243 | B244: SO-2026-0243 | C244: 46142 | D244: C009 | E244: =SUMIFS(Sales!$L$2:$L$759,Sales!$B$2:$B$759,B244) -> 9256500 | F244: 45 | G244: =C244+F244 -> 46187 | H244: 46214 | I244: 9256500 | J244: =ROUND(E244-I244,0) -> 0 | K244: =IF(J244<=0,"Paid",IF(G244<Settings!$B$2,"Overdue","Open")) -> Paid | L244: =IF(J244>0,MAX(0,Settings!$B$2-G244),0) -> 0 | M244: =IF(J244<=0,"Paid",IF(L244=0,"Current",IF(L244<=30,"1-30",IF(L244<=60,"31-60",IF(L244<=90,"61-90","90+"))))) -> Paid
A245: INV-00244 | B245: SO-2026-0244 | C245: 46150 | D245: C002 | E245: =SUMIFS(Sales!$L$2:$L$759,Sales!$B$2:$B$759,B245) -> 1379000 | F245: 45 | G245: =C245+F245 -> 46195 | I245: 0 | J245: =ROUND(E245-I245,0) -> 1379000 | K245: =IF(J245<=0,"Paid",IF(G245<Settings!$B$2,"Overdue","Open")) -> Overdue | L245: =IF(J245>0,MAX(0,Settings!$B$2-G245),0) -> 125 | M245: =IF(J245<=0,"Paid",IF(L245=0,"Current",IF(L245<=30,"1-30",IF(L245<=60,"31-60",IF(L245<=90,"61-90","90+"))))) -> 90+
A246: INV-00245 | B246: SO-2026-0245 | C246: 46144 | D246: C003 | E246: =SUMIFS(Sales!$L$2:$L$759,Sales!$B$2:$B$759,B246) -> 22076200 | F246: 45 | G246: =C246+F246 -> 46189 | H246: 46195 | I246: 22076200 | J246: =ROUND(E246-I246,0) -> 0 | K246: =IF(J246<=0,"Paid",IF(G246<Settings!$B$2,"Overdue","Open")) -> Paid | L246: =IF(J246>0,MAX(0,Settings!$B$2-G246),0) -> 0 | M246: =IF(J246<=0,"Paid",IF(L246=0,"Current",IF(L246<=30,"1-30",IF(L246<=60,"31-60",IF(L246<=90,"61-90","90+"))))) -> Paid
A247: INV-00246 | B247: SO-2026-0246 | C247: 46135 | D247: C002 | E247: =SUMIFS(Sales!$L$2:$L$759,Sales!$B$2:$B$759,B247) -> 24656520 | F247: 45 | G247: =C247+F247 -> 46180 | H247: 46197 | I247: 24656520 | J247: =ROUND(E247-I247,0) -> 0 | K247: =IF(J247<=0,"Paid",IF(G247<Settings!$B$2,"Overdue","Open")) -> Paid | L247: =IF(J247>0,MAX(0,Settings!$B$2-G247),0) -> 0 | M247: =IF(J247<=0,"Paid",IF(L247=0,"Current",IF(L247<=30,"1-30",IF(L247<=60,"31-60",IF(L247<=90,"61-90","90+"))))) -> Paid
A248: INV-00247 | B248: SO-2026-0247 | C248: 46137 | D248: C002 | E248: =SUMIFS(Sales!$L$2:$L$759,Sales!$B$2:$B$759,B248) -> 5779100 | F248: 45 | G248: =C248+F248 -> 46182 | H248: 46187 | I248: 4070015 | J248: =ROUND(E248-I248,0) -> 1709085 | K248: =IF(J248<=0,"Paid",IF(G248<Settings!$B$2,"Overdue","Open")) -> Overdue | L248: =IF(J248>0,MAX(0,Settings!$B$2-G248),0) -> 138 | M248: =IF(J248<=0,"Paid",IF(L248=0,"Current",IF(L248<=30,"1-30",IF(L248<=60,"31-60",IF(L248<=90,"61-90","90+"))))) -> 90+
A249: INV-00248 | B249: SO-2026-0248 | C249: 46152 | D249: C013 | E249: =SUMIFS(Sales!$L$2:$L$759,Sales!$B$2:$B$759,B249) -> 4617600 | F249: 30 | G249: =C249+F249 -> 46182 | H249: 46178 | I249: 4617600 | J249: =ROUND(E249-I249,0) -> 0 | K249: =IF(J249<=0,"Paid",IF(G249<Settings!$B$2,"Overdue","Open")) -> Paid | L249: =IF(J249>0,MAX(0,Settings!$B$2-G249),0) -> 0 | M249: =IF(J249<=0,"Paid",IF(L249=0,"Current",IF(L249<=30,"1-30",IF(L249<=60,"31-60",IF(L249<=90,"61-90","90+"))))) -> Paid
A250: INV-00249 | B250: SO-2026-0249 | C250: 46147 | D250: C001 | E250: =SUMIFS(Sales!$L$2:$L$759,Sales!$B$2:$B$759,B250) -> 11670036 | F250: 30 | G250: =C250+F250 -> 46177 | H250: 46204 | I250: 11670036 | J250: =ROUND(E250-I250,0) -> 0 | K250: =IF(J250<=0,"Paid",IF(G250<Settings!$B$2,"Overdue","Open")) -> Paid | L250: =IF(J250>0,MAX(0,Settings!$B$2-G250),0) -> 0 | M250: =IF(J250<=0,"Paid",IF(L250=0,"Current",IF(L250<=30,"1-30",IF(L250<=60,"31-60",IF(L250<=90,"61-90","90+"))))) -> Paid
A251: INV-00250 | B251: SO-2026-0250 | C251: 46148 | D251: C010 | E251: =SUMIFS(Sales!$L$2:$L$759,Sales!$B$2:$B$759,B251) -> 9866100 | F251: 30 | G251: =C251+F251 -> 46178 | H251: 46183 | I251: 9866100 | J251: =ROUND(E251-I251,0) -> 0 | K251: =IF(J251<=0,"Paid",IF(G251<Settings!$B$2,"Overdue","Open")) -> Paid | L251: =IF(J251>0,MAX(0,Settings!$B$2-G251),0) -> 0 | M251: =IF(J251<=0,"Paid",IF(L251=0,"Current",IF(L251<=30,"1-30",IF(L251<=60,"31-60",IF(L251<=90,"61-90","90+"))))) -> Paid
A252: INV-00251 | B252: SO-2026-0251 | C252: 46141 | D252: C003 | E252: =SUMIFS(Sales!$L$2:$L$759,Sales!$B$2:$B$759,B252) -> 1646400 | F252: 45 | G252: =C252+F252 -> 46186 | H252: 46208 | I252: 1646400 | J252: =ROUND(E252-I252,0) -> 0 | K252: =IF(J252<=0,"Paid",IF(G252<Settings!$B$2,"Overdue","Open")) -> Paid | L252: =IF(J252>0,MAX(0,Settings!$B$2-G252),0) -> 0 | M252: =IF(J252<=0,"Paid",IF(L252=0,"Current",IF(L252<=30,"1-30",IF(L252<=60,"31-60",IF(L252<=90,"61-90","90+"))))) -> Paid
A253: INV-00252 | B253: SO-2026-0252 | C253: 46142 | D253: C007 | E253: =SUMIFS(Sales!$L$2:$L$759,Sales!$B$2:$B$759,B253) -> 8250848 | F253: 30 | G253: =C253+F253 -> 46172 | H253: 46183 | I253: 8250848 | J253: =ROUND(E253-I253,0) -> 0 | K253: =IF(J253<=0,"Paid",IF(G253<Settings!$B$2,"Overdue","Open")) -> Paid | L253: =IF(J253>0,MAX(0,Settings!$B$2-G253),0) -> 0 | M253: =IF(J253<=0,"Paid",IF(L253=0,"Current",IF(L253<=30,"1-30",IF(L253<=60,"31-60",IF(L253<=90,"61-90","90+"))))) -> Paid
A254: INV-00253 | B254: SO-2026-0253 | C254: 46140 | D254: C005 | E254: =SUMIFS(Sales!$L$2:$L$759,Sales!$B$2:$B$759,B254) -> 15503300 | F254: 60 | G254: =C254+F254 -> 46200 | H254: 46232 | I254: 15503300 | J254: =ROUND(E254-I254,0) -> 0 | K254: =IF(J254<=0,"Paid",IF(G254<Settings!$B$2,"Overdue","Open")) -> Paid | L254: =IF(J254>0,MAX(0,Settings!$B$2-G254),0) -> 0 | M254: =IF(J254<=0,"Paid",IF(L254=0,"Current",IF(L254<=30,"1-30",IF(L254<=60,"31-60",IF(L254<=90,"61-90","90+"))))) -> Paid
A255: INV-00254 | B255: SO-2026-0254 | C255: 46143 | D255: C001 | E255: =SUMIFS(Sales!$L$2:$L$759,Sales!$B$2:$B$759,B255) -> 7682400 | F255: 30 | G255: =C255+F255 -> 46173 | H255: 46211 | I255: 7682400 | J255: =ROUND(E255-I255,0) -> 0 | K255: =IF(J255<=0,"Paid",IF(G255<Settings!$B$2,"Overdue","Open")) -> Paid | L255: =IF(J255>0,MAX(0,Settings!$B$2-G255),0) -> 0 | M255: =IF(J255<=0,"Paid",IF(L255=0,"Current",IF(L255<=30,"1-30",IF(L255<=60,"31-60",IF(L255<=90,"61-90","90+"))))) -> Paid
A256: INV-00255 | B256: SO-2026-0255 | C256: 46148 | D256: C001 | E256: =SUMIFS(Sales!$L$2:$L$759,Sales!$B$2:$B$759,B256) -> 18787734 | F256: 30 | G256: =C256+F256 -> 46178 | H256: 46176 | I256: 18787734 | J256: =ROUND(E256-I256,0) -> 0 | K256: =IF(J256<=0,"Paid",IF(G256<Settings!$B$2,"Overdue","Open")) -> Paid | L256: =IF(J256>0,MAX(0,Settings!$B$2-G256),0) -> 0 | M256: =IF(J256<=0,"Paid",IF(L256=0,"Current",IF(L256<=30,"1-30",IF(L256<=60,"31-60",IF(L256<=90,"61-90","90+"))))) -> Paid
A257: INV-00256 | B257: SO-2026-0256 | C257: 46151 | D257: C009 | E257: =SUMIFS(Sales!$L$2:$L$759,Sales!$B$2:$B$759,B257) -> 7201800 | F257: 45 | G257: =C257+F257 -> 46196 | H257: 46241 | I257: 7201800 | J257: =ROUND(E257-I257,0) -> 0 | K257: =IF(J257<=0,"Paid",IF(G257<Settings!$B$2,"Overdue","Open")) -> Paid | L257: =IF(J257>0,MAX(0,Settings!$B$2-G257),0) -> 0 | M257: =IF(J257<=0,"Paid",IF(L257=0,"Current",IF(L257<=30,"1-30",IF(L257<=60,"31-60",IF(L257<=90,"61-90","90+"))))) -> Paid
... A279: INV-00278 | B279: SO-2026-0278 | C279: 46191 | D279: C005 | E279: =SUMIFS(Sales!$L$2:$L$759,Sales!$B$2:$B$759,B279) -> 3078400 | F279: 60 | G279: =C279+F279 -> 46251 | H279: 46259 | I279: 3078400 | J279: =ROUND(E279-I279,0) -> 0 | K279: =IF(J279<=0,"Paid",IF(G279<Settings!$B$2,"Overdue","Open")) -> Paid | L279: =IF(J279>0,MAX(0,Settings!$B$2-G279),0) -> 0 | M279: =IF(J279<=0,"Paid",IF(L279=0,"Current",IF(L279<=30,"1-30",IF(L279<=60,"31-60",IF(L279<=90,"61-90","90+"))))) -> Paid
A280: INV-00279 | B280: SO-2026-0279 | C280: 46207 | D280: C008 | E280: =SUMIFS(Sales!$L$2:$L$759,Sales!$B$2:$B$759,B280) -> 1715700 | F280: 60 | G280: =C280+F280 -> 46267 | I280: 0 | J280: =ROUND(E280-I280,0) -> 1715700 | K280: =IF(J280<=0,"Paid",IF(G280<Settings!$B$2,"Overdue","Open")) -> Overdue | L280: =IF(J280>0,MAX(0,Settings!$B$2-G280),0) -> 53 | M280: =IF(J280<=0,"Paid",IF(L280=0,"Current",IF(L280<=30,"1-30",IF(L280<=60,"31-60",IF(L280<=90,"61-90","90+"))))) -> 31-60
A281: INV-00280 | B281: SO-2026-0280 | C281: 46196 | D281: C009 | E281: =SUMIFS(Sales!$L$2:$L$759,Sales!$B$2:$B$759,B281) -> 60862900 | F281: 45 | G281: =C281+F281 -> 46241 | H281: 46250 | I281: 60862900 | J281: =ROUND(E281-I281,0) -> 0 | K281: =IF(J281<=0,"Paid",IF(G281<Settings!$B$2,"Overdue","Open")) -> Paid | L281: =IF(J281>0,MAX(0,Settings!$B$2-G281),0) -> 0 | M281: =IF(J281<=0,"Paid",IF(L281=0,"Current",IF(L281<=30,"1-30",IF(L281<=60,"31-60",IF(L281<=90,"61-90","90+"))))) -> Paid
A282: INV-00281 | B282: SO-2026-0281 | C282: 46207 | D282: C003 | E282: =SUMIFS(Sales!$L$2:$L$759,Sales!$B$2:$B$759,B282) -> 14873600 | F282: 45 | G282: =C282+F282 -> 46252 | H282: 46279 | I282: 14873600 | J282: =ROUND(E282-I282,0) -> 0 | K282: =IF(J282<=0,"Paid",IF(G282<Settings!$B$2,"Overdue","Open")) -> Paid | L282: =IF(J282>0,MAX(0,Settings!$B$2-G282),0) -> 0 | M282: =IF(J282<=0,"Paid",IF(L282=0,"Current",IF(L282<=30,"1-30",IF(L282<=60,"31-60",IF(L282<=90,"61-90","90+"))))) -> Paid
A283: INV-00282 | B283: SO-2026-0282 | C283: 46202 | D283: C003 | E283: =SUMIFS(Sales!$L$2:$L$759,Sales!$B$2:$B$759,B283) -> 10729200 | F283: 45 | G283: =C283+F283 -> 46247 | H283: 46238 | I283: 10729200 | J283: =ROUND(E283-I283,0) -> 0 | K283: =IF(J283<=0,"Paid",IF(G283<Settings!$B$2,"Overdue","Open")) -> Paid | L283: =IF(J283>0,MAX(0,Settings!$B$2-G283),0) -> 0 | M283: =IF(J283<=0,"Paid",IF(L283=0,"Current",IF(L283<=30,"1-30",IF(L283<=60,"31-60",IF(L283<=90,"61-90","90+"))))) -> Paid
A284: INV-00283 | B284: SO-2026-0283 | C284: 46213 | D284: C008 | E284: =SUMIFS(Sales!$L$2:$L$759,Sales!$B$2:$B$759,B284) -> 25201600 | F284: 60 | G284: =C284+F284 -> 46273 | H284: 46298 | I284: 25201600 | J284: =ROUND(E284-I284,0) -> 0 | K284: =IF(J284<=0,"Paid",IF(G284<Settings!$B$2,"Overdue","Open")) -> Paid | L284: =IF(J284>0,MAX(0,Settings!$B$2-G284),0) -> 0 | M284: =IF(J284<=0,"Paid",IF(L284=0,"Current",IF(L284<=30,"1-30",IF(L284<=60,"31-60",IF(L284<=90,"61-90","90+"))))) -> Paid
A285: INV-00284 | B285: SO-2026-0284 | C285: 46218 | D285: C006 | E285: =SUMIFS(Sales!$L$2:$L$759,Sales!$B$2:$B$759,B285) -> 7728672 | F285: 45 | G285: =C285+F285 -> 46263 | H285: 46291 | I285: 7728672 | J285: =ROUND(E285-I285,0) -> 0 | K285: =IF(J285<=0,"Paid",IF(G285<Settings!$B$2,"Overdue","Open")) -> Paid | L285: =IF(J285>0,MAX(0,Settings!$B$2-G285),0) -> 0 | M285: =IF(J285<=0,"Paid",IF(L285=0,"Current",IF(L285<=30,"1-30",IF(L285<=60,"31-60",IF(L285<=90,"61-90","90+"))))) -> Paid
A286: INV-00285 | B286: SO-2026-0285 | C286: 46201 | D286: C001 | E286: =SUMIFS(Sales!$L$2:$L$759,Sales!$B$2:$B$759,B286) -> 10998600 | F286: 30 | G286: =C286+F286 -> 46231 | H286: 46242 | I286: 10998600 | J286: =ROUND(E286-I286,0) -> 0 | K286: =IF(J286<=0,"Paid",IF(G286<Settings!$B$2,"Overdue","Open")) -> Paid | L286: =IF(J286>0,MAX(0,Settings!$B$2-G286),0) -> 0 | M286: =IF(J286<=0,"Paid",IF(L286=0,"Current",IF(L286<=30,"1-30",IF(L286<=60,"31-60",IF(L286<=90,"61-90","90+"))))) -> Paid
A287: INV-00286 | B287: SO-2026-0286 | C287: 46212 | D287: C002 | E287: =SUMIFS(Sales!$L$2:$L$759,Sales!$B$2:$B$759,B287) -> 9693510 | F287: 45 | G287: =C287+F287 -> 46257 | H287: 46256 | I287: 9693510 | J287: =ROUND(E287-I287,0) -> 0 | K287: =IF(J287<=0,"Paid",IF(G287<Settings!$B$2,"Overdue","Open")) -> Paid | L287: =IF(J287>0,MAX(0,Settings!$B$2-G287),0) -> 0 | M287: =IF(J287<=0,"Paid",IF(L287=0,"Current",IF(L287<=30,"1-30",IF(L287<=60,"31-60",IF(L287<=90,"61-90","90+"))))) -> Paid
A288: INV-00287 | B288: SO-2026-0287 | C288: 46217 | D288: C007 | E288: =SUMIFS(Sales!$L$2:$L$759,Sales!$B$2:$B$759,B288) -> 731700 | F288: 30 | G288: =C288+F288 -> 46247 | H288: 46246 | I288: 731700 | J288: =ROUND(E288-I288,0) -> 0 | K288: =IF(J288<=0,"Paid",IF(G288<Settings!$B$2,"Overdue","Open")) -> Paid | L288: =IF(J288>0,MAX(0,Settings!$B$2-G288),0) -> 0 | M288: =IF(J288<=0,"Paid",IF(L288=0,"Current",IF(L288<=30,"1-30",IF(L288<=60,"31-60",IF(L288<=90,"61-90","90+"))))) -> Paid
A289: INV-00288 | B289: SO-2026-0288 | C289: 46206 | D289: C002 | E289: =SUMIFS(Sales!$L$2:$L$759,Sales!$B$2:$B$759,B289) -> 10977300 | F289: 45 | G289: =C289+F289 -> 46251 | H289: 46244 | I289: 10977300 | J289: =ROUND(E289-I289,0) -> 0 | K289: =IF(J289<=0,"Paid",IF(G289<Settings!$B$2,"Overdue","Open")) -> Paid | L289: =IF(J289>0,MAX(0,Settings!$B$2-G289),0) -> 0 | M289: =IF(J289<=0,"Paid",IF(L289=0,"Current",IF(L289<=30,"1-30",IF(L289<=60,"31-60",IF(L289<=90,"61-90","90+"))))) -> Paid
A290: INV-00289 | B290: SO-2026-0289 | C290: 46217 | D290: C010 | E290: =SUMIFS(Sales!$L$2:$L$759,Sales!$B$2:$B$759,B290) -> 4605600 | F290: 30 | G290: =C290+F290 -> 46247 | H290: 46268 | I290: 4605600 | J290: =ROUND(E290-I290,0) -> 0 | K290: =IF(J290<=0,"Paid",IF(G290<Settings!$B$2,"Overdue","Open")) -> Paid | L290: =IF(J290>0,MAX(0,Settings!$B$2-G290),0) -> 0 | M290: =IF(J290<=0,"Paid",IF(L290=0,"Current",IF(L290<=30,"1-30",IF(L290<=60,"31-60",IF(L290<=90,"61-90","90+"))))) -> Paid
A291: INV-00290 | B291: SO-2026-0290 | C291: 46215 | D291: C001 | E291: =SUMIFS(Sales!$L$2:$L$759,Sales!$B$2:$B$759,B291) -> 29187200 | F291: 30 | G291: =C291+F291 -> 46245 | H291: 46271 | I291: 29187200 | J291: =ROUND(E291-I291,0) -> 0 | K291: =IF(J291<=0,"Paid",IF(G291<Settings!$B$2,"Overdue","Open")) -> Paid | L291: =IF(J291>0,MAX(0,Settings!$B$2-G291),0) -> 0 | M291: =IF(J291<=0,"Paid",IF(L291=0,"Current",IF(L291<=30,"1-30",IF(L291<=60,"31-60",IF(L291<=90,"61-90","90+"))))) -> Paid
A292: INV-00291 | B292: SO-2026-0291 | C292: 46213 | D292: C004 | E292: =SUMIFS(Sales!$L$2:$L$759,Sales!$B$2:$B$759,B292) -> 23960000 | F292: 30 | G292: =C292+F292 -> 46243 | H292: 46250 | I292: 23960000 | J292: =ROUND(E292-I292,0) -> 0 | K292: =IF(J292<=0,"Paid",IF(G292<Settings!$B$2,"Overdue","Open")) -> Paid | L292: =IF(J292>0,MAX(0,Settings!$B$2-G292),0) -> 0 | M292: =IF(J292<=0,"Paid",IF(L292=0,"Current",IF(L292<=30,"1-30",IF(L292<=60,"31-60",IF(L292<=90,"61-90","90+"))))) -> Paid
... A307: INV-00306 | B307: SO-2026-0306 | C307: 46240 | D307: C004 | E307: =SUMIFS(Sales!$L$2:$L$759,Sales!$B$2:$B$759,B307) -> 29021800 | F307: 30 | G307: =C307+F307 -> 46270 | H307: 46278 | I307: 29021800 | J307: =ROUND(E307-I307,0) -> 0 | K307: =IF(J307<=0,"Paid",IF(G307<Settings!$B$2,"Overdue","Open")) -> Paid | L307: =IF(J307>0,MAX(0,Settings!$B$2-G307),0) -> 0 | M307: =IF(J307<=0,"Paid",IF(L307=0,"Current",IF(L307<=30,"1-30",IF(L307<=60,"31-60",IF(L307<=90,"61-90","90+"))))) -> Paid
A308: INV-00307 | B308: SO-2026-0307 | C308: 46247 | D308: C003 | E308: =SUMIFS(Sales!$L$2:$L$759,Sales!$B$2:$B$759,B308) -> 26351060 | F308: 45 | G308: =C308+F308 -> 46292 | I308: 0 | J308: =ROUND(E308-I308,0) -> 26351060 | K308: =IF(J308<=0,"Paid",IF(G308<Settings!$B$2,"Overdue","Open")) -> Overdue | L308: =IF(J308>0,MAX(0,Settings!$B$2-G308),0) -> 28 | M308: =IF(J308<=0,"Paid",IF(L308=0,"Current",IF(L308<=30,"1-30",IF(L308<=60,"31-60",IF(L308<=90,"61-90","90+"))))) -> 1-30
A309: INV-00308 | B309: SO-2026-0308 | C309: 46247 | D309: C010 | E309: =SUMIFS(Sales!$L$2:$L$759,Sales!$B$2:$B$759,B309) -> 16599236 | F309: 30 | G309: =C309+F309 -> 46277 | H309: 46288 | I309: 14594984 | J309: =ROUND(E309-I309,0) -> 2004252 | K309: =IF(J309<=0,"Paid",IF(G309<Settings!$B$2,"Overdue","Open")) -> Overdue | L309: =IF(J309>0,MAX(0,Settings!$B$2-G309),0) -> 43 | M309: =IF(J309<=0,"Paid",IF(L309=0,"Current",IF(L309<=30,"1-30",IF(L309<=60,"31-60",IF(L309<=90,"61-90","90+"))))) -> 31-60
A310: INV-00309 | B310: SO-2026-0309 | C310: 46252 | D310: C007 | E310: =SUMIFS(Sales!$L$2:$L$759,Sales!$B$2:$B$759,B310) -> 14414800 | F310: 30 | G310: =C310+F310 -> 46282 | H310: 46301 | I310: 14414800 | J310: =ROUND(E310-I310,0) -> 0 | K310: =IF(J310<=0,"Paid",IF(G310<Settings!$B$2,"Overdue","Open")) -> Paid | L310: =IF(J310>0,MAX(0,Settings!$B$2-G310),0) -> 0 | M310: =IF(J310<=0,"Paid",IF(L310=0,"Current",IF(L310<=30,"1-30",IF(L310<=60,"31-60",IF(L310<=90,"61-90","90+"))))) -> Paid
A311: INV-00310 | B311: SO-2026-0310 | C311: 46252 | D311: C005 | E311: =SUMIFS(Sales!$L$2:$L$759,Sales!$B$2:$B$759,B311) -> 8515800 | F311: 60 | G311: =C311+F311 -> 46312 | H311: 46320 | I311: 8515800 | J311: =ROUND(E311-I311,0) -> 0 | K311: =IF(J311<=0,"Paid",IF(G311<Settings!$B$2,"Overdue","Open")) -> Paid | L311: =IF(J311>0,MAX(0,Settings!$B$2-G311),0) -> 0 | M311: =IF(J311<=0,"Paid",IF(L311=0,"Current",IF(L311<=30,"1-30",IF(L311<=60,"31-60",IF(L311<=90,"61-90","90+"))))) -> Paid
A312: INV-00311 | B312: SO-2026-0311 | C312: 46242 | D312: C005 | E312: =SUMIFS(Sales!$L$2:$L$759,Sales!$B$2:$B$759,B312) -> 27956380 | F312: 60 | G312: =C312+F312 -> 46302 | H312: 46300 | I312: 27956380 | J312: =ROUND(E312-I312,0) -> 0 | K312: =IF(J312<=0,"Paid",IF(G312<Settings!$B$2,"Overdue","Open")) -> Paid | L312: =IF(J312>0,MAX(0,Settings!$B$2-G312),0) -> 0 | M312: =IF(J312<=0,"Paid",IF(L312=0,"Current",IF(L312<=30,"1-30",IF(L312<=60,"31-60",IF(L312<=90,"61-90","90+"))))) -> Paid
A313: INV-00312 | B313: SO-2026-0312 | C313: 46244 | D313: C002 | E313: =SUMIFS(Sales!$L$2:$L$759,Sales!$B$2:$B$759,B313) -> 5391532 | F313: 45 | G313: =C313+F313 -> 46289 | H313: 46280 | I313: 5391532 | J313: =ROUND(E313-I313,0) -> 0 | K313: =IF(J313<=0,"Paid",IF(G313<Settings!$B$2,"Overdue","Open")) -> Paid | L313: =IF(J313>0,MAX(0,Settings!$B$2-G313),0) -> 0 | M313: =IF(J313<=0,"Paid",IF(L313=0,"Current",IF(L313<=30,"1-30",IF(L313<=60,"31-60",IF(L313<=90,"61-90","90+"))))) -> Paid
A314: INV-00313 | B314: SO-2026-0313 | C314: 46247 | D314: C002 | E314: =SUMIFS(Sales!$L$2:$L$759,Sales!$B$2:$B$759,B314) -> 8513556 | F314: 45 | G314: =C314+F314 -> 46292 | H314: 46279 | I314: 8513556 | J314: =ROUND(E314-I314,0) -> 0 | K314: =IF(J314<=0,"Paid",IF(G314<Settings!$B$2,"Overdue","Open")) -> Paid | L314: =IF(J314>0,MAX(0,Settings!$B$2-G314),0) -> 0 | M314: =IF(J314<=0,"Paid",IF(L314=0,"Current",IF(L314<=30,"1-30",IF(L314<=60,"31-60",IF(L314<=90,"61-90","90+"))))) -> Paid
A315: INV-00314 | B315: SO-2026-0314 | C315: 46261 | D315: C001 | E315: =SUMIFS(Sales!$L$2:$L$759,Sales!$B$2:$B$759,B315) -> 8289800 | F315: 30 | G315: =C315+F315 -> 46291 | H315: 46291 | I315: 6025927.1 | J315: =ROUND(E315-I315,0) -> 2263873 | K315: =IF(J315<=0,"Paid",IF(G315<Settings!$B$2,"Overdue","Open")) -> Overdue | L315: =IF(J315>0,MAX(0,Settings!$B$2-G315),0) -> 29 | M315: =IF(J315<=0,"Paid",IF(L315=0,"Current",IF(L315<=30,"1-30",IF(L315<=60,"31-60",IF(L315<=90,"61-90","90+"))))) -> 1-30
A316: INV-00315 | B316: SO-2026-0315 | C316: 46255 | D316: C002 | E316: =SUMIFS(Sales!$L$2:$L$759,Sales!$B$2:$B$759,B316) -> 13664760 | F316: 45 | G316: =C316+F316 -> 46300 | H316: 46297 | I316: 13664760 | J316: =ROUND(E316-I316,0) -> 0 | K316: =IF(J316<=0,"Paid",IF(G316<Settings!$B$2,"Overdue","Open")) -> Paid | L316: =IF(J316>0,MAX(0,Settings!$B$2-G316),0) -> 0 | M316: =IF(J316<=0,"Paid",IF(L316=0,"Current",IF(L316<=30,"1-30",IF(L316<=60,"31-60",IF(L316<=90,"61-90","90+"))))) -> Paid
A317: INV-00316 | B317: SO-2026-0316 | C317: 46245 | D317: C003 | E317: =SUMIFS(Sales!$L$2:$L$759,Sales!$B$2:$B$759,B317) -> 12572545 | F317: 45 | G317: =C317+F317 -> 46290 | H317: 46304 | I317: 12572545 | J317: =ROUND(E317-I317,0) -> 0 | K317: =IF(J317<=0,"Paid",IF(G317<Settings!$B$2,"Overdue","Open")) -> Paid | L317: =IF(J317>0,MAX(0,Settings!$B$2-G317),0) -> 0 | M317: =IF(J317<=0,"Paid",IF(L317=0,"Current",IF(L317<=30,"1-30",IF(L317<=60,"31-60",IF(L317<=90,"61-90","90+"))))) -> Paid
A318: INV-00317 | B318: SO-2026-0317 | C318: 46264 | D318: C008 | E318: =SUMIFS(Sales!$L$2:$L$759,Sales!$B$2:$B$759,B318) -> 17604752 | F318: 60 | G318: =C318+F318 -> 46324 | I318: 0 | J318: =ROUND(E318-I318,0) -> 17604752 | K318: =IF(J318<=0,"Paid",IF(G318<Settings!$B$2,"Overdue","Open")) -> Open | L318: =IF(J318>0,MAX(0,Settings!$B$2-G318),0) -> 0 | M318: =IF(J318<=0,"Paid",IF(L318=0,"Current",IF(L318<=30,"1-30",IF(L318<=60,"31-60",IF(L318<=90,"61-90","90+"))))) -> Current
A319: INV-00318 | B319: SO-2026-0318 | C319: 46262 | D319: C005 | E319: =SUMIFS(Sales!$L$2:$L$759,Sales!$B$2:$B$759,B319) -> 3447052 | F319: 60 | G319: =C319+F319 -> 46322 | H319: 46320 | I319: 3447052 | J319: =ROUND(E319-I319,0) -> 0 | K319: =IF(J319<=0,"Paid",IF(G319<Settings!$B$2,"Overdue","Open")) -> Paid | L319: =IF(J319>0,MAX(0,Settings!$B$2-G319),0) -> 0 | M319: =IF(J319<=0,"Paid",IF(L319=0,"Current",IF(L319<=30,"1-30",IF(L319<=60,"31-60",IF(L319<=90,"61-90","90+"))))) -> Paid
A320: INV-00319 | B320: SO-2026-0319 | C320: 46266 | D320: C006 | E320: =SUMIFS(Sales!$L$2:$L$759,Sales!$B$2:$B$759,B320) -> 14827220 | F320: 45 | G320: =C320+F320 -> 46311 | I320: 0 | J320: =ROUND(E320-I320,0) -> 14827220 | K320: =IF(J320<=0,"Paid",IF(G320<Settings!$B$2,"Overdue","Open")) -> Overdue | L320: =IF(J320>0,MAX(0,Settings!$B$2-G320),0) -> 9 | M320: =IF(J320<=0,"Paid",IF(L320=0,"Current",IF(L320<=30,"1-30",IF(L320<=60,"31-60",IF(L320<=90,"61-90","90+"))))) -> 1-30
A321: INV-00320 | B321: SO-2026-0320 | C321: 46263 | D321: C004 | E321: =SUMIFS(Sales!$L$2:$L$759,Sales!$B$2:$B$759,B321) -> 2209900 | F321: 30 | G321: =C321+F321 -> 46293 | H321: 46316 | I321: 2209900 | J321: =ROUND(E321-I321,0) -> 0 | K321: =IF(J321<=0,"Paid",IF(G321<Settings!$B$2,"Overdue","Open")) -> Paid | L321: =IF(J321>0,MAX(0,Settings!$B$2-G321),0) -> 0 | M321: =IF(J321<=0,"Paid",IF(L321=0,"Current",IF(L321<=30,"1-30",IF(L321<=60,"31-60",IF(L321<=90,"61-90","90+"))))) -> Paid
A322: INV-00321 | B322: SO-2026-0321 | C322: 46264 | D322: C002 | E322: =SUMIFS(Sales!$L$2:$L$759,Sales!$B$2:$B$759,B322) -> 15958966 | F322: 45 | G322: =C322+F322 -> 46309 | H322: 46310 | I322: 15958966 | J322: =ROUND(E322-I322,0) -> 0 | K322: =IF(J322<=0,"Paid",IF(G322<Settings!$B$2,"Overdue","Open")) -> Paid | L322: =IF(J322>0,MAX(0,Settings!$B$2-G322),0) -> 0 | M322: =IF(J322<=0,"Paid",IF(L322=0,"Current",IF(L322<=30,"1-30",IF(L322<=60,"31-60",IF(L322<=90,"61-90","90+"))))) -> Paid
A323: INV-00322 | B323: SO-2026-0322 | C323: 46255 | D323: C005 | E323: =SUMIFS(Sales!$L$2:$L$759,Sales!$B$2:$B$759,B323) -> 3283200 | F323: 60 | G323: =C323+F323 -> 46315 | I323: 0 | J323: =ROUND(E323-I323,0) -> 3283200 | K323: =IF(J323<=0,"Paid",IF(G323<Settings!$B$2,"Overdue","Open")) -> Overdue | L323: =IF(J323>0,MAX(0,Settings!$B$2-G323),0) -> 5 | M323: =IF(J323<=0,"Paid",IF(L323=0,"Current",IF(L323<=30,"1-30",IF(L323<=60,"31-60",IF(L323<=90,"61-90","90+"))))) -> 1-30
...

Sheet Expenses
A1: Month | B1: Category | C1: Cost Centre | D1: Amount
A2: 45658 | B2: Payroll | C2: Workshop | D2: 15741000
A3: 45658 | B3: Payroll | C3: Sales & Admin | D3: 7895000
A4: 45658 | B4: Utilities & Fuel | C4: Workshop | D4: 4418000
A5: 45658 | B5: Equipment Maintenance | C5: Workshop | D5: 4603000
A6: 45658 | B6: Logistics & Transport | C6: Sales & Admin | D6: 4606000
A7: 45658 | B7: Insurance & Compliance | C7: Management | D7: 2797000
A8: 45658 | B8: Admin & Overheads | C8: Sales & Admin | D8: 6539000
A9: 45689 | B9: Payroll | C9: Workshop | D9: 12420000
A10: 45689 | B10: Payroll | C10: Sales & Admin | D10: 5482000
A11: 45689 | B11: Utilities & Fuel | C11: Workshop | D11: 3634000
A12: 45689 | B12: Equipment Maintenance | C12: Workshop | D12: 3623000
A13: 45689 | B13: Logistics & Transport | C13: Sales & Admin | D13: 3446000
... A155: 46296 | B155: Admin & Overheads | C155: Sales & Admin | D155: 7432000
